Workbook
Name \A: #REF!
Name \A: #REF!
Name \E: #REF!
Name \E: #REF!
Name \L: #REF!
Name \L: #REF!
Name \S: #REF!
Name \S: #REF!
Name __cii2: [1]CII!$C$3:$Q$316
Name __dov01: '[2]tsy summary'!$U$151
Name __dur10: '[3]Treasury Yields'!$H$14
Name __dur2: '[2]tsy summary'!$H$20
Name __dur3: '[2]tsy summary'!$H$21
Name __dur4: '[2]tsy summary'!$H$23
Name __dur5: '[2]tsy summary'!$H$26
Name __Num10: '[4]Maturing Loans'!$A$1
Name __Num11: '[4]Macro-Level Slowdown'!$A$1
Name __Num12: '[4]Interest Rate Risk'!$A$1
Name __Num13: '[4]Position by State'!$A$1
Name __Num14: '[4]Position by Type'!$A$1
Name __Num15: '[4]Position by LTV'!$A$1
Name __Num16: '[4]Top Ten Commitments'!$A$1
Name __Num17: [4]Requests!$A$1
Name __Num2: '[4]Table of Contents'!$A$1
Name __Num21: '[4]Position by DSCR'!$A$1
Name __Num22: '[4]Position by DSCR'!$A$1
Name __Num5: '[4]Security History'!$A$1
Name __Num6: '[4]Risk Rating'!$A$1
Name __Num7: [4]Watchlist!$A$1
Name __Num8: [4]Delinquency!$A$1
Name __Num9: [4]Pipeline!$A$1
Name __prc10: '[3]Treasury Yields'!$G$14
Name __prc2: '[2]tsy summary'!$G$20
Name __prc3: '[2]tsy summary'!$G$21
Name __prc4: '[2]tsy summary'!$G$23
Name __prc5: '[2]tsy summary'!$G$26
Name __TSY15: '[2]tsy summary'!$C$13
Name __TSY16: '[5]tsy summary'!$C$14
Name __TSY25: '[5]tsy summary'!$C$16
Name _100_0G_A1: #REF!
Name _100_0G_A1: #REF!
Name _104_0HBG: #REF!
Name _104_0HBG: #REF!
Name _108_0INST: #REF!
Name _108_0INST: #REF!
Name _112_0TOT: #REF!
Name _112_0TOT: #REF!
Name _116_9_0FACTO: #REF!
Name _116_9_0FACTO: #REF!
Name _12_0H: #REF!
Name _12_0H: #REF!
Name _120L_0CDG: #REF!
Name _120L_0CDG: #REF!
Name _124L_0ERASE: #REF!
Name _124L_0ERASE: #REF!
Name _128Y_0CDG: #REF!
Name _128Y_0CDG: #REF!
Name _132Y_0ERASE: #REF!
Name _132Y_0ERASE: #REF!
Name _16_0CSG: #REF!

Sheet Checklist
A1: Cash Entries Signoff | B1: 202511
E3: Prepare | G3: Review
E4: Date | F4: Preparer | G4: Date | H4: Reviewer | I4: OPEN
A5: 45964 | B5: ="DC"&TEXT(A5,"mm")&TEXT(A5,"dd")&RIGHT(YEAR(A5),2)&1 -> DC1103251 | C5: ="Cash Activity "&TEXT(A5,"m")&"-"&TEXT(A5,"d") -> Cash Activity 11-3 | D5: ="Cash Entries "&TEXT(A5,"m")&"-"&TEXT(A5,"d") -> Cash Entries 11-3 | E5: 45966 | F5: AP | G5: 45966 | H5: BJJ
A6: =WORKDAY.INTL(A5,1,"0000011") -> 45965 | B6: ="DC"&TEXT(A6,"mm")&TEXT(A6,"dd")&RIGHT(YEAR(A6),2)&1 -> DC1104251 | C6: ="Cash Activity "&TEXT(A6,"m")&"-"&TEXT(A6,"d") -> Cash Activity 11-4 | D6: ="Cash Entries "&TEXT(A6,"m")&"-"&TEXT(A6,"d") -> Cash Entries 11-4 | E6: 45966 | F6: AP | G6: 45966 | H6: BJJ | I6: Incorrect advance wire – refund expected | J6: IMA Check
A7: =WORKDAY.INTL(A6,1,"0000011") -> 45966 | B7: ="DC"&TEXT(A7,"mm")&TEXT(A7,"dd")&RIGHT(YEAR(A7),2)&1 -> DC1105251 | C7: ="Cash Activity "&TEXT(A7,"m")&"-"&TEXT(A7,"d") -> Cash Activity 11-5 | D7: ="Cash Entries "&TEXT(A7,"m")&"-"&TEXT(A7,"d") -> Cash Entries 11-5 | E7: 45968 | F7: AP | G7: 45968 | H7: BJJ
A8: =WORKDAY.INTL(A7,1,"0000011") -> 45967 | B8: ="DC"&TEXT(A8,"mm")&TEXT(A8,"dd")&RIGHT(YEAR(A8),2)&1 -> DC1106251 | C8: ="Cash Activity "&TEXT(A8,"m")&"-"&TEXT(A8,"d") -> Cash Activity 11-6 | D8: ="Cash Entries "&TEXT(A8,"m")&"-"&TEXT(A8,"d") -> Cash Entries 11-6 | E8: 45968 | F8: AP | G8: 45968 | H8: BJJ | I8: Check Deposited Return - DG - Effingham IL; Unnamed remits
A9: =WORKDAY.INTL(A8,1,"0000011") -> 45968 | B9: ="DC"&TEXT(A10,"mm")&TEXT(A10,"dd")&RIGHT(YEAR(A10),2)&1 -> DC1110251 | C9: ="Cash Activity "&TEXT(A10,"m")&"-"&TEXT(A10,"d") -> Cash Activity 11-10 | D9: ="Cash Entries "&TEXT(A10,"m")&"-"&TEXT(A10,"d") -> Cash Entries 11-10 | E9: 45973 | F9: AP | G9: 45979 | H9: BJJ
A10: =WORKDAY.INTL(A9,1,"0000011") -> 45971 | B10: ="DC"&TEXT(A9,"mm")&TEXT(A9,"dd")&RIGHT(YEAR(A9),2)&1 -> DC1107251 | C10: ="Cash Activity "&TEXT(A9,"m")&"-"&TEXT(A9,"d") -> Cash Activity 11-7 | D10: ="Cash Entries "&TEXT(A9,"m")&"-"&TEXT(A9,"d") -> Cash Entries 11-7 | E10: 45973 | F10: AP | G10: 45979 | H10: BJJ
A11: 45973 | B11: ="DC"&TEXT(A11,"mm")&TEXT(A11,"dd")&RIGHT(YEAR(A11),2)&1 -> DC1112251 | C11: ="Cash Activity "&TEXT(A11,"m")&"-"&TEXT(A11,"d") -> Cash Activity 11-12 | D11: ="Cash Entries "&TEXT(A11,"m")&"-"&TEXT(A11,"d") -> Cash Entries 11-12 | E11: 45978 | F11: AP | G11: 45979 | H11: BJJ
A12: =WORKDAY.INTL(A11,1,"0000011") -> 45974 | B12: ="DC"&TEXT(A12,"mm")&TEXT(A12,"dd")&RIGHT(YEAR(A12),2)&1 -> DC1113251 | C12: ="Cash Activity "&TEXT(A12,"m")&"-"&TEXT(A12,"d") -> Cash Activity 11-13 | D12: ="Cash Entries "&TEXT(A12,"m")&"-"&TEXT(A12,"d") -> Cash Entries 11-13 | E12: 45978 | F12: AP | G12: 45979 | H12: BJJ
A13: =WORKDAY.INTL(A12,1,"0000011") -> 45975 | B13: ="DC"&TEXT(A13,"mm")&TEXT(A13,"dd")&RIGHT(YEAR(A13),2)&1 -> DC1114251 | C13: ="Cash Activity "&TEXT(A13,"m")&"-"&TEXT(A13,"d") -> Cash Activity 11-14 | D13: ="Cash Entries "&TEXT(A13,"m")&"-"&TEXT(A13,"d") -> Cash Entries 11-14 | E13: 45978 | F13: AP | G13: 45979 | H13: BJJ
A14: =WORKDAY.INTL(A13,1,"0000011") -> 45978 | B14: ="DC"&TEXT(A14,"mm")&TEXT(A14,"dd")&RIGHT(YEAR(A14),2)&1 -> DC1117251 | C14: ="Cash Activity "&TEXT(A14,"m")&"-"&TEXT(A14,"d") -> Cash Activity 11-17 | D14: ="Cash Entries "&TEXT(A14,"m")&"-"&TEXT(A14,"d") -> Cash Entries 11-17 | E14: 45979 | F14: AP | G14: 45979 | H14: BJJ
A15: =WORKDAY.INTL(A14,1,"0000011") -> 45979 | B15: ="DC"&TEXT(A15,"mm")&TEXT(A15,"dd")&RIGHT(YEAR(A15),2)&1 -> DC1118251 | C15: ="Cash Activity "&TEXT(A15,"m")&"-"&TEXT(A15,"d") -> Cash Activity 11-18 | D15: ="Cash Entries "&TEXT(A15,"m")&"-"&TEXT(A15,"d") -> Cash Entries 11-18 | E15: 45982 | F15: AP
A16: =WORKDAY.INTL(A15,1,"0000011") -> 45980 | B16: ="DC"&TEXT(A16,"mm")&TEXT(A16,"dd")&RIGHT(YEAR(A16),2)&1 -> DC1119251 | C16: ="Cash Activity "&TEXT(A16,"m")&"-"&TEXT(A16,"d") -> Cash Activity 11-19 | D16: ="Cash Entries "&TEXT(A16,"m")&"-"&TEXT(A16,"d") -> Cash Entries 11-19 | E16: 45982 | F16: AP
A17: =WORKDAY.INTL(A16,1,"0000011") -> 45981 | B17: ="DC"&TEXT(A17,"mm")&TEXT(A17,"dd")&RIGHT(YEAR(A17),2)&1 -> DC1120251 | C17: ="Cash Activity "&TEXT(A17,"m")&"-"&TEXT(A17,"d") -> Cash Activity 11-20 | D17: ="Cash Entries "&TEXT(A17,"m")&"-"&TEXT(A17,"d") -> Cash Entries 11-20 | E17: 45982 | F17: AP
A18: =WORKDAY.INTL(A17,1,"0000011") -> 45982 | B18: ="DC"&TEXT(A18,"mm")&TEXT(A18,"dd")&RIGHT(YEAR(A18),2)&1 -> DC1121251 | C18: ="Cash Activity "&TEXT(A18,"m")&"-"&TEXT(A18,"d") -> Cash Activity 11-21 | D18: ="Cash Entries "&TEXT(A18,"m")&"-"&TEXT(A18,"d") -> Cash Entries 11-21
A19: =WORKDAY.INTL(A18,1,"0000011") -> 45985 | B19: ="DC"&TEXT(A19,"mm")&TEXT(A19,"dd")&RIGHT(YEAR(A19),2)&1 -> DC1124251 | C19: ="Cash Activity "&TEXT(A19,"m")&"-"&TEXT(A19,"d") -> Cash Activity 11-24 | D19: ="Cash Entries "&TEXT(A19,"m")&"-"&TEXT(A19,"d") -> Cash Entries 11-24
A20: =WORKDAY.INTL(A19,1,"0000011") -> 45986 | B20: ="DC"&TEXT(A20,"mm")&TEXT(A20,"dd")&RIGHT(YEAR(A20),2)&1 -> DC1125251 | C20: ="Cash Activity "&TEXT(A20,"m")&"-"&TEXT(A20,"d") -> Cash Activity 11-25 | D20: ="Cash Entries "&TEXT(A20,"m")&"-"&TEXT(A20,"d") -> Cash Entries 11-25
A21: =WORKDAY.INTL(A20,1,"0000011") -> 45987 | B21: ="DC"&TEXT(A21,"mm")&TEXT(A21,"dd")&RIGHT(YEAR(A21),2)&1 -> DC1126251 | C21: ="Cash Activity "&TEXT(A21,"m")&"-"&TEXT(A21,"d") -> Cash Activity 11-26 | D21: ="Cash Entries "&TEXT(A21,"m")&"-"&TEXT(A21,"d") -> Cash Entries 11-26
A22: =WORKDAY.INTL(A21,1,"0000011") -> 45988 | B22: ="DC"&TEXT(A22,"mm")&TEXT(A22,"dd")&RIGHT(YEAR(A22),2)&1 -> DC1127251 | C22: ="Cash Activity "&TEXT(A22,"m")&"-"&TEXT(A22,"d") -> Cash Activity 11-27 | D22: ="Cash Entries "&TEXT(A22,"m")&"-"&TEXT(A22,"d") -> Cash Entries 11-27
A23: =WORKDAY.INTL(A22,1,"0000011") -> 45989 | B23: ="DC"&TEXT(A23,"mm")&TEXT(A23,"dd")&RIGHT(YEAR(A23),2)&1 -> DC1128251 | C23: ="Cash Activity "&TEXT(A23,"m")&"-"&TEXT(A23,"d") -> Cash Activity 11-28 | D23: ="Cash Entries "&TEXT(A23,"m")&"-"&TEXT(A23,"d") -> Cash Entries 11-28

Sheet Cash Activity 11-3
A1: ="Daily Bank Activity - "&MONTH(Checklist!A5)&"/"&DAY(Checklist!A5)&"/"&YEAR(Checklist!A5) -> Daily Bank Activity - 11/3/2025
A2: Credit (+) / Debit (-)
B4: # | C4: Bank | D4: Acct Name | E4: Acct # | F4: Date | G4: Type | H4: Amount | I4: Bank Ref | J4: Bank Stmt Description | K4: Trans Type | L4: Entity | M4: AIT | N4: Short Description | O4: GL Account 1 | P4: GL Account 2 | Q4: Posted?
B5: 1 | C5: PNC | D5: LCFH REIT | E5: 8026459924 | F5: 45964 | G5: CR | H5: 803.27 | I5: '00000000000 | J5: PNC SWEEP INTEREST @ 0.000000 EFFECTIVE DATE 10-31 | K5: =IF(ISNUMBER(SEARCH("Manual Payment - ",N5,1)),"AP",IF(ISNUMBER(SEARCH("Payment - Concur",N5,1)),"WDL",IF(ISNUMBER(SEARCH("Payroll Transfer",N5,1)),"XFR",IF(ISNUMBER(SEARCH("XFR",N5,1)),"XFR",IF(H5>0,"RCT","WDL"))))) -> RCT | L5: =VLOOKUP(D5,'Entity Code'!A:B,2,0) -> LCFHR | N5: Overnight interest sweep PNC LCFHR account. No entry required | O5: N/A | P5: N/A | Q5: N/A
B6: 2 | C6: PNC | D6: LCFH REIT | E6: 8026459924 | F6: 45964 | G6: CR | H6: 3102567.1 | I6: '00000000000 | J6: SWEEP TRANSFR FROM INVESTMENT ACCT 8026459924 | K6: =IF(ISNUMBER(SEARCH("Manual Payment - ",N6,1)),"AP",IF(ISNUMBER(SEARCH("Payment - Concur",N6,1)),"WDL",IF(ISNUMBER(SEARCH("Payroll Transfer",N6,1)),"XFR",IF(ISNUMBER(SEARCH("XFR",N6,1)),"XFR",IF(H6>0,"RCT","WDL"))))) -> RCT | L6: =VLOOKUP(D6,'Entity Code'!A:B,2,0) -> LCFHR | N6: Overnight interest sweep PNC LCFHR account. No entry required | O6: N/A | P6: N/A | Q6: N/A
B7: 3 | C7: PNC | D7: LCFH REIT | E7: 8026459924 | F7: 45964 | G7: DR | H7: -2452621.7 | I7: '00000000000 | J7: SWEEP TO INVESTMENT ACCT# 8026459924 | K7: =IF(ISNUMBER(SEARCH("Manual Payment - ",N7,1)),"AP",IF(ISNUMBER(SEARCH("Payment - Concur",N7,1)),"WDL",IF(ISNUMBER(SEARCH("Payroll Transfer",N7,1)),"XFR",IF(ISNUMBER(SEARCH("XFR",N7,1)),"XFR",IF(H7>0,"RCT","WDL"))))) -> WDL | L7: =VLOOKUP(D7,'Entity Code'!A:B,2,0) -> LCFHR | N7: Overnight interest sweep PNC LCFHR account. No entry required | O7: N/A | P7: N/A | Q7: N/A
B8: 4 | C8: PNC | D8: LCFH REIT | E8: 8026459924 | F8: 45964 | G8: DR | H8: -8025016.7 | I8: 'PAB3C462791H04W8 | J8: WIRE TRANSFER ISO AMT:USD 8025016.67 STTLMT DATE:1 | K8: =IF(ISNUMBER(SEARCH("Manual Payment - ",N8,1)),"AP",IF(ISNUMBER(SEARCH("Payment - Concur",N8,1)),"WDL",IF(ISNUMBER(SEARCH("Payroll Transfer",N8,1)),"XFR",IF(ISNUMBER(SEARCH("XFR",N8,1)),"XFR",IF(H8>0,"RCT","WDL"))))) -> WDL | L8: =VLOOKUP(D8,'Entity Code'!A:B,2,0) -> LCFHR | N8: SocGen Paydown | O8: 2701-CAMR-000 | P8: N/A | Q8: SS&C to post
B9: 5 | C9: PNC | D9: LCR 3 | E9: 8026496047 | F9: 45964 | G9: DR | H9: -182796.41 | I9: 'PAB3E3959A6H22KU | J9: WIRE TRANSFER ISO AMT:USD 182796.41 STTLMT DATE:11 | K9: =IF(ISNUMBER(SEARCH("Manual Payment - ",N9,1)),"AP",IF(ISNUMBER(SEARCH("Payment - Concur",N9,1)),"WDL",IF(ISNUMBER(SEARCH("Payroll Transfer",N9,1)),"XFR",IF(ISNUMBER(SEARCH("XFR",N9,1)),"XFR",IF(H9>0,"RCT","WDL"))))) -> WDL | L9: =VLOOKUP(D9,'Entity Code'!A:B,2,0) -> LCR3 | N9: Central Florida Resource Center - Future Funding Advance #1 | O9: 2701-LMS0-000 | P9: N/A | Q9: SS&C to post
B10: 6 | C10: PNC | D10: LCC | E10: 8026482868 | F10: 45964 | G10: DR | H10: -52732 | I10: 'PAB3C46274QI23NZ | J10: WIRE TRANSFER ISO AMT:USD 52732.00 STTLMT DATE:110 | K10: =IF(ISNUMBER(SEARCH("Manual Payment - ",N10,1)),"AP",IF(ISNUMBER(SEARCH("Payment - Concur",N10,1)),"WDL",IF(ISNUMBER(SEARCH("Payroll Transfer",N10,1)),"XFR",IF(ISNUMBER(SEARCH("XFR",N10,1)),"XFR",IF(H10>0,"RCT","WDL"))))) -> WDL | L10: =VLOOKUP(D10,'Entity Code'!A:B,2,0) -> LCC | N10: Stock Repurchase | O10: LCC -3595-0000-000- | P10: N/A | Q10: SS&C to post
B11: 7 | C11: JPM | D11: LADDER CAPITAL FINANCE LLC OPERATIN | E11: 865357602 | F11: 45964 | G11: Debit | H11: -7588.75 | I11: 6825200307JO | J11: FEDWIRE DEBIT | K11: =IF(ISNUMBER(SEARCH("Manual Payment - ",N11,1)),"AP",IF(ISNUMBER(SEARCH("Payment - Concur",N11,1)),"WDL",IF(ISNUMBER(SEARCH("Payroll Transfer",N11,1)),"XFR",IF(ISNUMBER(SEARCH("XFR",N11,1)),"XFR",IF(H11>0,"RCT","WDL"))))) -> AP | L11: =VLOOKUP(D11,'Entity Code'!A:B,2,0) -> LCF | N11: Manual Payment - IT Consultant Agreement | O11: N/A | P11: N/A | Q11: Ladder to post
B12: 8 | C12: PNC | D12: Ladder Capital Finance | E12: 8026459916 | F12: 45964 | G12: CR | H12: 0.03 | I12: '00000000000 | J12: INTEREST ADJUSTMENT CREDIT EFFECTIVE DATE 10-31-25 | K12: =IF(ISNUMBER(SEARCH("Manual Payment - ",N12,1)),"AP",IF(ISNUMBER(SEARCH("Payment - Concur",N12,1)),"WDL",IF(ISNUMBER(SEARCH("Payroll Transfer",N12,1)),"XFR",IF(ISNUMBER(SEARCH("XFR",N12,1)),"XFR",IF(H12>0,"RCT","WDL"))))) -> RCT | L12: =VLOOKUP(D12,'Entity Code'!A:B,2,0) -> LCF | N12: Interest Income - PNC | O12: 4101-0000-000 | P12: N/A | Q12: SS&C to post
B13: 9 | C13: PNC | D13: Tuebor TRS4 | E13: 8180060487 | F13: 45964 | G13: CR | H13: 0.03 | I13: '00000000000 | J13: INTEREST ADJUSTMENT CREDIT EFFECTIVE DATE 10-31-25 | K13: =IF(ISNUMBER(SEARCH("Manual Payment - ",N13,1)),"AP",IF(ISNUMBER(SEARCH("Payment - Concur",N13,1)),"WDL",IF(ISNUMBER(SEARCH("Payroll Transfer",N13,1)),"XFR",IF(ISNUMBER(SEARCH("XFR",N13,1)),"XFR",IF(H13>0,"RCT","WDL"))))) -> RCT | L13: =VLOOKUP(D13,'Entity Code'!A:B,2,0) -> TUET4 | N13: Interest Income - PNC | O13: 4101-0000-000 | P13: N/A | Q13: SS&C to post
B14: 10 | C14: PNC | D14: Ladder Capital Finance | E14: 8026459916 | F14: 45964 | G14: CR | H14: 737.67 | I14: '00000000000 | J14: INTEREST TRANSFER FROM 000008180452958 EFFECTIVE D | K14: =IF(ISNUMBER(SEARCH("Manual Payment - ",N14,1)),"AP",IF(ISNUMBER(SEARCH("Payment - Concur",N14,1)),"WDL",IF(ISNUMBER(SEARCH("Payroll Transfer",N14,1)),"XFR",IF(ISNUMBER(SEARCH("XFR",N14,1)),"XFR",IF(H14>0,"RCT","WDL"))))) -> RCT | L14: =VLOOKUP(D14,'Entity Code'!A:B,2,0) -> LCF | N14: Interest Income - PNC | O14: 4101-0000-000 | P14: N/A | Q14: SS&C to post
B15: 11 | C15: PNC | D15: Tuebor TRS4 | E15: 8180060487 | F15: 45964 | G15: CR | H15: 737.67 | I15: '00000000000 | J15: INTEREST TRANSFER FROM 000008180452966 EFFECTIVE D | K15: =IF(ISNUMBER(SEARCH("Manual Payment - ",N15,1)),"AP",IF(ISNUMBER(SEARCH("Payment - Concur",N15,1)),"WDL",IF(ISNUMBER(SEARCH("Payroll Transfer",N15,1)),"XFR",IF(ISNUMBER(SEARCH("XFR",N15,1)),"XFR",IF(H15>0,"RCT","WDL"))))) -> RCT | L15: =VLOOKUP(D15,'Entity Code'!A:B,2,0) -> TUET4 | N15: Interest Income - PNC | O15: 4101-0000-000 | P15: N/A | Q15: SS&C to post
B16: 12 | C16: JPM | D16: LADDER CAPITAL CRE EQUITY LLC | E16: 528280121 | F16: 45964 | G16: Credit | H16: 1260.7 | I16: 0166141307FC | J16: CHIPS CREDIT | K16: =IF(ISNUMBER(SEARCH("Manual Payment - ",N16,1)),"AP",IF(ISNUMBER(SEARCH("Payment - Concur",N16,1)),"WDL",IF(ISNUMBER(SEARCH("Payroll Transfer",N16,1)),"XFR",IF(ISNUMBER(SEARCH("XFR",N16,1)),"XFR",IF(H16>0,"RCT","WDL"))))) -> RCT | L16: =VLOOKUP(D16,'Entity Code'!A:B,2,0) -> LCREE | N16: Nov RE Remit - DGCAT | O16: LCREE-1470-0000-000-DGCAT | P16: N/A | Q16: Ladder to post
B17: 13 | C17: PNC | D17: CRE EQUITY | E17: 8026496039 | F17: 45964 | G17: CR | H17: 50833.33 | I17: '25304009889690 | J17: ACH CREDIT RECEIVED - Cust ID: 3186050 Desc: PAYME | K17: =IF(ISNUMBER(SEARCH("Manual Payment - ",N17,1)),"AP",IF(ISNUMBER(SEARCH("Payment - Concur",N17,1)),"WDL",IF(ISNUMBER(SEARCH("Payroll Transfer",N17,1)),"XFR",IF(ISNUMBER(SEARCH("XFR",N17,1)),"XFR",IF(H17>0,"RCT","WDL"))))) -> RCT | L17: =VLOOKUP(D17,'Entity Code'!A:B,2,0) -> LCREE | N17: Rental Income - ASEVA | O17: LCREE-1470-0000-000-ASEVA | P17: N/A | Q17: Ladder to post
B18: 13 | C18: PNC | D18: CRE EQUITY | E18: 8026496039 | F18: 45964 | G18: CR | H18: 36916.66 | I18: '25304008009706 | J18: ACH CREDIT RECEIVED - Cust ID: 2000384175 Desc: PA | K18: =IF(ISNUMBER(SEARCH("Manual Payment - ",N18,1)),"AP",IF(ISNUMBER(SEARCH("Payment - Concur",N18,1)),"WDL",IF(ISNUMBER(SEARCH("Payroll Transfer",N18,1)),"XFR",IF(ISNUMBER(SEARCH("XFR",N18,1)),"XFR",IF(H18>0,"RCT","WDL"))))) -> RCT | L18: =VLOOKUP(D18,'Entity Code'!A:B,2,0) -> LCREE | N18: Rental Income - LLBGA | O18: LCREE-1470-0000-000-LLBGA | P18: N/A | Q18: Ladder to post
B19: 13 | C19: PNC | D19: CRE EQUITY | E19: 8026496039 | F19: 45964 | G19: CR | H19: 33250 | I19: '25304008009768 | J19: ACH CREDIT RECEIVED - Cust ID: 2000385535 Desc: PA | K19: =IF(ISNUMBER(SEARCH("Manual Payment - ",N19,1)),"AP",IF(ISNUMBER(SEARCH("Payment - Concur",N19,1)),"WDL",IF(ISNUMBER(SEARCH("Payroll Transfer",N19,1)),"XFR",IF(ISNUMBER(SEARCH("XFR",N19,1)),"XFR",IF(H19>0,"RCT","WDL"))))) -> RCT | L19: =VLOOKUP(D19,'Entity Code'!A:B,2,0) -> LCREE | N19: Rental Income - WGHI2 | O19: LCREE-1470-0000-000-WGHI2 | P19: N/A | Q19: Ladder to post
B20: 13 | C20: PNC | D20: CRE EQUITY | E20: 8026496039 | F20: 45964 | G20: CR | H20: 27083.33 | I20: '25304008009758 | J20: ACH CREDIT RECEIVED - Cust ID: 2000385534 Desc: PA | K20: =IF(ISNUMBER(SEARCH("Manual Payment - ",N20,1)),"AP",IF(ISNUMBER(SEARCH("Payment - Concur",N20,1)),"WDL",IF(ISNUMBER(SEARCH("Payroll Transfer",N20,1)),"XFR",IF(ISNUMBER(SEARCH("XFR",N20,1)),"XFR",IF(H20>0,"RCT","WDL"))))) -> RCT | L20: =VLOOKUP(D20,'Entity Code'!A:B,2,0) -> LCREE | N20: Rental Income - WGNI2 | O20: LCREE-1470-0000-000-WGNI2 | P20: N/A | Q20: Ladder to post
B21: 14 | C21: PNC | D21: LCR 3 | E21: 8026496047 | F21: 45964 | G21: CR | H21: 16160000 | I21: '25B3H5621O900KJO | J21: WIRE TRANSFER ISO AMT:USD 16160000.00 STTLMT DATE: | K21: =IF(ISNUMBER(SEARCH("Manual Payment - ",N21,1)),"AP",IF(ISNUMBER(SEARCH("Payment - Concur",N21,1)),"WDL",IF(ISNUMBER(SEARCH("Payroll Transfer",N21,1)),"XFR",IF(ISNUMBER(SEARCH("XFR",N21,1)),"XFR",IF(H21>0,"RCT","WDL"))))) -> RCT | L21: =VLOOKUP(D21,'Entity Code'!A:B,2,0) -> LCR3 | N21: Group RMC Partial Paydown | O21: 2701-LMS0-000 | P21: N/A | Q21: SS&C to post
B22: 15 | C22: PNC | D22: LCR 3 | E22: 8026496047 | F22: 45964 | G22: CR | H22: 183000 | I22: '25B3F225304Z29WA | J22: BOOK TRANSFER CREDIT 0029WA ORIGINATOR:LADDER CAPI | K22: =IF(ISNUMBER(SEARCH("Manual Payment - ",N22,1)),"AP",IF(ISNUMBER(SEARCH("Payment - Concur",N22,1)),"WDL",IF(ISNUMBER(SEARCH("Payroll Transfer",N22,1)),"XFR",IF(ISNUMBER(SEARCH("XFR",N22,1)),"XFR",IF(H22>0,"RCT","WDL"))))) -> XFR | L22: =VLOOKUP(D22,'Entity Code'!A:B,2,0) -> LCR3 | N22: XFR from LCFHR PNC to LCR3 PNC | O22: 2701-CAMR-000 | P22: N/A | Q22: SS&C to post
B23: 15 | C23: PNC | D23: LCFH REIT | E23: 8026459924 | F23: 45964 | G23: DR | H23: -183000 | I23: '25B3F225304Z29WA | J23: BOOK TRANSFER DEBIT 0029WA ORIGINATOR:LADDER CAPIT | K23: =IF(ISNUMBER(SEARCH("Manual Payment - ",N23,1)),"AP",IF(ISNUMBER(SEARCH("Payment - Concur",N23,1)),"WDL",IF(ISNUMBER(SEARCH("Payroll Transfer",N23,1)),"XFR",IF(ISNUMBER(SEARCH("XFR",N23,1)),"XFR",IF(H23>0,"RCT","WDL"))))) -> XFR | L23: =VLOOKUP(D23,'Entity Code'!A:B,2,0) -> LCFHR | N23: XFR from LCFHR PNC to LCR3 PNC | O23: 2701-CAMR-000 | P23: N/A | Q23: SS&C to post
B24: 16 | C24: PNC | D24: LCC | E24: 8026482868 | F24: 45964 | G24: CR | H24: 52732 | I24: '25B3F2252P104G6G | J24: BOOK TRANSFER CREDIT 004G6G ORIGINATOR:LADDER CAPI | K24: =IF(ISNUMBER(SEARCH("Manual Payment - ",N24,1)),"AP",IF(ISNUMBER(SEARCH("Payment - Concur",N24,1)),"WDL",IF(ISNUMBER(SEARCH("Payroll Transfer",N24,1)),"XFR",IF(ISNUMBER(SEARCH("XFR",N24,1)),"XFR",IF(H24>0,"RCT","WDL"))))) -> XFR | L24: =VLOOKUP(D24,'Entity Code'!A:B,2,0) -> LCC | N24: XFR from LCFHR PNC to LCC | O24: 2701-CAMR-000 | P24: N/A | Q24: SS&C to post
B25: 16 | C25: PNC | D25: LCFH REIT | E25: 8026459924 | F25: 45964 | G25: DR | H25: -52732 | I25: '25B3F2252P104G6G | J25: BOOK TRANSFER DEBIT 004G6G ORIGINATOR:LADDER CAPIT | K25: =IF(ISNUMBER(SEARCH("Manual Payment - ",N25,1)),"AP",IF(ISNUMBER(SEARCH("Payment - Concur",N25,1)),"WDL",IF(ISNUMBER(SEARCH("Payroll Transfer",N25,1)),"XFR",IF(ISNUMBER(SEARCH("XFR",N25,1)),"XFR",IF(H25>0,"RCT","WDL"))))) -> XFR | L25: =VLOOKUP(D25,'Entity Code'!A:B,2,0) -> LCFHR | N25: XFR from LCFHR PNC to LCC | O25: 2701-CAMR-000 | P25: N/A | Q25: SS&C to post
B26: 17 | C26: PNC | D26: LCI | E26: 8026496012 | F26: 45964 | G26: CR | H26: 50000 | I26: '25B3F22537PZ19WC | J26: BOOK TRANSFER CREDIT 0019WC ORIGINATOR:LADDER CAPI | K26: =IF(ISNUMBER(SEARCH("Manual Payment - ",N26,1)),"AP",IF(ISNUMBER(SEARCH("Payment - Concur",N26,1)),"WDL",IF(ISNUMBER(SEARCH("Payroll Transfer",N26,1)),"XFR",IF(ISNUMBER(SEARCH("XFR",N26,1)),"XFR",IF(H26>0,"RCT","WDL"))))) -> XFR | L26: =VLOOKUP(D26,'Entity Code'!A:B,2,0) -> LCI | N26: XFR from LCFHR PNC to LCI PNC | O26: 2701-CAMR-000 | P26: N/A | Q26: SS&C to post
B27: 17 | C27: PNC | D27: LCFH REIT | E27: 8026459924 | F27: 45964 | G27: DR | H27: -50000 | I27: '25B3F22537PZ19WC | J27: BOOK TRANSFER DEBIT 0019WC ORIGINATOR:LADDER CAPIT | K27: =IF(ISNUMBER(SEARCH("Manual Payment - ",N27,1)),"AP",IF(ISNUMBER(SEARCH("Payment - Concur",N27,1)),"WDL",IF(ISNUMBER(SEARCH("Payroll Transfer",N27,1)),"XFR",IF(ISNUMBER(SEARCH("XFR",N27,1)),"XFR",IF(H27>0,"RCT","WDL"))))) -> XFR | L27: =VLOOKUP(D27,'Entity Code'!A:B,2,0) -> LCFHR | N27: XFR from LCFHR PNC to LCI PNC | O27: 2701-CAMR-000 | P27: N/A | Q27: SS&C to post
B28: 18 | C28: PNC | D28: LCI | E28: 8026496012 | F28: 45964 | G28: DR | H28: -50000 | I28: 'PAB3C46274DJ0BGR | J28: WIRE TRANSFER ISO AMT:USD 50000.00 STTLMT DATE:110 | K28: =IF(ISNUMBER(SEARCH("Manual Payment - ",N28,1)),"AP",IF(ISNUMBER(SEARCH("Payment - Concur",N28,1)),"WDL",IF(ISNUMBER(SEARCH("Payroll Transfer",N28,1)),"XFR",IF(ISNUMBER(SEARCH("XFR",N28,1)),"XFR",IF(H28>0,"RCT","WDL"))))) -> XFR | L28: =VLOOKUP(D28,'Entity Code'!A:B,2,0) -> LCI | N28: XFR from LCI PNC to LCFP Equity PB | O28: 2701-CAMR-000 | P28: N/A | Q28: SS&C to post
... B32: 21 | C32: PNC | D32: LCFH REIT | E32: 8026459924 | F32: 45964 | G32: CR | H32: 8000000 | I32: '25B3H5215MTZ08EG | J32: WIRE TRANSFER ISO STTLMT DATE:11032025 CLR SYS REF | K32: =IF(ISNUMBER(SEARCH("Manual Payment - ",N32,1)),"AP",IF(ISNUMBER(SEARCH("Payment - Concur",N32,1)),"WDL",IF(ISNUMBER(SEARCH("Payroll Transfer",N32,1)),"XFR",IF(ISNUMBER(SEARCH("XFR",N32,1)),"XFR",IF(H32>0,"RCT","WDL"))))) -> XFR | L32: =VLOOKUP(D32,'Entity Code'!A:B,2,0) -> LCFHR | N32: XFR from LCFHR BNY to LCFHR PNC | O32: 2701-CAMR-000 | P32: N/A | Q32: SS&C to post
B33: 22 | C33: JPM | D33: LADDER CAPITAL FINANCE LLC OPERATIN | E33: 865357602 | F33: 45964 | G33: Debit | H33: -1187.5 | I33: 0063500304VB | J33: FEDWIRE DEBIT | K33: =IF(ISNUMBER(SEARCH("Manual Payment - ",N33,1)),"AP",IF(ISNUMBER(SEARCH("Payment - Concur",N33,1)),"WDL",IF(ISNUMBER(SEARCH("Payroll Transfer",N33,1)),"XFR",IF(ISNUMBER(SEARCH("XFR",N33,1)),"XFR",IF(H33>0,"RCT","WDL"))))) -> AP | L33: =VLOOKUP(D33,'Entity Code'!A:B,2,0) -> LCF | N33: Manual Payment - Rosenberg & Estis | O33: N/A | P33: N/A | Q33: Ladder to post
B34: 23 | C34: JPM | D34: LADDER CAPITAL FINANCE LLC OPERATIN | E34: 865357602 | F34: 45964 | G34: Debit | H34: -8701.28 | I34: 3079172302TC | J34: EFT DEBIT | K34: =IF(ISNUMBER(SEARCH("Manual Payment - ",N34,1)),"AP",IF(ISNUMBER(SEARCH("Payment - Concur",N34,1)),"WDL",IF(ISNUMBER(SEARCH("Payroll Transfer",N34,1)),"XFR",IF(ISNUMBER(SEARCH("XFR",N34,1)),"XFR",IF(H34>0,"RCT","WDL"))))) -> AP | L34: =VLOOKUP(D34,'Entity Code'!A:B,2,0) -> LCF | N34: Manual Payment - The New West Con | O34: N/A | P34: N/A | Q34: Ladder to post
B35: 24 | C35: JPM | D35: LADDER CAPITAL FINANCE LLC OPERATIN | E35: 865357602 | F35: 45964 | G35: Debit | H35: -5935 | I35: 3079172300TC | J35: EFT DEBIT | K35: =IF(ISNUMBER(SEARCH("Manual Payment - ",N35,1)),"AP",IF(ISNUMBER(SEARCH("Payment - Concur",N35,1)),"WDL",IF(ISNUMBER(SEARCH("Payroll Transfer",N35,1)),"XFR",IF(ISNUMBER(SEARCH("XFR",N35,1)),"XFR",IF(H35>0,"RCT","WDL"))))) -> AP | L35: =VLOOKUP(D35,'Entity Code'!A:B,2,0) -> LCF | N35: Manual Payment - Industrious office | O35: N/A | P35: N/A | Q35: Ladder to post
B36: 25 | C36: JPM | D36: LADDER CAPITAL FINANCE LLC OPERATIN | E36: 865357602 | F36: 45964 | G36: Debit | H36: -191680.03 | I36: 0049100304VB | J36: BOOK TRANSFER DEBIT | K36: =IF(ISNUMBER(SEARCH("Manual Payment - ",N36,1)),"AP",IF(ISNUMBER(SEARCH("Payment - Concur",N36,1)),"WDL",IF(ISNUMBER(SEARCH("Payroll Transfer",N36,1)),"XFR",IF(ISNUMBER(SEARCH("XFR",N36,1)),"XFR",IF(H36>0,"RCT","WDL"))))) -> AP | L36: =VLOOKUP(D36,'Entity Code'!A:B,2,0) -> LCF | N36: Manual Payment - 320 Park Ave | O36: N/A | P36: N/A | Q36: Ladder to post
B37: 26 | C37: JPM | D37: LADDER CAPITAL FINANCE LLC OPERATIN | E37: 865357602 | F37: 45964 | G37: Debit | H37: -23192.55 | I37: 0049200304VB | J37: BOOK TRANSFER DEBIT | K37: =IF(ISNUMBER(SEARCH("Manual Payment - ",N37,1)),"AP",IF(ISNUMBER(SEARCH("Payment - Concur",N37,1)),"WDL",IF(ISNUMBER(SEARCH("Payroll Transfer",N37,1)),"XFR",IF(ISNUMBER(SEARCH("XFR",N37,1)),"XFR",IF(H37>0,"RCT","WDL"))))) -> AP | L37: =VLOOKUP(D37,'Entity Code'!A:B,2,0) -> LCF | N37: Manual Payment - AMEX | O37: N/A | P37: N/A | Q37: Ladder to post

Sheet Cash Entries 11-3
A1: ENTITY | B1: YEARMONTH | C1: SOURCE | D1: BATCH ID | E1: BATCH DESCRIPTION | F1: BATCHDATE | G1: DR_AMT | H1: CR AMT | I1: TRXDATE | J1: DIST REFERENCE | K1: GPACCT
A2: LCREE | B2: =Checklist!$B$1 -> 202511 | C2: GJ | D2: =Checklist!$B$5 -> DC1103251 | E2: =D2 -> DC1103251 | F2: =Checklist!$A$5 -> 45964 | G2: 1260.7 | H2: 0 | I2: =$F$2 -> 45964 | J2: Nov RE Remit - DGCAT | K2: LCREE-1043-0000-000-
A3: LCREE | B3: =Checklist!$B$1 -> 202511 | C3: GJ | D3: =D2 -> DC1103251 | E3: =D3 -> DC1103251 | F3: =$F$2 -> 45964 | G3: 0 | H3: 1260.7 | I3: =$F$2 -> 45964 | J3: Nov RE Remit - DGCAT | K3: LCREE-1470-0000-000-DGCAT
A4: LCREE | B4: =Checklist!$B$1 -> 202511 | C4: GJ | D4: =D3 -> DC1103251 | E4: =D4 -> DC1103251 | F4: =$F$2 -> 45964 | G4: 50833.33 | H4: 0 | I4: =$F$2 -> 45964 | J4: Rental Income - ASEVA | K4: LCREE-1065-0008-000-
A5: LCREE | B5: =Checklist!$B$1 -> 202511 | C5: GJ | D5: =D4 -> DC1103251 | E5: =D5 -> DC1103251 | F5: =$F$2 -> 45964 | G5: 0 | H5: 50833.33 | I5: =$F$2 -> 45964 | J5: Rental Income - ASEVA | K5: LCREE-1470-0000-000-ASEVA
A6: LCREE | B6: =Checklist!$B$1 -> 202511 | C6: GJ | D6: =D5 -> DC1103251 | E6: =D6 -> DC1103251 | F6: =$F$2 -> 45964 | G6: 36916.66 | H6: 0 | I6: =$F$2 -> 45964 | J6: Rental Income - LLBGA | K6: LCREE-1065-0008-000-
A7: LCREE | B7: =Checklist!$B$1 -> 202511 | C7: GJ | D7: =D6 -> DC1103251 | E7: =D7 -> DC1103251 | F7: =$F$2 -> 45964 | G7: 0 | H7: 36916.66 | I7: =$F$2 -> 45964 | J7: Rental Income - LLBGA | K7: LCREE-1470-0000-000-LLBGA
A8: LCREE | B8: =Checklist!$B$1 -> 202511 | C8: GJ | D8: =D7 -> DC1103251 | E8: =D8 -> DC1103251 | F8: =$F$2 -> 45964 | G8: 33250 | H8: 0 | I8: =$F$2 -> 45964 | J8: Rental Income - WGHI2 | K8: LCREE-1065-0008-000-
A9: LCREE | B9: =Checklist!$B$1 -> 202511 | C9: GJ | D9: =D8 -> DC1103251 | E9: =D9 -> DC1103251 | F9: =$F$2 -> 45964 | G9: 0 | H9: 33250 | I9: =$F$2 -> 45964 | J9: Rental Income - WGHI2 | K9: LCREE-1470-0000-000-WGHI2
A10: LCREE | B10: =Checklist!$B$1 -> 202511 | C10: GJ | D10: =D9 -> DC1103251 | E10: =D10 -> DC1103251 | F10: =$F$2 -> 45964 | G10: 27083.33 | H10: 0 | I10: =$F$2 -> 45964 | J10: Rental Income - WGNI2 | K10: LCREE-1065-0008-000-
A11: LCREE | B11: =Checklist!$B$1 -> 202511 | C11: GJ | D11: =D10 -> DC1103251 | E11: =D11 -> DC1103251 | F11: =$F$2 -> 45964 | G11: 0 | H11: 27083.33 | I11: =$F$2 -> 45964 | J11: Rental Income - WGNI2 | K11: LCREE-1470-0000-000-WGNI2
B12: =Checklist!$B$1 -> 202511 | C12: GJ | D12: =D11 -> DC1103251 | E12: =D12 -> DC1103251 | F12: =$F$2 -> 45964 | I12: =$F$2 -> 45964
B13: =Checklist!$B$1 -> 202511 | C13: GJ | D13: =D12 -> DC1103251 | E13: =D13 -> DC1103251 | F13: =$F$2 -> 45964 | I13: =$F$2 -> 45964
B14: =Checklist!$B$1 -> 202511 | C14: GJ | D14: =D13 -> DC1103251 | E14: =D14 -> DC1103251 | F14: =$F$2 -> 45964 | I14: =$F$2 -> 45964
B15: =Checklist!$B$1 -> 202511 | C15: GJ | D15: =D14 -> DC1103251 | E15: =D15 -> DC1103251 | F15: =$F$2 -> 45964 | I15: =$F$2 -> 45964
B16: =Checklist!$B$1 -> 202511 | C16: GJ | D16: =D15 -> DC1103251 | E16: =D16 -> DC1103251 | F16: =$F$2 -> 45964 | I16: =$F$2 -> 45964
B17: =Checklist!$B$1 -> 202511 | C17: GJ | D17: =D16 -> DC1103251 | E17: =D17 -> DC1103251 | F17: =$F$2 -> 45964 | I17: =$F$2 -> 45964
B18: =Checklist!$B$1 -> 202511 | C18: GJ | D18: =D17 -> DC1103251 | E18: =D18 -> DC1103251 | F18: =$F$2 -> 45964 | I18: =$F$2 -> 45964
B19: =Checklist!$B$1 -> 202511 | C19: GJ | D19: =D18 -> DC1103251 | E19: =D19 -> DC1103251 | F19: =$F$2 -> 45964 | I19: =$F$2 -> 45964
B20: =Checklist!$B$1 -> 202511 | C20: GJ | D20: =D19 -> DC1103251 | E20: =D20 -> DC1103251 | F20: =$F$2 -> 45964 | I20: =$F$2 -> 45964
B21: =Checklist!$B$1 -> 202511 | C21: GJ | D21: =D20 -> DC1103251 | E21: =D21 -> DC1103251 | F21: =$F$2 -> 45964 | I21: =$F$2 -> 45964
B22: =Checklist!$B$1 -> 202511 | C22: GJ | D22: =D21 -> DC1103251 | E22: =D22 -> DC1103251 | F22: =$F$2 -> 45964 | I22: =$F$2 -> 45964
B23: =Checklist!$B$1 -> 202511 | C23: GJ | D23: =D22 -> DC1103251 | E23: =D23 -> DC1103251 | F23: =$F$2 -> 45964 | I23: =$F$2 -> 45964
... B25: =Checklist!$B$1 -> 202511 | C25: GJ | D25: =D24 -> DC1103251 | E25: =D25 -> DC1103251 | F25: =$F$2 -> 45964 | I25: =$F$2 -> 45964

Sheet Cash Activity 11-4
A1: ="Daily Bank Activity - "&MONTH(Checklist!A6)&"/"&DAY(Checklist!A6)&"/"&YEAR(Checklist!A6) -> Daily Bank Activity - 11/4/2025
A2: Credit (+) / Debit (-)
B4: # | C4: Bank | D4: Acct Name | E4: Acct # | F4: Date | G4: Type | H4: Amount | I4: Bank Ref | J4: Bank Stmt Description | K4: Trans Type | L4: Entity | M4: AIT | N4: Short Description | O4: GL Account 1 | P4: GL Account 2 | Q4: Posted?
B5: 1 | C5: PNC | D5: LCFH REIT | E5: 8026459924 | F5: 45965 | G5: CR | H5: 211.66 | I5: '00000000000 | J5: PNC SWEEP INTEREST @ 0.000000 EFFECTIVE DATE 11-03 | K5: =IF(ISNUMBER(SEARCH("Manual Payment - ",N5,1)),"AP",IF(ISNUMBER(SEARCH("Payment - Concur",N5,1)),"WDL",IF(ISNUMBER(SEARCH("Payroll Transfer",N5,1)),"XFR",IF(ISNUMBER(SEARCH("XFR",N5,1)),"XFR",IF(H5>0,"RCT","WDL"))))) -> RCT | L5: =VLOOKUP(D5,'Entity Code'!A:B,2,0) -> LCFHR | N5: Overnight interest sweep PNC LCFHR account. No entry required | O5: N/A | P5: N/A | Q5: N/A
B6: 2 | C6: PNC | D6: LCFH REIT | E6: 8026459924 | F6: 45965 | G6: CR | H6: 2452621.7 | I6: '00000000000 | J6: SWEEP TRANSFR FROM INVESTMENT ACCT 8026459924 | K6: =IF(ISNUMBER(SEARCH("Manual Payment - ",N6,1)),"AP",IF(ISNUMBER(SEARCH("Payment - Concur",N6,1)),"WDL",IF(ISNUMBER(SEARCH("Payroll Transfer",N6,1)),"XFR",IF(ISNUMBER(SEARCH("XFR",N6,1)),"XFR",IF(H6>0,"RCT","WDL"))))) -> RCT | L6: =VLOOKUP(D6,'Entity Code'!A:B,2,0) -> LCFHR | N6: Overnight interest sweep PNC LCFHR account. No entry required | O6: N/A | P6: N/A | Q6: N/A
B7: 3 | C7: PNC | D7: LCFH REIT | E7: 8026459924 | F7: 45965 | G7: DR | H7: -5072833.3 | I7: '00000000000 | J7: SWEEP TO INVESTMENT ACCT# 8026459924 | K7: =IF(ISNUMBER(SEARCH("Manual Payment - ",N7,1)),"AP",IF(ISNUMBER(SEARCH("Payment - Concur",N7,1)),"WDL",IF(ISNUMBER(SEARCH("Payroll Transfer",N7,1)),"XFR",IF(ISNUMBER(SEARCH("XFR",N7,1)),"XFR",IF(H7>0,"RCT","WDL"))))) -> WDL | L7: =VLOOKUP(D7,'Entity Code'!A:B,2,0) -> LCFHR | N7: Overnight interest sweep PNC LCFHR account. No entry required | O7: N/A | P7: N/A | Q7: N/A
B8: 4 | C8: PNC | D8: LCFH REIT | E8: 8026459924 | F8: 45965 | G8: DR | H8: -10000000 | I8: 'PAB4C4927P7I4RWJ | J8: WIRE TRANSFER ISO AMT:USD 10000000.00 STTLMT DATE: | K8: =IF(ISNUMBER(SEARCH("Manual Payment - ",N8,1)),"AP",IF(ISNUMBER(SEARCH("Payment - Concur",N8,1)),"WDL",IF(ISNUMBER(SEARCH("Payroll Transfer",N8,1)),"XFR",IF(ISNUMBER(SEARCH("XFR",N8,1)),"XFR",IF(H8>0,"RCT","WDL"))))) -> WDL | L8: =VLOOKUP(D8,'Entity Code'!A:B,2,0) -> LCFHR | N8: SocGen Paydown | O8: 2701-CAMR-000 | P8: N/A | Q8: SS&C to post
B9: 5 | C9: PNC | D9: Tuebor REIT | E9: 8026495976 | F9: 45965 | G9: DR | H9: -182796.41 | I9: '25B3N0050C3Z52A1 | J9: WIRE TRANSFER ISO STTLMT DATE:11042025 CLR SYS REF | K9: =IF(ISNUMBER(SEARCH("Manual Payment - ",N9,1)),"AP",IF(ISNUMBER(SEARCH("Payment - Concur",N9,1)),"WDL",IF(ISNUMBER(SEARCH("Payroll Transfer",N9,1)),"XFR",IF(ISNUMBER(SEARCH("XFR",N9,1)),"XFR",IF(H9>0,"RCT","WDL"))))) -> WDL | L9: =VLOOKUP(D9,'Entity Code'!A:B,2,0) -> TUERI | N9: Incorrect advance wire – refund expected | O9: =IFERROR(VLOOKUP(E9,'Bank Account'!A:B,2,FALSE),VLOOKUP(_xlfn.NUMBERVALUE(E9),'Bank Account'!A:B,2,FALSE)) -> TUERI-1065-0010-000-
B10: 6 | C10: JPM | D10: LADDER CAPITAL FINANCE LLC TRADING | E10: 865357610 | F10: 45965 | G10: Credit | H10: 13774.39 | I10: 3580941602 | J10: REMOTE ONLINE DEP | K10: =IF(ISNUMBER(SEARCH("Manual Payment - ",N10,1)),"AP",IF(ISNUMBER(SEARCH("Payment - Concur",N10,1)),"WDL",IF(ISNUMBER(SEARCH("Payroll Transfer",N10,1)),"XFR",IF(ISNUMBER(SEARCH("XFR",N10,1)),"XFR",IF(H10>0,"RCT","WDL"))))) -> RCT | L10: =VLOOKUP(D10,'Entity Code'!A:B,2,0) -> LCF | N10: Checks Deposited - employee expense reimbursement, IMA and Meridian Mark management fee share | O10: Various | Q10: Ladder to post
B11: 7 | C11: JPM | D11: LADDER CAPITAL CRE EQUITY LLC | E11: 528280121 | F11: 45965 | G11: Credit | H11: 40930.28 | I11: 3580941587 | J11: REMOTE ONLINE DEP | K11: =IF(ISNUMBER(SEARCH("Manual Payment - ",N11,1)),"AP",IF(ISNUMBER(SEARCH("Payment - Concur",N11,1)),"WDL",IF(ISNUMBER(SEARCH("Payroll Transfer",N11,1)),"XFR",IF(ISNUMBER(SEARCH("XFR",N11,1)),"XFR",IF(H11>0,"RCT","WDL"))))) -> RCT | L11: =VLOOKUP(D11,'Entity Code'!A:B,2,0) -> LCREE | N11: Checks Deposited - DG De Soto, Warren, Tremont and Effingham | O11: Various | P11: N/A | Q11: Ladder to post
B12: 8 | C12: JPM | D12: LADDER CAPITAL CRE EQUITY LLC | E12: 528280121 | F12: 45965 | G12: Credit | H12: 46666.67 | I12: 3580941596 | J12: REMOTE ONLINE DEP | K12: =IF(ISNUMBER(SEARCH("Manual Payment - ",N12,1)),"AP",IF(ISNUMBER(SEARCH("Payment - Concur",N12,1)),"WDL",IF(ISNUMBER(SEARCH("Payroll Transfer",N12,1)),"XFR",IF(ISNUMBER(SEARCH("XFR",N12,1)),"XFR",IF(H12>0,"RCT","WDL"))))) -> RCT | L12: =VLOOKUP(D12,'Entity Code'!A:B,2,0) -> LCREE | N12: Rental Income - WGPON | O12: LCREE-1470-0000-000-WGPON | P12: N/A | Q12: Ladder to post
B13: 9 | C13: PNC | D13: LCREF | E13: 8026497285 | F13: 45965 | G13: CR | H13: 350000 | I13: '25B4L1857BC14LOY | J13: WIRE TRANSFER ISO AMT:USD 350000.00 STTLMT DATE:11 | K13: =IF(ISNUMBER(SEARCH("Manual Payment - ",N13,1)),"AP",IF(ISNUMBER(SEARCH("Payment - Concur",N13,1)),"WDL",IF(ISNUMBER(SEARCH("Payroll Transfer",N13,1)),"XFR",IF(ISNUMBER(SEARCH("XFR",N13,1)),"XFR",IF(H13>0,"RCT","WDL"))))) -> RCT | L13: =VLOOKUP(D13,'Entity Code'!A:B,2,0) -> LCREF | N13: 519 Uptown Owner's Account Excess Funds | O13: LCREF-1470-0000-000-519UP | P13: N/A | Q13: Ladder to post
B14: 10 | C14: PNC | D14: Tuebor REIT | E14: 8026495976 | F14: 45965 | G14: CR | H14: 1400000 | I14: '25B4K3538I8Z8EMF | J14: WIRE TRANSFER ISO AMT:USD 1400000.00 STTLMT DATE:1 | K14: =IF(ISNUMBER(SEARCH("Manual Payment - ",N14,1)),"AP",IF(ISNUMBER(SEARCH("Payment - Concur",N14,1)),"WDL",IF(ISNUMBER(SEARCH("Payroll Transfer",N14,1)),"XFR",IF(ISNUMBER(SEARCH("XFR",N14,1)),"XFR",IF(H14>0,"RCT","WDL"))))) -> RCT | L14: =VLOOKUP(D14,'Entity Code'!A:B,2,0) -> TUERI | N14: 15600 JFK Owner's Account Excess Funds | O14: TUERI-1470-0000-000-15JFK | P14: N/A | Q14: Ladder to post
B15: 11 | C15: PNC | D15: LCFH REIT | E15: 8026459924 | F15: 45965 | G15: CR | H15: 22520000 | I15: '25B4H00479K111UZ | J15: WIRE TRANSFER ISO STTLMT DATE:11042025 CLR SYS REF | K15: =IF(ISNUMBER(SEARCH("Manual Payment - ",N15,1)),"AP",IF(ISNUMBER(SEARCH("Payment - Concur",N15,1)),"WDL",IF(ISNUMBER(SEARCH("Payroll Transfer",N15,1)),"XFR",IF(ISNUMBER(SEARCH("XFR",N15,1)),"XFR",IF(H15>0,"RCT","WDL"))))) -> XFR | L15: =VLOOKUP(D15,'Entity Code'!A:B,2,0) -> LCFHR | N15: XFR from LCFHR BNY to LCFHR PNC | O15: 2701-CAMR-000 | P15: N/A | Q15: SS&C to post
B16: 12 | C16: PNC | D16: LCFH REIT | E16: 8026459924 | F16: 45965 | G16: DR | H16: -9900000 | I16: 'PAB4C4927PGH3776 | J16: WIRE TRANSFER ISO AMT:USD 9900000.00 STTLMT DATE:1 | K16: =IF(ISNUMBER(SEARCH("Manual Payment - ",N16,1)),"AP",IF(ISNUMBER(SEARCH("Payment - Concur",N16,1)),"WDL",IF(ISNUMBER(SEARCH("Payroll Transfer",N16,1)),"XFR",IF(ISNUMBER(SEARCH("XFR",N16,1)),"XFR",IF(H16>0,"RCT","WDL"))))) -> XFR | L16: =VLOOKUP(D16,'Entity Code'!A:B,2,0) -> LCFHR | N16: XFR from LCFHR PNC to LCFP3 | O16: 2701-CAMR-000 | P16: N/A | Q16: SS&C to post
B17: 13 | C17: JPM | D17: LADDER CAPITAL FINANCE LLC OPERATIN | E17: 865357602 | F17: 45965 | G17: Debit | H17: -10422.54 | I17: 3084101163TC | J17: EFT DEBIT | K17: =IF(ISNUMBER(SEARCH("Manual Payment - ",N17,1)),"AP",IF(ISNUMBER(SEARCH("Payment - Concur",N17,1)),"WDL",IF(ISNUMBER(SEARCH("Payroll Transfer",N17,1)),"XFR",IF(ISNUMBER(SEARCH("XFR",N17,1)),"XFR",IF(H17>0,"RCT","WDL"))))) -> WDL | L17: =VLOOKUP(D17,'Entity Code'!A:B,2,0) -> LCF | N17: Payment - Concur | O17: N/A | P17: N/A | Q17: Ladder to post
B18: 14 | C18: JPM | D18: LADDER CAPITAL FINANCE LLC OPERATIN | E18: 865357602 | F18: 45965 | G18: Debit | H18: -1642.72 | I18: 3084101161TC | J18: EFT DEBIT | K18: =IF(ISNUMBER(SEARCH("Manual Payment - ",N18,1)),"AP",IF(ISNUMBER(SEARCH("Payment - Concur",N18,1)),"WDL",IF(ISNUMBER(SEARCH("Payroll Transfer",N18,1)),"XFR",IF(ISNUMBER(SEARCH("XFR",N18,1)),"XFR",IF(H18>0,"RCT","WDL"))))) -> AP | L18: =VLOOKUP(D18,'Entity Code'!A:B,2,0) -> LCF | N18: Manual Payment - Con Ed | O18: N/A | P18: N/A | Q18: Ladder to post
N23: Check Deposited - employee expense reimbursement | O23: 361.96 | P23: LCF -5405-0000-000-
N24: Check Deposited - IMA | O24: 901.79 | P24: reached out to SG on 11/7
N25: Check Deposited - Meridian Mark management fee share | O25: 12510.64 | P25: LCF -4410-LN03-200-
O26: =SUM(O23:O25) -> 13774.39
O27: =H10 -> 13774.39
O28: =O26-O27 -> 0
N31: Check Deposited - DG - DeSoto IA | O31: 4527.41 | P31: LCREE-1470-0000-000-DGDES
N32: Check Deposited - DG - Warren | O32: 4953.9 | P32: DGWAR-1950-0000-000-
N33: Check Deposited - DG - Tremont IL | O33: 14531 | P33: DGTRE-1950-0000-000-
N34: Check Deposited - DG - Effingham IL | O34: 16917.97 | P34: LCREE-1950-0000-000-
O35: =SUM(O31:O34) -> 40930.28
O36: =H11 -> 40930.28
O37: =O35-O36 -> 0

Sheet Cash Entries 11-4
A1: ENTITY | B1: YEARMONTH | C1: SOURCE | D1: BATCH ID | E1: BATCH DESCRIPTION | F1: BATCHDATE | G1: DR_AMT | H1: CR AMT | I1: TRXDATE | J1: DIST REFERENCE | K1: GPACCT
A2: LCF | B2: =Checklist!$B$1 -> 202511 | C2: GJ | D2: =Checklist!$B$6 -> DC1104251 | E2: =D2 -> DC1104251 | F2: =Checklist!$A$6 -> 45965 | G2: 13774.39 | H2: 0 | I2: =$F$2 -> 45965 | J2: Checks Deposited - employee expense reimbursement, IMA and Meridian Mark management fee share | K2: LCF -1029-0000-000-
A3: LCF | B3: =Checklist!$B$1 -> 202511 | C3: GJ | D3: =D2 -> DC1104251 | E3: =D3 -> DC1104251 | F3: =Checklist!$A$6 -> 45965 | G3: 0 | H3: 361.96 | I3: =$F$2 -> 45965 | J3: Checks Deposited - employee expense reimbursement, IMA and Meridian Mark management fee share | K3: LCF -5405-0000-000- | L3: Check Deposited - employee expense reimbursement
A4: LCF | B4: =Checklist!$B$1 -> 202511 | C4: GJ | D4: =D3 -> DC1104251 | E4: =D4 -> DC1104251 | F4: =Checklist!$A$6 -> 45965 | G4: 0 | H4: 901.79 | I4: =$F$2 -> 45965 | J4: Checks Deposited - employee expense reimbursement, IMA and Meridian Mark management fee share | L4: Check Deposited - IMA
A5: LCF | B5: =Checklist!$B$1 -> 202511 | C5: GJ | D5: =D4 -> DC1104251 | E5: =D5 -> DC1104251 | F5: =Checklist!$A$6 -> 45965 | G5: 0 | H5: 12510.64 | I5: =$F$2 -> 45965 | J5: Checks Deposited - employee expense reimbursement, IMA and Meridian Mark management fee share | K5: LCF -4410-LN03-200- | L5: Check Deposited - Meridian Mark management fee share
A6: LCREE | B6: =Checklist!$B$1 -> 202511 | C6: GJ | D6: =D5 -> DC1104251 | E6: =D6 -> DC1104251 | F6: =Checklist!$A$6 -> 45965 | G6: 40930.28 | H6: 0 | I6: =$F$2 -> 45965 | J6: Checks Deposited - DG De Soto, Warren, Tremont and Effingham | K6: LCREE-1043-0000-000-
A7: LCREE | B7: =Checklist!$B$1 -> 202511 | C7: GJ | D7: =D6 -> DC1104251 | E7: =D7 -> DC1104251 | F7: =Checklist!$A$6 -> 45965 | G7: 0 | H7: 4527.41 | I7: =$F$2 -> 45965 | J7: Checks Deposited - DG De Soto, Warren, Tremont and Effingham | K7: LCREE-1470-0000-000-DGDES | L7: DeSoto
A8: DGWAR | B8: =Checklist!$B$1 -> 202511 | C8: GJ | D8: =D7 -> DC1104251 | E8: =D8 -> DC1104251 | F8: =Checklist!$A$6 -> 45965 | G8: 0 | H8: 4953.9 | I8: =$F$2 -> 45965 | J8: Checks Deposited - DG De Soto, Warren, Tremont and Effingham | K8: DGWAR-1950-0000-000- | L8: confirm State Street booked debit to 1950
A9: DGTRE | B9: =Checklist!$B$1 -> 202511 | C9: GJ | D9: =D8 -> DC1104251 | E9: =D9 -> DC1104251 | F9: =Checklist!$A$6 -> 45965 | G9: 0 | H9: 14531 | I9: =$F$2 -> 45965 | J9: Checks Deposited - DG De Soto, Warren, Tremont and Effingham | K9: DGTRE-1950-0000-000- | L9: confirm State Street booked debit to 1950
A10: LCREE | B10: =Checklist!$B$1 -> 202511 | C10: GJ | D10: =D9 -> DC1104251 | E10: =D10 -> DC1104251 | F10: =Checklist!$A$6 -> 45965 | G10: 0 | H10: 16917.97 | I10: =$F$2 -> 45965 | J10: Checks Deposited - DG De Soto, Warren, Tremont and Effingham | K10: LCREE-1950-0000-000- | L10: Effingham
A11: DGWAR | B11: =Checklist!$B$1 -> 202511 | C11: GJ | D11: =D10 -> DC1104251 | E11: =D11 -> DC1104251 | F11: =Checklist!$A$6 -> 45965 | G11: 4953.9 | H11: 0 | I11: =$F$2 -> 45965 | J11: Checks Deposited - DG De Soto, Warren, Tremont and Effingham | K11: DGWAR-1900-0000-000-LCREE
A12: DGTRE | B12: =Checklist!$B$1 -> 202511 | C12: GJ | D12: =D11 -> DC1104251 | E12: =D12 -> DC1104251 | F12: =Checklist!$A$6 -> 45965 | G12: 14531 | H12: 0 | I12: =$F$2 -> 45965 | J12: Checks Deposited - DG De Soto, Warren, Tremont and Effingham | K12: DGTRE-1900-0000-000-LCREE
A13: LCREE | B13: =Checklist!$B$1 -> 202511 | C13: GJ | D13: =D12 -> DC1104251 | E13: =D13 -> DC1104251 | F13: =Checklist!$A$6 -> 45965 | G13: 0 | H13: 4953.9 | I13: =$F$2 -> 45965 | J13: Checks Deposited - DG De Soto, Warren, Tremont and Effingham | K13: LCREE-1900-0000-000-DGWAR
A14: LCREE | B14: =Checklist!$B$1 -> 202511 | C14: GJ | D14: =D13 -> DC1104251 | E14: =D14 -> DC1104251 | F14: =Checklist!$A$6 -> 45965 | G14: 0 | H14: 14531 | I14: =$F$2 -> 45965 | J14: Checks Deposited - DG De Soto, Warren, Tremont and Effingham | K14: LCREE-1900-0000-000-DGTRE
A15: LCREE | B15: =Checklist!$B$1 -> 202511 | C15: GJ | D15: =D14 -> DC1104251 | E15: =D15 -> DC1104251 | F15: =Checklist!$A$6 -> 45965 | G15: 46666.67 | H15: 0 | I15: =$F$2 -> 45965 | J15: Rental Income - WGPON | K15: LCREE-1043-0000-000-
A16: LCREE | B16: =Checklist!$B$1 -> 202511 | C16: GJ | D16: =D15 -> DC1104251 | E16: =D16 -> DC1104251 | F16: =Checklist!$A$6 -> 45965 | G16: 0 | H16: 46666.67 | I16: =$F$2 -> 45965 | J16: Rental Income - WGPON | K16: LCREE-1470-0000-000-WFPON
A17: LCREF | B17: =Checklist!$B$1 -> 202511 | C17: GJ | D17: =D16 -> DC1104251 | E17: =D17 -> DC1104251 | F17: =Checklist!$A$6 -> 45965 | G17: 350000 | H17: 0 | I17: =$F$2 -> 45965 | J17: 519 Uptown Owner's Account Excess Funds | K17: LCREF-1065-0008-000-
A18: LCREF | B18: =Checklist!$B$1 -> 202511 | C18: GJ | D18: =D17 -> DC1104251 | E18: =D18 -> DC1104251 | F18: =Checklist!$A$6 -> 45965 | G18: 0 | H18: 350000 | I18: =$F$2 -> 45965 | J18: 519 Uptown Owner's Account Excess Funds | K18: LCREF-1470-0000-000-519UP
A19: TUERI | B19: =Checklist!$B$1 -> 202511 | C19: GJ | D19: =D18 -> DC1104251 | E19: =D19 -> DC1104251 | F19: =Checklist!$A$6 -> 45965 | G19: 1400000 | H19: 0 | I19: =$F$2 -> 45965 | J19: 15600 JFK Owner's Account Excess Funds | K19: TUERI-1065-0010-000-
A20: TUERI | B20: =Checklist!$B$1 -> 202511 | C20: GJ | D20: =D19 -> DC1104251 | E20: =D20 -> DC1104251 | F20: =Checklist!$A$6 -> 45965 | G20: 0 | H20: 1400000 | I20: =$F$2 -> 45965 | J20: 15600 JFK Owner's Account Excess Funds | K20: TUERI-1470-0000-000-15JFK
B21: =Checklist!$B$1 -> 202511 | C21: GJ | D21: =D20 -> DC1104251 | E21: =D21 -> DC1104251 | F21: =Checklist!$A$6 -> 45965 | I21: =$F$2 -> 45965
B22: =Checklist!$B$1 -> 202511 | C22: GJ | D22: =D21 -> DC1104251 | E22: =D22 -> DC1104251 | F22: =Checklist!$A$6 -> 45965 | I22: =$F$2 -> 45965
B23: =Checklist!$B$1 -> 202511 | C23: GJ | D23: =D22 -> DC1104251 | E23: =D23 -> DC1104251 | F23: =Checklist!$A$6 -> 45965 | I23: =$F$2 -> 45965
B24: =Checklist!$B$1 -> 202511 | C24: GJ | D24: =D23 -> DC1104251 | E24: =D24 -> DC1104251 | F24: =Checklist!$A$6 -> 45965 | I24: =$F$2 -> 45965
B25: =Checklist!$B$1 -> 202511 | C25: GJ | D25: =D24 -> DC1104251 | E25: =D25 -> DC1104251 | F25: =Checklist!$A$6 -> 45965 | I25: =$F$2 -> 45965
B26: =Checklist!$B$1 -> 202511 | C26: GJ | D26: =D25 -> DC1104251 | E26: =D26 -> DC1104251 | F26: =Checklist!$A$6 -> 45965 | I26: =$F$2 -> 45965
B27: =Checklist!$B$1 -> 202511 | C27: GJ | D27: =D26 -> DC1104251 | E27: =D27 -> DC1104251 | F27: =Checklist!$A$6 -> 45965 | I27: =$F$2 -> 45965
B28: =Checklist!$B$1 -> 202511 | C28: GJ | D28: =D27 -> DC1104251 | E28: =D28 -> DC1104251 | F28: =Checklist!$A$6 -> 45965 | I28: =$F$2 -> 45965

Sheet Cash Activity 11-5
A1: ="Daily Bank Activity - "&MONTH(Checklist!A7)&"/"&DAY(Checklist!A7)&"/"&YEAR(Checklist!A7) -> Daily Bank Activity - 11/5/2025
A2: Credit (+) / Debit (-)
B4: # | C4: Bank | D4: Acct Name | E4: Acct # | F4: Date | G4: Type | H4: Amount | I4: Bank Ref | J4: Bank Stmt Description | K4: Trans Type | L4: Entity | M4: AIT | N4: Short Description | O4: GL Account 1 | P4: GL Account 2 | Q4: Posted?
B5: 1 | C5: PNC | D5: LCFH REIT | E5: 8026459924 | F5: 45966 | G5: CR | H5: 437.79 | I5: '00000000000 | J5: PNC SWEEP INTEREST @ 0.000000 EFFECTIVE DATE 11-04 | K5: =IF(ISNUMBER(SEARCH("Manual Payment - ",N5,1)),"AP",IF(ISNUMBER(SEARCH("Payment - Concur",N5,1)),"WDL",IF(ISNUMBER(SEARCH("Payroll Transfer",N5,1)),"XFR",IF(ISNUMBER(SEARCH("XFR",N5,1)),"XFR",IF(H5>0,"RCT","WDL"))))) -> RCT | L5: =VLOOKUP(D5,'Entity Code'!A:B,2,0) -> LCFHR | N5: Overnight interest sweep PNC LCFHR account. No entry required | O5: N/A | P5: N/A | Q5: N/A
B6: 2 | C6: PNC | D6: LCFH REIT | E6: 8026459924 | F6: 45966 | G6: CR | H6: 5072833.3 | I6: '00000000000 | J6: SWEEP TRANSFR FROM INVESTMENT ACCT 8026459924 | K6: =IF(ISNUMBER(SEARCH("Manual Payment - ",N6,1)),"AP",IF(ISNUMBER(SEARCH("Payment - Concur",N6,1)),"WDL",IF(ISNUMBER(SEARCH("Payroll Transfer",N6,1)),"XFR",IF(ISNUMBER(SEARCH("XFR",N6,1)),"XFR",IF(H6>0,"RCT","WDL"))))) -> RCT | L6: =VLOOKUP(D6,'Entity Code'!A:B,2,0) -> LCFHR | N6: Overnight interest sweep PNC LCFHR account. No entry required | O6: N/A | P6: N/A | Q6: N/A
B7: 3 | C7: PNC | D7: LCFH REIT | E7: 8026459924 | F7: 45966 | G7: DR | H7: -50350317 | I7: '00000000000 | J7: SWEEP TO INVESTMENT ACCT# 8026459924 | K7: =IF(ISNUMBER(SEARCH("Manual Payment - ",N7,1)),"AP",IF(ISNUMBER(SEARCH("Payment - Concur",N7,1)),"WDL",IF(ISNUMBER(SEARCH("Payroll Transfer",N7,1)),"XFR",IF(ISNUMBER(SEARCH("XFR",N7,1)),"XFR",IF(H7>0,"RCT","WDL"))))) -> WDL | L7: =VLOOKUP(D7,'Entity Code'!A:B,2,0) -> LCFHR | N7: Overnight interest sweep PNC LCFHR account. No entry required | O7: N/A | P7: N/A | Q7: N/A
B8: 4 | C8: PNC | D8: LCREF | E8: 8026497285 | F8: 45966 | G8: DR | H8: -200000 | I8: 'PAB5E0054P8I46SR | J8: WIRE TRANSFER ISO AMT:USD 200000.00 STTLMT DATE:11 | K8: =IF(ISNUMBER(SEARCH("Manual Payment - ",N8,1)),"AP",IF(ISNUMBER(SEARCH("Payment - Concur",N8,1)),"WDL",IF(ISNUMBER(SEARCH("Payroll Transfer",N8,1)),"XFR",IF(ISNUMBER(SEARCH("XFR",N8,1)),"XFR",IF(H8>0,"RCT","WDL"))))) -> WDL | L8: =VLOOKUP(D8,'Entity Code'!A:B,2,0) -> LCREF | N8: 7th & Hill - Protective Advance #1 | O8: 2701-LMS0-000 | P8: N/A | Q8: SS&C to post
B9: 5 | C9: JPM | D9: LADDER CAPITAL FINANCE LLC OPERATIN | E9: 865357602 | F9: 45966 | G9: Debit | H9: -5769.23 | I9: 2572100309JO | J9: FEDWIRE DEBIT | K9: =IF(ISNUMBER(SEARCH("Manual Payment - ",N9,1)),"AP",IF(ISNUMBER(SEARCH("Payment - Concur",N9,1)),"WDL",IF(ISNUMBER(SEARCH("Payroll Transfer",N9,1)),"XFR",IF(ISNUMBER(SEARCH("XFR",N9,1)),"XFR",IF(H9>0,"RCT","WDL"))))) -> AP | L9: =VLOOKUP(D9,'Entity Code'!A:B,2,0) -> LCF | N9: Manual Payment - Item Six | O9: N/A | P9: N/A | Q9: Ladder to post
B10: 6 | C10: PNC | D10: LCF Payroll | E10: 8147891123 | F10: 45966 | G10: DR | H10: -88.15 | I10: '25B5C4439LA02WIZ | J10: WIRE TRANSFER ISO STTLMT DATE:11052025 CLR SYS REF | K10: =IF(ISNUMBER(SEARCH("Manual Payment - ",N10,1)),"AP",IF(ISNUMBER(SEARCH("Payment - Concur",N10,1)),"WDL",IF(ISNUMBER(SEARCH("Payroll Transfer",N10,1)),"XFR",IF(ISNUMBER(SEARCH("XFR",N10,1)),"XFR",IF(H10>0,"RCT","WDL"))))) -> WDL | L10: =VLOOKUP(D10,'Entity Code'!A:B,2,0) -> LCF | N10: Payroll - Trinet service fee | O10: LCF -1745-0000-000- | P10: N/A | Q10: Ladder to post
B11: 7 | C11: PNC | D11: LCFH REIT | E11: 8026459924 | F11: 45966 | G11: CR | H11: 2045.61 | I11: '25B5M3511CX10CP7 | J11: WIRE TRANSFER ISO AMT:USD 2045.61 STTLMT DATE:1105 | K11: =IF(ISNUMBER(SEARCH("Manual Payment - ",N11,1)),"AP",IF(ISNUMBER(SEARCH("Payment - Concur",N11,1)),"WDL",IF(ISNUMBER(SEARCH("Payroll Transfer",N11,1)),"XFR",IF(ISNUMBER(SEARCH("XFR",N11,1)),"XFR",IF(H11>0,"RCT","WDL"))))) -> RCT | L11: =VLOOKUP(D11,'Entity Code'!A:B,2,0) -> LCFHR | N11: JPM Securities Repo Margin Interest | O11: 2701-CAMR-000 | P11: N/A | Q11: SS&C to post
B12: 8 | C12: JPM | D12: LADDER CAPITAL FINANCE LLC TRADING | E12: 865357610 | F12: 45966 | G12: Credit | H12: 7500 | I12: 0734911309FF | J12: FEDWIRE CREDIT | K12: =IF(ISNUMBER(SEARCH("Manual Payment - ",N12,1)),"AP",IF(ISNUMBER(SEARCH("Payment - Concur",N12,1)),"WDL",IF(ISNUMBER(SEARCH("Payroll Transfer",N12,1)),"XFR",IF(ISNUMBER(SEARCH("XFR",N12,1)),"XFR",IF(H12>0,"RCT","WDL"))))) -> RCT | L12: =VLOOKUP(D12,'Entity Code'!A:B,2,0) -> LCF | N12: Consent Fee - Village At Westfork | O12: 2701-LMS0-000 | P12: N/A | Q12: SS&C to post
B13: 9 | C13: JPM | D13: LADDER CAPITAL CRE EQUITY LLC | E13: 528280121 | F13: 45966 | G13: Credit | H13: 29914.14 | I13: 0229941309FF | J13: FEDWIRE CREDIT | K13: =IF(ISNUMBER(SEARCH("Manual Payment - ",N13,1)),"AP",IF(ISNUMBER(SEARCH("Payment - Concur",N13,1)),"WDL",IF(ISNUMBER(SEARCH("Payroll Transfer",N13,1)),"XFR",IF(ISNUMBER(SEARCH("XFR",N13,1)),"XFR",IF(H13>0,"RCT","WDL"))))) -> RCT | L13: =VLOOKUP(D13,'Entity Code'!A:B,2,0) -> LCREE | N13: Excess Funds - DGPEO | O13: LCREE-1470-0000-000-DGPEO | P13: N/A | Q13: Ladder to post
B14: 10 | C14: PNC | D14: LCREF | E14: 8026497285 | F14: 45966 | G14: CR | H14: 44016841 | I14: '25B5L49219513YBK | J14: WIRE TRANSFER ISO AMT:USD 44016841.00 STTLMT DATE: | K14: =IF(ISNUMBER(SEARCH("Manual Payment - ",N14,1)),"AP",IF(ISNUMBER(SEARCH("Payment - Concur",N14,1)),"WDL",IF(ISNUMBER(SEARCH("Payroll Transfer",N14,1)),"XFR",IF(ISNUMBER(SEARCH("XFR",N14,1)),"XFR",IF(H14>0,"RCT","WDL"))))) -> RCT | L14: =VLOOKUP(D14,'Entity Code'!A:B,2,0) -> LCREF | N14: 17 West 60th Street Payoff Proceeds | O14: 2701-LMS0-000 | P14: N/A | Q14: SS&C to post
B15: 11 | C15: PNC | D15: LCREF | E15: 8026497285 | F15: 45966 | G15: CR | H15: 300000 | I15: '25B5F54446A15W7C | J15: WIRE TRANSFER ISO AMT:USD 300000.00 STTLMT DATE:11 | K15: =IF(ISNUMBER(SEARCH("Manual Payment - ",N15,1)),"AP",IF(ISNUMBER(SEARCH("Payment - Concur",N15,1)),"WDL",IF(ISNUMBER(SEARCH("Payroll Transfer",N15,1)),"XFR",IF(ISNUMBER(SEARCH("XFR",N15,1)),"XFR",IF(H15>0,"RCT","WDL"))))) -> XFR | L15: =VLOOKUP(D15,'Entity Code'!A:B,2,0) -> LCREF | N15: XFR from LCFP4 to LCREF | O15: 2701-CAMR-000 | P15: N/A | Q15: SS&C to post
B16: 12 | C16: PNC | D16: LADDER CRE PARENT | E16: 8026497277 | F16: 45966 | G16: CR | H16: 44500000 | I16: '25B5L5858NO06D8M | J16: BOOK TRANSFER CREDIT 006D8M ORIGINATOR:LADDER CRE | K16: =IF(ISNUMBER(SEARCH("Manual Payment - ",N16,1)),"AP",IF(ISNUMBER(SEARCH("Payment - Concur",N16,1)),"WDL",IF(ISNUMBER(SEARCH("Payroll Transfer",N16,1)),"XFR",IF(ISNUMBER(SEARCH("XFR",N16,1)),"XFR",IF(H16>0,"RCT","WDL"))))) -> RCT | L16: =VLOOKUP(D16,'Entity Code'!A:B,2,0) -> LCREP | N16: Dividend Payment | O16: LCREP-1470-0000-000-LCREF | P16: N/A | Q16: Ladder to post
B17: 12 | C17: PNC | D17: LCREF | E17: 8026497285 | F17: 45966 | G17: DR | H17: -44500000 | I17: '25B5L5858NO06D8M | J17: BOOK TRANSFER DEBIT 006D8M ORIGINATOR:LADDER CRE F | K17: =IF(ISNUMBER(SEARCH("Manual Payment - ",N17,1)),"AP",IF(ISNUMBER(SEARCH("Payment - Concur",N17,1)),"WDL",IF(ISNUMBER(SEARCH("Payroll Transfer",N17,1)),"XFR",IF(ISNUMBER(SEARCH("XFR",N17,1)),"XFR",IF(H17>0,"RCT","WDL"))))) -> WDL | L17: =VLOOKUP(D17,'Entity Code'!A:B,2,0) -> LCREF | N17: Dividend Payment | O17: LCREF-3670-0000-000-LCREP | P17: N/A | Q17: Ladder to post
B18: 13 | C18: PNC | D18: LCFH REIT | E18: 8026459924 | F18: 45966 | G18: CR | H18: 44055000 | I18: '25B5L5858OB1421K | J18: BOOK TRANSFER CREDIT 00421K ORIGINATOR:LADDER CRE | K18: =IF(ISNUMBER(SEARCH("Manual Payment - ",N18,1)),"AP",IF(ISNUMBER(SEARCH("Payment - Concur",N18,1)),"WDL",IF(ISNUMBER(SEARCH("Payroll Transfer",N18,1)),"XFR",IF(ISNUMBER(SEARCH("XFR",N18,1)),"XFR",IF(H18>0,"RCT","WDL"))))) -> RCT | L18: =VLOOKUP(D18,'Entity Code'!A:B,2,0) -> LCFHR | N18: Partnership Distribution | O18: MID2R-1470-0000-000-LCREP | P18: N/A | Q18: Ladder to post
B19: 13 | C19: PNC | D19: LADDER CRE PARENT | E19: 8026497277 | F19: 45966 | G19: DR | H19: -44055000 | I19: '25B5L5858OB1421K | J19: BOOK TRANSFER DEBIT 00421K ORIGINATOR:LADDER CRE P | K19: =IF(ISNUMBER(SEARCH("Manual Payment - ",N19,1)),"AP",IF(ISNUMBER(SEARCH("Payment - Concur",N19,1)),"WDL",IF(ISNUMBER(SEARCH("Payroll Transfer",N19,1)),"XFR",IF(ISNUMBER(SEARCH("XFR",N19,1)),"XFR",IF(H19>0,"RCT","WDL"))))) -> WDL | L19: =VLOOKUP(D19,'Entity Code'!A:B,2,0) -> LCREP | N19: Partnership Distribution | O19: LCREP-3670-0000-000-MID2R | P19: N/A | Q19: Ladder to post
B20: 14 | C20: PNC | D20: Ladder Capital Finance | E20: 8026459916 | F20: 45966 | G20: CR | H20: 445000 | I20: '25B5L585905Z5CB9 | J20: BOOK TRANSFER CREDIT 005CB9 ORIGINATOR:LADDER CRE | K20: =IF(ISNUMBER(SEARCH("Manual Payment - ",N20,1)),"AP",IF(ISNUMBER(SEARCH("Payment - Concur",N20,1)),"WDL",IF(ISNUMBER(SEARCH("Payroll Transfer",N20,1)),"XFR",IF(ISNUMBER(SEARCH("XFR",N20,1)),"XFR",IF(H20>0,"RCT","WDL"))))) -> RCT | L20: =VLOOKUP(D20,'Entity Code'!A:B,2,0) -> LCF | N20: Partnership Distribution | O20: LMID2-1470-0000-000-LCREP | P20: N/A | Q20: Ladder to post
B21: 14 | C21: PNC | D21: LADDER CRE PARENT | E21: 8026497277 | F21: 45966 | G21: DR | H21: -445000 | I21: '25B5L585905Z5CB9 | J21: BOOK TRANSFER DEBIT 005CB9 ORIGINATOR:LADDER CRE P | K21: =IF(ISNUMBER(SEARCH("Manual Payment - ",N21,1)),"AP",IF(ISNUMBER(SEARCH("Payment - Concur",N21,1)),"WDL",IF(ISNUMBER(SEARCH("Payroll Transfer",N21,1)),"XFR",IF(ISNUMBER(SEARCH("XFR",N21,1)),"XFR",IF(H21>0,"RCT","WDL"))))) -> WDL | L21: =VLOOKUP(D21,'Entity Code'!A:B,2,0) -> LCREP | N21: Partnership Distribution | O21: LCREP-3670-0000-000-LMID2 | P21: N/A | Q21: Ladder to post
B22: 15 | C22: PNC | D22: LCI | E22: 8026496012 | F22: 45966 | G22: CR | H22: 1220000 | I22: '25B5L00186410RP4 | J22: BOOK TRANSFER CREDIT 000RP4 ORIGINATOR:TUEBOR REIT | K22: =IF(ISNUMBER(SEARCH("Manual Payment - ",N22,1)),"AP",IF(ISNUMBER(SEARCH("Payment - Concur",N22,1)),"WDL",IF(ISNUMBER(SEARCH("Payroll Transfer",N22,1)),"XFR",IF(ISNUMBER(SEARCH("XFR",N22,1)),"XFR",IF(H22>0,"RCT","WDL"))))) -> RCT | L22: =VLOOKUP(D22,'Entity Code'!A:B,2,0) -> LCI | N22: Capital Distribution | O22: 3800-0000-000 | P22: N/A | Q22: SS&C to post
B23: 15 | C23: PNC | D23: Tuebor REIT | E23: 8026495976 | F23: 45966 | G23: DR | H23: -1220000 | I23: '25B5L00186410RP4 | J23: BOOK TRANSFER DEBIT 000RP4 ORIGINATOR:TUEBOR REIT | K23: =IF(ISNUMBER(SEARCH("Manual Payment - ",N23,1)),"AP",IF(ISNUMBER(SEARCH("Payment - Concur",N23,1)),"WDL",IF(ISNUMBER(SEARCH("Payroll Transfer",N23,1)),"XFR",IF(ISNUMBER(SEARCH("XFR",N23,1)),"XFR",IF(H23>0,"RCT","WDL"))))) -> WDL | L23: =VLOOKUP(D23,'Entity Code'!A:B,2,0) -> TUERI | N23: Capital Distribution | O23: 1450-0000-000 | P23: N/A | Q23: SS&C to post
B24: 16 | C24: PNC | D24: LCFH REIT | E24: 8026459924 | F24: 45966 | G24: CR | H24: 1220000 | I24: '25B5L00186MZ4IZM | J24: BOOK TRANSFER CREDIT 004IZM ORIGINATOR:LADDER CAPI | K24: =IF(ISNUMBER(SEARCH("Manual Payment - ",N24,1)),"AP",IF(ISNUMBER(SEARCH("Payment - Concur",N24,1)),"WDL",IF(ISNUMBER(SEARCH("Payroll Transfer",N24,1)),"XFR",IF(ISNUMBER(SEARCH("XFR",N24,1)),"XFR",IF(H24>0,"RCT","WDL"))))) -> XFR | L24: =VLOOKUP(D24,'Entity Code'!A:B,2,0) -> LCFHR | N24: XFR from LCI PNC to LCFHR PNC | O24: 2701-CAMR-000 | P24: N/A | Q24: SS&C to post
B25: 16 | C25: PNC | D25: LCI | E25: 8026496012 | F25: 45966 | G25: DR | H25: -1220000 | I25: '25B5L00186MZ4IZM | J25: BOOK TRANSFER DEBIT 004IZM ORIGINATOR:LADDER CAPIT | K25: =IF(ISNUMBER(SEARCH("Manual Payment - ",N25,1)),"AP",IF(ISNUMBER(SEARCH("Payment - Concur",N25,1)),"WDL",IF(ISNUMBER(SEARCH("Payroll Transfer",N25,1)),"XFR",IF(ISNUMBER(SEARCH("XFR",N25,1)),"XFR",IF(H25>0,"RCT","WDL"))))) -> XFR | L25: =VLOOKUP(D25,'Entity Code'!A:B,2,0) -> LCI | N25: XFR from LCI PNC to LCFHR PNC | O25: 2701-CAMR-000 | P25: N/A | Q25: SS&C to post
B26: 17 | C26: JPM | D26: LADDER CAPITAL FINANCE LLC OPERATIN | E26: 865357602 | F26: 45966 | G26: Debit | H26: -38475.5 | I26: 8398500309JO | J26: FEDWIRE DEBIT | K26: =IF(ISNUMBER(SEARCH("Manual Payment - ",N26,1)),"AP",IF(ISNUMBER(SEARCH("Payment - Concur",N26,1)),"WDL",IF(ISNUMBER(SEARCH("Payroll Transfer",N26,1)),"XFR",IF(ISNUMBER(SEARCH("XFR",N26,1)),"XFR",IF(H26>0,"RCT","WDL"))))) -> AP | L26: =VLOOKUP(D26,'Entity Code'!A:B,2,0) -> LCF | N26: Manual Payment - Default Resolution Network | O26: N/A | P26: N/A | Q26: Ladder to post

Sheet Cash Entries 11-5
A1: ENTITY | B1: YEARMONTH | C1: SOURCE | D1: BATCH ID | E1: BATCH DESCRIPTION | F1: BATCHDATE | G1: DR_AMT | H1: CR AMT | I1: TRXDATE | J1: DIST REFERENCE | K1: GPACCT
A2: LCF | B2: =Checklist!$B$1 -> 202511 | C2: GJ | D2: =Checklist!$B$7 -> DC1105251 | E2: =D2 -> DC1105251 | F2: =Checklist!$A$7 -> 45966 | G2: 88.15 | H2: 0 | I2: =$F$2 -> 45966 | J2: Payroll - Trinet service fee | K2: LCF -1745-0000-000-
A3: LCF | B3: =Checklist!$B$1 -> 202511 | C3: GJ | D3: =D2 -> DC1105251 | E3: =D3 -> DC1105251 | F3: =$F$2 -> 45966 | G3: 0 | H3: 88.15 | I3: =$F$2 -> 45966 | J3: Payroll - Trinet service fee | K3: LCF -1006-0000-000-
A4: LCREE | B4: =Checklist!$B$1 -> 202511 | C4: GJ | D4: DC1105252 | E4: =D4 -> DC1105252 | F4: =$F$2 -> 45966 | G4: 29914.14 | H4: 0 | I4: =$F$2 -> 45966 | J4: Excess Funds - DGPEO | K4: LCREE-1043-0000-000-
A5: LCREE | B5: =Checklist!$B$1 -> 202511 | C5: GJ | D5: =D4 -> DC1105252 | E5: =D5 -> DC1105252 | F5: =$F$2 -> 45966 | G5: 0 | H5: 29914.14 | I5: =$F$2 -> 45966 | J5: Excess Funds - DGPEO | K5: LCREE-1470-0000-000-DGPEO
B6: =Checklist!$B$1 -> 202511 | C6: GJ | D6: DC1105253 | E6: =D6 -> DC1105253 | F6: =$F$2 -> 45966 | I6: =$F$2 -> 45966
B7: =Checklist!$B$1 -> 202511 | C7: GJ | D7: =D6 -> DC1105253 | E7: =D7 -> DC1105253 | F7: =$F$2 -> 45966 | I7: =$F$2 -> 45966
B8: =Checklist!$B$1 -> 202511 | C8: GJ | D8: =D7 -> DC1105253 | E8: =D8 -> DC1105253 | F8: =$F$2 -> 45966 | I8: =$F$2 -> 45966
B9: =Checklist!$B$1 -> 202511 | C9: GJ | D9: =D8 -> DC1105253 | E9: =D9 -> DC1105253 | F9: =$F$2 -> 45966 | I9: =$F$2 -> 45966
B10: =Checklist!$B$1 -> 202511 | C10: GJ | D10: =D9 -> DC1105253 | E10: =D10 -> DC1105253 | F10: =$F$2 -> 45966 | I10: =$F$2 -> 45966
B11: =Checklist!$B$1 -> 202511 | C11: GJ | D11: =D10 -> DC1105253 | E11: =D11 -> DC1105253 | F11: =$F$2 -> 45966 | I11: =$F$2 -> 45966
B12: =Checklist!$B$1 -> 202511 | C12: GJ | D12: =D11 -> DC1105253 | E12: =D12 -> DC1105253 | F12: =$F$2 -> 45966 | I12: =$F$2 -> 45966
B13: =Checklist!$B$1 -> 202511 | C13: GJ | D13: =D12 -> DC1105253 | E13: =D13 -> DC1105253 | F13: =$F$2 -> 45966 | I13: =$F$2 -> 45966
B14: =Checklist!$B$1 -> 202511 | C14: GJ | D14: =D13 -> DC1105253 | E14: =D14 -> DC1105253 | F14: =$F$2 -> 45966 | I14: =$F$2 -> 45966
B15: =Checklist!$B$1 -> 202511 | C15: GJ | D15: =D14 -> DC1105253 | E15: =D15 -> DC1105253 | F15: =$F$2 -> 45966 | I15: =$F$2 -> 45966
B16: =Checklist!$B$1 -> 202511 | C16: GJ | D16: =D15 -> DC1105253 | E16: =D16 -> DC1105253 | F16: =$F$2 -> 45966 | I16: =$F$2 -> 45966
B17: =Checklist!$B$1 -> 202511 | C17: GJ | D17: =D16 -> DC1105253 | E17: =D17 -> DC1105253 | F17: =$F$2 -> 45966 | I17: =$F$2 -> 45966
B18: =Checklist!$B$1 -> 202511 | C18: GJ | D18: =D17 -> DC1105253 | E18: =D18 -> DC1105253 | F18: =$F$2 -> 45966 | I18: =$F$2 -> 45966
... B25: =Checklist!$B$1 -> 202511 | C25: GJ | D25: =D24 -> DC1105253 | E25: =D25 -> DC1105253 | F25: =$F$2 -> 45966 | I25: =$F$2 -> 45966

Sheet Cash Activity 11-6
A1: ="Daily Bank Activity - "&MONTH(Checklist!A8)&"/"&DAY(Checklist!A8)&"/"&YEAR(Checklist!A8) -> Daily Bank Activity - 11/6/2025
A2: Credit (+) / Debit (-)
B4: # | C4: Bank | D4: Acct Name | E4: Acct # | F4: Date | G4: Type | H4: Amount | I4: Bank Ref | J4: Bank Stmt Description | K4: Trans Type | L4: Entity | M4: AIT | N4: Short Description | O4: GL Account 1 | P4: GL Account 2 | Q4: Posted?
B5: 1 | C5: PNC | D5: LCFH REIT | E5: 8026459924 | F5: 45967 | G5: CR | H5: 4345.3 | I5: '00000000000 | J5: PNC SWEEP INTEREST @ 0.000000 EFFECTIVE DATE 11-05 | K5: =IF(ISNUMBER(SEARCH("Manual Payment - ",N5,1)),"AP",IF(ISNUMBER(SEARCH("Payment - Concur",N5,1)),"WDL",IF(ISNUMBER(SEARCH("Payroll Transfer",N5,1)),"XFR",IF(ISNUMBER(SEARCH("XFR",N5,1)),"XFR",IF(H5>0,"RCT","WDL"))))) -> RCT | L5: =VLOOKUP(D5,'Entity Code'!A:B,2,0) -> LCFHR | N5: Overnight interest sweep PNC LCFHR account. No entry required | O5: N/A | P5: N/A | Q5: N/A
B6: 2 | C6: PNC | D6: LCFH REIT | E6: 8026459924 | F6: 45967 | G6: CR | H6: 50350317 | I6: '00000000000 | J6: SWEEP TRANSFR FROM INVESTMENT ACCT 8026459924 | K6: =IF(ISNUMBER(SEARCH("Manual Payment - ",N6,1)),"AP",IF(ISNUMBER(SEARCH("Payment - Concur",N6,1)),"WDL",IF(ISNUMBER(SEARCH("Payroll Transfer",N6,1)),"XFR",IF(ISNUMBER(SEARCH("XFR",N6,1)),"XFR",IF(H6>0,"RCT","WDL"))))) -> RCT | L6: =VLOOKUP(D6,'Entity Code'!A:B,2,0) -> LCFHR | N6: Overnight interest sweep PNC LCFHR account. No entry required | O6: N/A | P6: N/A | Q6: N/A
B7: 3 | C7: PNC | D7: LCFH REIT | E7: 8026459924 | F7: 45967 | G7: DR | H7: -4694670.1 | I7: '00000000000 | J7: SWEEP TO INVESTMENT ACCT# 8026459924 | K7: =IF(ISNUMBER(SEARCH("Manual Payment - ",N7,1)),"AP",IF(ISNUMBER(SEARCH("Payment - Concur",N7,1)),"WDL",IF(ISNUMBER(SEARCH("Payroll Transfer",N7,1)),"XFR",IF(ISNUMBER(SEARCH("XFR",N7,1)),"XFR",IF(H7>0,"RCT","WDL"))))) -> WDL | L7: =VLOOKUP(D7,'Entity Code'!A:B,2,0) -> LCFHR | N7: Overnight interest sweep PNC LCFHR account. No entry required | O7: N/A | P7: N/A | Q7: N/A
B8: 4 | C8: PNC | D8: LCFH REIT | E8: 8026459924 | F8: 45967 | G8: DR | H8: -20020756 | I8: 'PAB6B3649K8H53PH | J8: WIRE TRANSFER ISO AMT:USD 20020755.56 STTLMT DATE: | K8: =IF(ISNUMBER(SEARCH("Manual Payment - ",N8,1)),"AP",IF(ISNUMBER(SEARCH("Payment - Concur",N8,1)),"WDL",IF(ISNUMBER(SEARCH("Payroll Transfer",N8,1)),"XFR",IF(ISNUMBER(SEARCH("XFR",N8,1)),"XFR",IF(H8>0,"RCT","WDL"))))) -> WDL | L8: =VLOOKUP(D8,'Entity Code'!A:B,2,0) -> LCFHR | N8: SocGen Paydown | O8: 2701-CAMR-000 | P8: N/A | Q8: SS&C to post
B9: 5 | C9: PNC | D9: CRE EQUITY | E9: 8026496039 | F9: 45967 | G9: DR | H9: -3621790.7 | I9: 'PAB6B1207DFI1AI3 | J9: WIRE TRANSFER ISO AMT:USD 3621790.73 STTLMT DATE:1 | K9: =IF(ISNUMBER(SEARCH("Manual Payment - ",N9,1)),"AP",IF(ISNUMBER(SEARCH("Payment - Concur",N9,1)),"WDL",IF(ISNUMBER(SEARCH("Payroll Transfer",N9,1)),"XFR",IF(ISNUMBER(SEARCH("XFR",N9,1)),"XFR",IF(H9>0,"RCT","WDL"))))) -> WDL | L9: =VLOOKUP(D9,'Entity Code'!A:B,2,0) -> LCREE | N9: Harps - Grove OK Mortgage Debt Payoff | O9: LCREE-1460-0000-000-GPGRO | P9: N/A | Q9: Ladder to post
B10: 6 | C10: PNC | D10: CRE EQUITY | E10: 8026496039 | F10: 45967 | G10: DR | H10: -901339.33 | I10: 'PAB6B1207ELI2XIA | J10: WIRE TRANSFER ISO AMT:USD 901339.33 STTLMT DATE:11 | K10: =IF(ISNUMBER(SEARCH("Manual Payment - ",N10,1)),"AP",IF(ISNUMBER(SEARCH("Payment - Concur",N10,1)),"WDL",IF(ISNUMBER(SEARCH("Payroll Transfer",N10,1)),"XFR",IF(ISNUMBER(SEARCH("XFR",N10,1)),"XFR",IF(H10>0,"RCT","WDL"))))) -> WDL | L10: =VLOOKUP(D10,'Entity Code'!A:B,2,0) -> LCREE | N10: DG - Wilmington IL Mortgage Debt Payoff | O10: LCREE-1460-0000-000-DGWIL | P10: N/A | Q10: Ladder to post
B11: 7 | C11: PNC | D11: CRE EQUITY | E11: 8026496039 | F11: 45967 | G11: DR | H11: -894856.79 | I11: 'PAB6B1207CKI0NHY | J11: WIRE TRANSFER ISO AMT:USD 894856.79 STTLMT DATE:11 | K11: =IF(ISNUMBER(SEARCH("Manual Payment - ",N11,1)),"AP",IF(ISNUMBER(SEARCH("Payment - Concur",N11,1)),"WDL",IF(ISNUMBER(SEARCH("Payroll Transfer",N11,1)),"XFR",IF(ISNUMBER(SEARCH("XFR",N11,1)),"XFR",IF(H11>0,"RCT","WDL"))))) -> WDL | L11: =VLOOKUP(D11,'Entity Code'!A:B,2,0) -> LCREE | N11: DG - Farmington IL Mortgage Debt Payoff | O11: LCREE-1460-0000-000-DGFAR | P11: N/A | Q11: Ladder to post
B12: 8 | C12: PNC | D12: CRE EQUITY | E12: 8026496039 | F12: 45967 | G12: DR | H12: -816503.21 | I12: 'PAB6B1207DPJ0O27 | J12: WIRE TRANSFER ISO AMT:USD 816503.21 STTLMT DATE:11 | K12: =IF(ISNUMBER(SEARCH("Manual Payment - ",N12,1)),"AP",IF(ISNUMBER(SEARCH("Payment - Concur",N12,1)),"WDL",IF(ISNUMBER(SEARCH("Payroll Transfer",N12,1)),"XFR",IF(ISNUMBER(SEARCH("XFR",N12,1)),"XFR",IF(H12>0,"RCT","WDL"))))) -> WDL | L12: =VLOOKUP(D12,'Entity Code'!A:B,2,0) -> LCREE | N12: DG - Bloomington IL Mortgage Debt Payoff | O12: LCREE-1460-0000-000-GPBLO | P12: N/A | Q12: Ladder to post
B13: 9 | C13: PNC | D13: CRE EQUITY | E13: 8026496039 | F13: 45967 | G13: DR | H13: -770801.43 | I13: 'PAB6B1207EDH3IDM | J13: WIRE TRANSFER ISO AMT:USD 770801.43 STTLMT DATE:11 | K13: =IF(ISNUMBER(SEARCH("Manual Payment - ",N13,1)),"AP",IF(ISNUMBER(SEARCH("Payment - Concur",N13,1)),"WDL",IF(ISNUMBER(SEARCH("Payroll Transfer",N13,1)),"XFR",IF(ISNUMBER(SEARCH("XFR",N13,1)),"XFR",IF(H13>0,"RCT","WDL"))))) -> WDL | L13: =VLOOKUP(D13,'Entity Code'!A:B,2,0) -> LCREE | N13: DG - Montrose MN Mortgage Debt Payoff | O13: LCREE-1460-0000-000-GPMON | P13: N/A | Q13: Ladder to post
B14: 10 | C14: PNC | D14: CRE EQUITY | E14: 8026496039 | F14: 45967 | G14: DR | H14: -738150.98 | I14: 'PAB6B1207CDJ4P22 | J14: WIRE TRANSFER ISO AMT:USD 738150.98 STTLMT DATE:11 | K14: =IF(ISNUMBER(SEARCH("Manual Payment - ",N14,1)),"AP",IF(ISNUMBER(SEARCH("Payment - Concur",N14,1)),"WDL",IF(ISNUMBER(SEARCH("Payroll Transfer",N14,1)),"XFR",IF(ISNUMBER(SEARCH("XFR",N14,1)),"XFR",IF(H14>0,"RCT","WDL"))))) -> WDL | L14: =VLOOKUP(D14,'Entity Code'!A:B,2,0) -> LCREE | N14: DG - Troy MO Mortgage Debt Payoff | O14: LCREE-1460-0000-000-GPTRO | P14: N/A | Q14: Ladder to post
B15: 11 | C15: PNC | D15: CRE EQUITY | E15: 8026496039 | F15: 45967 | G15: DR | H15: -738125.68 | I15: 'PAB6B1207CDH0DDF | J15: WIRE TRANSFER ISO AMT:USD 738125.68 STTLMT DATE:11 | K15: =IF(ISNUMBER(SEARCH("Manual Payment - ",N15,1)),"AP",IF(ISNUMBER(SEARCH("Payment - Concur",N15,1)),"WDL",IF(ISNUMBER(SEARCH("Payroll Transfer",N15,1)),"XFR",IF(ISNUMBER(SEARCH("XFR",N15,1)),"XFR",IF(H15>0,"RCT","WDL"))))) -> WDL | L15: =VLOOKUP(D15,'Entity Code'!A:B,2,0) -> LCREE | N15: DG - Danville IL Mortgage Debt Payoff | O15: LCREE-1460-0000-000-GPDAN | P15: N/A | Q15: Ladder to post
B16: 12 | C16: PNC | D16: CRE EQUITY | E16: 8026496039 | F16: 45967 | G16: DR | H16: -448415.46 | I16: 'PAB6B3649J9J3SXV | J16: WIRE TRANSFER ISO AMT:USD 448415.46 STTLMT DATE:11 | K16: =IF(ISNUMBER(SEARCH("Manual Payment - ",N16,1)),"AP",IF(ISNUMBER(SEARCH("Payment - Concur",N16,1)),"WDL",IF(ISNUMBER(SEARCH("Payroll Transfer",N16,1)),"XFR",IF(ISNUMBER(SEARCH("XFR",N16,1)),"XFR",IF(H16>0,"RCT","WDL"))))) -> WDL | L16: =VLOOKUP(D16,'Entity Code'!A:B,2,0) -> LCREE | N16: BofA Tracts C and G M&T Owners Account | O16: LCREE-1460-0000-000-BOAJV | P16: N/A | Q16: Ladder to post
B17: 13 | C17: PNC | D17: CRE EQUITY | E17: 8026496039 | F17: 45967 | G17: DR | H17: -243629.92 | I17: 'PAB6B3649FQI1HMZ | J17: WIRE TRANSFER ISO AMT:USD 243629.92 STTLMT DATE:11 | K17: =IF(ISNUMBER(SEARCH("Manual Payment - ",N17,1)),"AP",IF(ISNUMBER(SEARCH("Payment - Concur",N17,1)),"WDL",IF(ISNUMBER(SEARCH("Payroll Transfer",N17,1)),"XFR",IF(ISNUMBER(SEARCH("XFR",N17,1)),"XFR",IF(H17>0,"RCT","WDL"))))) -> WDL | L17: =VLOOKUP(D17,'Entity Code'!A:B,2,0) -> LCREE | N17: BofA Tract E M&T Owners Account | O17: LCREE-1460-0000-000-BOAJV | P17: N/A | Q17: Ladder to post
B18: 14 | C18: JPM | D18: LADDER CAPITAL CRE EQUITY LLC | E18: 528280121 | F18: 45967 | G18: Debit | H18: -16917.97 | I18: 0 | J18: DEPOSITED ITM RETURN | K18: =IF(ISNUMBER(SEARCH("Manual Payment - ",N18,1)),"AP",IF(ISNUMBER(SEARCH("Payment - Concur",N18,1)),"WDL",IF(ISNUMBER(SEARCH("Payroll Transfer",N18,1)),"XFR",IF(ISNUMBER(SEARCH("XFR",N18,1)),"XFR",IF(H18>0,"RCT","WDL"))))) -> WDL | L18: =VLOOKUP(D18,'Entity Code'!A:B,2,0) -> LCREE | N18: Check Deposited Return - DG - Effingham IL | Q18: Ladder to post
B19: 15 | C19: JPM | D19: LADDER CAPITAL FINANCE LLC TRADING | E19: 865357610 | F19: 45967 | G19: Credit | H19: 22000 | I19: 1069541310FF | J19: FEDWIRE CREDIT | K19: =IF(ISNUMBER(SEARCH("Manual Payment - ",N19,1)),"AP",IF(ISNUMBER(SEARCH("Payment - Concur",N19,1)),"WDL",IF(ISNUMBER(SEARCH("Payroll Transfer",N19,1)),"XFR",IF(ISNUMBER(SEARCH("XFR",N19,1)),"XFR",IF(H19>0,"RCT","WDL"))))) -> RCT | L19: =VLOOKUP(D19,'Entity Code'!A:B,2,0) -> LCF | N19: Float Payment - Village At Westfork | O19: 2701-LMS0-000 | P19: N/A | Q19: SS&C to post
B20: 16 | C20: PNC | D20: Tuebor REIT | E20: 8026495976 | F20: 45967 | G20: CR | H20: 182796.41 | I20: 'PAB685329J6H2IYK | J20: WIRE TRANSFER ISO AMT:USD 182796.41 STTLMT DATE:11 | K20: =IF(ISNUMBER(SEARCH("Manual Payment - ",N20,1)),"AP",IF(ISNUMBER(SEARCH("Payment - Concur",N20,1)),"WDL",IF(ISNUMBER(SEARCH("Payroll Transfer",N20,1)),"XFR",IF(ISNUMBER(SEARCH("XFR",N20,1)),"XFR",IF(H20>0,"RCT","WDL"))))) -> RCT | L20: =VLOOKUP(D20,'Entity Code'!A:B,2,0) -> TUERI | N20: Trimont Return Funds: Central Florida Resource Center - Future Funding Advance #1 | O20: 2701-LMS0-000 | P20: N/A | Q20: SS&C to post
B21: 17 | C21: PNC | D21: CRE EQUITY | E21: 8026496039 | F21: 45967 | G21: CR | H21: 243629.92 | I21: '25B6D3111GKZ212H | J21: WIRE TRANSFER ISO AMT:USD 243629.92 STTLMT DATE:11 | K21: =IF(ISNUMBER(SEARCH("Manual Payment - ",N21,1)),"AP",IF(ISNUMBER(SEARCH("Payment - Concur",N21,1)),"WDL",IF(ISNUMBER(SEARCH("Payroll Transfer",N21,1)),"XFR",IF(ISNUMBER(SEARCH("XFR",N21,1)),"XFR",IF(H21>0,"RCT","WDL"))))) -> RCT | L21: =VLOOKUP(D21,'Entity Code'!A:B,2,0) -> LCREE | N21: Bank of America Campus Jacksonville Tract E | O21: LCREE-1470-0000-000-BOAJV | P21: N/A | Q21: Ladder to post
B22: 18 | C22: PNC | D22: CRE EQUITY | E22: 8026496039 | F22: 45967 | G22: CR | H22: 448415.46 | I22: '25B6C2645DGZ4XWD | J22: WIRE TRANSFER ISO AMT:USD 448415.46 STTLMT DATE:11 | K22: =IF(ISNUMBER(SEARCH("Manual Payment - ",N22,1)),"AP",IF(ISNUMBER(SEARCH("Payment - Concur",N22,1)),"WDL",IF(ISNUMBER(SEARCH("Payroll Transfer",N22,1)),"XFR",IF(ISNUMBER(SEARCH("XFR",N22,1)),"XFR",IF(H22>0,"RCT","WDL"))))) -> RCT | L22: =VLOOKUP(D22,'Entity Code'!A:B,2,0) -> LCREE | N22: Bank of America Campus Jacksonville Tracts C and G | O22: LCREE-1470-0000-000-BOAJV | P22: N/A | Q22: Ladder to post
B23: 19 | C23: PNC | D23: LCI | E23: 8026496012 | F23: 45967 | G23: CR | H23: 35121.51 | I23: '25B6E320154056GN | J23: BOOK TRANSFER CREDIT 0056GN ORIGINATOR:TUEBOR TRS | K23: =IF(ISNUMBER(SEARCH("Manual Payment - ",N23,1)),"AP",IF(ISNUMBER(SEARCH("Payment - Concur",N23,1)),"WDL",IF(ISNUMBER(SEARCH("Payroll Transfer",N23,1)),"XFR",IF(ISNUMBER(SEARCH("XFR",N23,1)),"XFR",IF(H23>0,"RCT","WDL"))))) -> RCT | L23: =VLOOKUP(D23,'Entity Code'!A:B,2,0) -> LCI | N23: IC Loan Interest Settlement | O23: 2701-CAMR-000 | P23: N/A | Q23: SS&C to post
B24: 19 | C24: PNC | D24: Tuebor TRS4 | E24: 8180060487 | F24: 45967 | G24: DR | H24: -35121.51 | I24: '25B6E320154056GN | J24: BOOK TRANSFER DEBIT 0056GN ORIGINATOR:TUEBOR TRS I | K24: =IF(ISNUMBER(SEARCH("Manual Payment - ",N24,1)),"AP",IF(ISNUMBER(SEARCH("Payment - Concur",N24,1)),"WDL",IF(ISNUMBER(SEARCH("Payroll Transfer",N24,1)),"XFR",IF(ISNUMBER(SEARCH("XFR",N24,1)),"XFR",IF(H24>0,"RCT","WDL"))))) -> WDL | L24: =VLOOKUP(D24,'Entity Code'!A:B,2,0) -> TUET4 | N24: IC Loan Interest Settlement | O24: 2701-CAMR-000 | P24: N/A | Q24: SS&C to post
B25: 20 | C25: PNC | D25: LCI | E25: 8026496012 | F25: 45967 | G25: CR | H25: 6515000 | I25: '25B6E32014W133HC | J25: BOOK TRANSFER CREDIT 0033HC ORIGINATOR:LADDER CAPI | K25: =IF(ISNUMBER(SEARCH("Manual Payment - ",N25,1)),"AP",IF(ISNUMBER(SEARCH("Payment - Concur",N25,1)),"WDL",IF(ISNUMBER(SEARCH("Payroll Transfer",N25,1)),"XFR",IF(ISNUMBER(SEARCH("XFR",N25,1)),"XFR",IF(H25>0,"RCT","WDL"))))) -> XFR | L25: =VLOOKUP(D25,'Entity Code'!A:B,2,0) -> LCI | N25: XFR from LCFHR PNC to LCI PNC | O25: 2701-CAMR-000 | P25: N/A | Q25: SS&C to post
B26: 20 | C26: PNC | D26: LCFH REIT | E26: 8026459924 | F26: 45967 | G26: DR | H26: -6515000 | I26: '25B6E32014W133HC | J26: BOOK TRANSFER DEBIT 0033HC ORIGINATOR:LADDER CAPIT | K26: =IF(ISNUMBER(SEARCH("Manual Payment - ",N26,1)),"AP",IF(ISNUMBER(SEARCH("Payment - Concur",N26,1)),"WDL",IF(ISNUMBER(SEARCH("Payroll Transfer",N26,1)),"XFR",IF(ISNUMBER(SEARCH("XFR",N26,1)),"XFR",IF(H26>0,"RCT","WDL"))))) -> XFR | L26: =VLOOKUP(D26,'Entity Code'!A:B,2,0) -> LCFHR | N26: XFR from LCFHR PNC to LCI PNC | O26: 2701-CAMR-000 | P26: N/A | Q26: SS&C to post
B27: 21 | C27: PNC | D27: LCFH REIT | E27: 8026459924 | F27: 45967 | G27: CR | H27: 6550063.6 | I27: '25B6E39597M03TCL | J27: BOOK TRANSFER CREDIT 003TCL ORIGINATOR:LADDER CAPI | K27: =IF(ISNUMBER(SEARCH("Manual Payment - ",N27,1)),"AP",IF(ISNUMBER(SEARCH("Payment - Concur",N27,1)),"WDL",IF(ISNUMBER(SEARCH("Payroll Transfer",N27,1)),"XFR",IF(ISNUMBER(SEARCH("XFR",N27,1)),"XFR",IF(H27>0,"RCT","WDL"))))) -> RCT | L27: =VLOOKUP(D27,'Entity Code'!A:B,2,0) -> LCFHR | N27: IC Loan Interest Settlement | O27: 2701-CAMR-000 | P27: N/A | Q27: SS&C to post
B28: 21 | C28: PNC | D28: LCI | E28: 8026496012 | F28: 45967 | G28: DR | H28: -6550063.6 | I28: '25B6E39597M03TCL | J28: BOOK TRANSFER DEBIT 003TCL ORIGINATOR:LADDER CAPIT | K28: =IF(ISNUMBER(SEARCH("Manual Payment - ",N28,1)),"AP",IF(ISNUMBER(SEARCH("Payment - Concur",N28,1)),"WDL",IF(ISNUMBER(SEARCH("Payroll Transfer",N28,1)),"XFR",IF(ISNUMBER(SEARCH("XFR",N28,1)),"XFR",IF(H28>0,"RCT","WDL"))))) -> WDL | L28: =VLOOKUP(D28,'Entity Code'!A:B,2,0) -> LCI | N28: IC Loan Interest Settlement | O28: 2701-CAMR-000 | P28: N/A | Q28: SS&C to post
B29: 22 | C29: PNC | D29: LCC | E29: 8026482868 | F29: 45967 | G29: CR | H29: 1053300 | I29: '25B6E39598J175CO | J29: BOOK TRANSFER CREDIT 0075CO ORIGINATOR:LADDER CAPI | K29: =IF(ISNUMBER(SEARCH("Manual Payment - ",N29,1)),"AP",IF(ISNUMBER(SEARCH("Payment - Concur",N29,1)),"WDL",IF(ISNUMBER(SEARCH("Payroll Transfer",N29,1)),"XFR",IF(ISNUMBER(SEARCH("XFR",N29,1)),"XFR",IF(H29>0,"RCT","WDL"))))) -> XFR | L29: =VLOOKUP(D29,'Entity Code'!A:B,2,0) -> LCC | N29: XFR from LCFHR PNC to LCC | O29: 2701-CAMR-000 | P29: N/A | Q29: SS&C to post
B30: 22 | C30: PNC | D30: LCFH REIT | E30: 8026459924 | F30: 45967 | G30: DR | H30: -1053300 | I30: '25B6E39598J175CO | J30: BOOK TRANSFER DEBIT 0075CO ORIGINATOR:LADDER CAPIT | K30: =IF(ISNUMBER(SEARCH("Manual Payment - ",N30,1)),"AP",IF(ISNUMBER(SEARCH("Payment - Concur",N30,1)),"WDL",IF(ISNUMBER(SEARCH("Payroll Transfer",N30,1)),"XFR",IF(ISNUMBER(SEARCH("XFR",N30,1)),"XFR",IF(H30>0,"RCT","WDL"))))) -> XFR | L30: =VLOOKUP(D30,'Entity Code'!A:B,2,0) -> LCFHR | N30: XFR from LCFHR PNC to LCC | O30: 2701-CAMR-000 | P30: N/A | Q30: SS&C to post
B31: 23 | C31: PNC | D31: LC TRS I | E31: 8026495984 | F31: 45967 | G31: CR | H31: 1053397.1 | I31: '25B6E39594T03TCJ | J31: BOOK TRANSFER CREDIT 003TCJ ORIGINATOR:LADDER CAPI | K31: =IF(ISNUMBER(SEARCH("Manual Payment - ",N31,1)),"AP",IF(ISNUMBER(SEARCH("Payment - Concur",N31,1)),"WDL",IF(ISNUMBER(SEARCH("Payroll Transfer",N31,1)),"XFR",IF(ISNUMBER(SEARCH("XFR",N31,1)),"XFR",IF(H31>0,"RCT","WDL"))))) -> RCT | L31: =VLOOKUP(D31,'Entity Code'!A:B,2,0) -> LTRS1 | N31: IC Loan Interest Settlement | O31: 2701-CAMR-000 | P31: N/A | Q31: SS&C to post
... B52: 33 | C52: PNC | D52: LCC | E52: 8026482868 | F52: 45967 | G52: DR | H52: -7200000 | I52: '25B6F3619OOZ5435 | J52: BOOK TRANSFER DEBIT 005435 ORIGINATOR:LADDER CAPIT | K52: =IF(ISNUMBER(SEARCH("Manual Payment - ",N52,1)),"AP",IF(ISNUMBER(SEARCH("Payment - Concur",N52,1)),"WDL",IF(ISNUMBER(SEARCH("Payroll Transfer",N52,1)),"XFR",IF(ISNUMBER(SEARCH("XFR",N52,1)),"XFR",IF(H52>0,"RCT","WDL"))))) -> XFR | L52: =VLOOKUP(D52,'Entity Code'!A:B,2,0) -> LCC | N52: XFR from LCC to LCFHR PNC | O52: 2701-CAMR-000 | P52: N/A | Q52: SS&C to post
B53: 34 | C53: PNC | D53: CRE EQUITY | E53: 8026496039 | F53: 45967 | G53: CR | H53: 8100000 | I53: '25B6F574371Z4JR8 | J53: BOOK TRANSFER CREDIT 004JR8 ORIGINATOR:LADDER CAPI | K53: =IF(ISNUMBER(SEARCH("Manual Payment - ",N53,1)),"AP",IF(ISNUMBER(SEARCH("Payment - Concur",N53,1)),"WDL",IF(ISNUMBER(SEARCH("Payroll Transfer",N53,1)),"XFR",IF(ISNUMBER(SEARCH("XFR",N53,1)),"XFR",IF(H53>0,"RCT","WDL"))))) -> XFR | L53: =VLOOKUP(D53,'Entity Code'!A:B,2,0) -> LCREE | N53: XFR from LCFHR PNC to LCREE PNC | O53: =IFERROR(VLOOKUP(E54,'Bank Account'!A:B,2,FALSE),VLOOKUP(_xlfn.NUMBERVALUE(E54),'Bank Account'!A:B,2,FALSE)) -> LCFHR-1065-0002-000- | P53: N/A | Q53: Ladder to post
B54: 34 | C54: PNC | D54: LCFH REIT | E54: 8026459924 | F54: 45967 | G54: DR | H54: -8100000 | I54: '25B6F574371Z4JR8 | J54: BOOK TRANSFER DEBIT 004JR8 ORIGINATOR:LADDER CAPIT | K54: =IF(ISNUMBER(SEARCH("Manual Payment - ",N54,1)),"AP",IF(ISNUMBER(SEARCH("Payment - Concur",N54,1)),"WDL",IF(ISNUMBER(SEARCH("Payroll Transfer",N54,1)),"XFR",IF(ISNUMBER(SEARCH("XFR",N54,1)),"XFR",IF(H54>0,"RCT","WDL"))))) -> XFR | L54: =VLOOKUP(D54,'Entity Code'!A:B,2,0) -> LCFHR | N54: XFR from LCFHR PNC to LCREE PNC | O54: =IFERROR(VLOOKUP(E53,'Bank Account'!A:B,2,FALSE),VLOOKUP(_xlfn.NUMBERVALUE(E53),'Bank Account'!A:B,2,FALSE)) -> LCREE-1065-0008-000- | P54: N/A | Q54: Ladder to post
B55: 35 | C55: PNC | D55: LCFH REIT | E55: 8026459924 | F55: 45967 | G55: DR | H55: -18000000 | I55: 'PAB6E1658NFH3CWA | J55: WIRE TRANSFER ISO AMT:USD 18000000.00 STTLMT DATE: | K55: =IF(ISNUMBER(SEARCH("Manual Payment - ",N55,1)),"AP",IF(ISNUMBER(SEARCH("Payment - Concur",N55,1)),"WDL",IF(ISNUMBER(SEARCH("Payroll Transfer",N55,1)),"XFR",IF(ISNUMBER(SEARCH("XFR",N55,1)),"XFR",IF(H55>0,"RCT","WDL"))))) -> XFR | L55: =VLOOKUP(D55,'Entity Code'!A:B,2,0) -> LCFHR | N55: XFR from LCFHR PNC to LCFHR BNY | O55: 2701-CAMR-000 | P55: N/A | Q55: SS&C to post
B56: 36 | C56: PNC | D56: LCI | E56: 8026496012 | F56: 45967 | G56: CR | H56: 180000 | I56: '25B6J1658OH078I7 | J56: BOOK TRANSFER CREDIT 0078I7 ORIGINATOR:TUEBOR REIT | K56: =IF(ISNUMBER(SEARCH("Manual Payment - ",N56,1)),"AP",IF(ISNUMBER(SEARCH("Payment - Concur",N56,1)),"WDL",IF(ISNUMBER(SEARCH("Payroll Transfer",N56,1)),"XFR",IF(ISNUMBER(SEARCH("XFR",N56,1)),"XFR",IF(H56>0,"RCT","WDL"))))) -> RCT | L56: =VLOOKUP(D56,'Entity Code'!A:B,2,0) -> LCI | N56: Capital Distribution | O56: 3800-0000-000 | P56: N/A | Q56: SS&C to post
B57: 36 | C57: PNC | D57: Tuebor REIT | E57: 8026495976 | F57: 45967 | G57: DR | H57: -180000 | I57: '25B6J1658OH078I7 | J57: BOOK TRANSFER DEBIT 0078I7 ORIGINATOR:TUEBOR REIT | K57: =IF(ISNUMBER(SEARCH("Manual Payment - ",N57,1)),"AP",IF(ISNUMBER(SEARCH("Payment - Concur",N57,1)),"WDL",IF(ISNUMBER(SEARCH("Payroll Transfer",N57,1)),"XFR",IF(ISNUMBER(SEARCH("XFR",N57,1)),"XFR",IF(H57>0,"RCT","WDL"))))) -> WDL | L57: =VLOOKUP(D57,'Entity Code'!A:B,2,0) -> TUERI | N57: Capital Distribution | O57: 1450-0000-000 | P57: N/A | Q57: SS&C to post
B58: 37 | C58: PNC | D58: LCFH REIT | E58: 8026459924 | F58: 45967 | G58: CR | H58: 180000 | I58: '25B6J1658IGZ89CF | J58: BOOK TRANSFER CREDIT 0089CF ORIGINATOR:LADDER CAPI | K58: =IF(ISNUMBER(SEARCH("Manual Payment - ",N58,1)),"AP",IF(ISNUMBER(SEARCH("Payment - Concur",N58,1)),"WDL",IF(ISNUMBER(SEARCH("Payroll Transfer",N58,1)),"XFR",IF(ISNUMBER(SEARCH("XFR",N58,1)),"XFR",IF(H58>0,"RCT","WDL"))))) -> XFR | L58: =VLOOKUP(D58,'Entity Code'!A:B,2,0) -> LCFHR | N58: XFR from LCI PNC to LCFHR PNC | O58: 2701-CAMR-000 | P58: N/A | Q58: SS&C to post
B59: 37 | C59: PNC | D59: LCI | E59: 8026496012 | F59: 45967 | G59: DR | H59: -180000 | I59: '25B6J1658IGZ89CF | J59: BOOK TRANSFER DEBIT 0089CF ORIGINATOR:LADDER CAPIT | K59: =IF(ISNUMBER(SEARCH("Manual Payment - ",N59,1)),"AP",IF(ISNUMBER(SEARCH("Payment - Concur",N59,1)),"WDL",IF(ISNUMBER(SEARCH("Payroll Transfer",N59,1)),"XFR",IF(ISNUMBER(SEARCH("XFR",N59,1)),"XFR",IF(H59>0,"RCT","WDL"))))) -> XFR | L59: =VLOOKUP(D59,'Entity Code'!A:B,2,0) -> LCI | N59: XFR from LCI PNC to LCFHR PNC | O59: 2701-CAMR-000 | P59: N/A | Q59: SS&C to post
B60: 38 | C60: JPM | D60: Ladder Capital Finance Holdings REIT | E60: 657597873 | F60: 45967 | G60: Credit | H60: 830000 | I60: 1005585310SB | J60: ATS CREDIT MEMO | K60: =IF(ISNUMBER(SEARCH("Manual Payment - ",N60,1)),"AP",IF(ISNUMBER(SEARCH("Payment - Concur",N60,1)),"WDL",IF(ISNUMBER(SEARCH("Payroll Transfer",N60,1)),"XFR",IF(ISNUMBER(SEARCH("XFR",N60,1)),"XFR",IF(H60>0,"RCT","WDL"))))) -> XFR | L60: =VLOOKUP(D60,'Entity Code'!A:B,2,0) -> LCFHR | N60: XFR from LCREE to LCFHR Trading | O60: =IFERROR(VLOOKUP(E61,'Bank Account'!A:B,2,FALSE),VLOOKUP(_xlfn.NUMBERVALUE(E61),'Bank Account'!A:B,2,FALSE)) -> LCREE-1043-0000-000- | P60: N/A | Q60: Ladder to post
B61: 38 | C61: JPM | D61: LADDER CAPITAL CRE EQUITY LLC | E61: 528280121 | F61: 45967 | G61: Debit | H61: -830000 | I61: 1005585310SB | J61: ATS DEBIT MEMO | K61: =IF(ISNUMBER(SEARCH("Manual Payment - ",N61,1)),"AP",IF(ISNUMBER(SEARCH("Payment - Concur",N61,1)),"WDL",IF(ISNUMBER(SEARCH("Payroll Transfer",N61,1)),"XFR",IF(ISNUMBER(SEARCH("XFR",N61,1)),"XFR",IF(H61>0,"RCT","WDL"))))) -> XFR | L61: =VLOOKUP(D61,'Entity Code'!A:B,2,0) -> LCREE | N61: XFR from LCREE to LCFHR Trading | O61: =IFERROR(VLOOKUP(E60,'Bank Account'!A:B,2,FALSE),VLOOKUP(_xlfn.NUMBERVALUE(E60),'Bank Account'!A:B,2,FALSE)) -> LCFHR-1046-0000-000- | P61: N/A | Q61: Ladder to post
B62: 39 | C62: PNC | D62: LCFH REIT | E62: 8026459924 | F62: 45967 | G62: CR | H62: 830000 | I62: '25B6M17102T06ESF | J62: WIRE TRANSFER ISO AMT:USD 830000.00 STTLMT DATE:11 | K62: =IF(ISNUMBER(SEARCH("Manual Payment - ",N62,1)),"AP",IF(ISNUMBER(SEARCH("Payment - Concur",N62,1)),"WDL",IF(ISNUMBER(SEARCH("Payroll Transfer",N62,1)),"XFR",IF(ISNUMBER(SEARCH("XFR",N62,1)),"XFR",IF(H62>0,"RCT","WDL"))))) -> XFR | L62: =VLOOKUP(D62,'Entity Code'!A:B,2,0) -> LCFHR | N62: XFR from LCFHR to LCFHR PNC | O62: 2701-CAMR-000 | P62: N/A | Q62: SS&C to post
B63: 39 | C63: JPM | D63: Ladder Capital Finance Holdings REIT | E63: 657597873 | F63: 45967 | G63: Debit | H63: -830000 | I63: 9821000310JO | J63: FEDWIRE DEBIT | K63: =IF(ISNUMBER(SEARCH("Manual Payment - ",N63,1)),"AP",IF(ISNUMBER(SEARCH("Payment - Concur",N63,1)),"WDL",IF(ISNUMBER(SEARCH("Payroll Transfer",N63,1)),"XFR",IF(ISNUMBER(SEARCH("XFR",N63,1)),"XFR",IF(H63>0,"RCT","WDL"))))) -> XFR | L63: =VLOOKUP(D63,'Entity Code'!A:B,2,0) -> LCFHR | N63: XFR from LCFHR to LCFHR PNC | O63: 2701-CAMR-000 | P63: N/A | Q63: SS&C to post
B64: 40 | C64: PNC | D64: Ladder Capital Finance | E64: 8026459916 | F64: 45967 | G64: CR | H64: 80000 | I64: '25B6J2749MYZ6BCL | J64: BOOK TRANSFER CREDIT 006BCL ORIGINATOR:LADDER CAPI | K64: =IF(ISNUMBER(SEARCH("Manual Payment - ",N64,1)),"AP",IF(ISNUMBER(SEARCH("Payment - Concur",N64,1)),"WDL",IF(ISNUMBER(SEARCH("Payroll Transfer",N64,1)),"XFR",IF(ISNUMBER(SEARCH("XFR",N64,1)),"XFR",IF(H64>0,"RCT","WDL"))))) -> XFR | L64: =VLOOKUP(D64,'Entity Code'!A:B,2,0) -> LCF | N64: XFR from LCF PNC Loan Dep to LCF PNC | O64: 2701-LMS0-000 | P64: N/A | Q64: SS&C to post
B65: 40 | C65: PNC | D65: LCF Borrower Deposits | E65: 8026478877 | F65: 45967 | G65: DR | H65: -80000 | I65: '25B6J2749MYZ6BCL | J65: BOOK TRANSFER DEBIT 006BCL ORIGINATOR:LADDER CAPIT | K65: =IF(ISNUMBER(SEARCH("Manual Payment - ",N65,1)),"AP",IF(ISNUMBER(SEARCH("Payment - Concur",N65,1)),"WDL",IF(ISNUMBER(SEARCH("Payroll Transfer",N65,1)),"XFR",IF(ISNUMBER(SEARCH("XFR",N65,1)),"XFR",IF(H65>0,"RCT","WDL"))))) -> XFR | L65: =VLOOKUP(D65,'Entity Code'!A:B,2,0) -> LCF | N65: XFR from LCF PNC Loan Dep to LCF PNC | O65: 2701-LMS0-000 | P65: N/A | Q65: SS&C to post
B66: 41 | C66: PNC | D66: LCI | E66: 8026496012 | F66: 45967 | G66: CR | H66: 514000 | I66: '25B6M19419S16CPY | J66: BOOK TRANSFER CREDIT 006CPY ORIGINATOR:LADDER CAPI | K66: =IF(ISNUMBER(SEARCH("Manual Payment - ",N66,1)),"AP",IF(ISNUMBER(SEARCH("Payment - Concur",N66,1)),"WDL",IF(ISNUMBER(SEARCH("Payroll Transfer",N66,1)),"XFR",IF(ISNUMBER(SEARCH("XFR",N66,1)),"XFR",IF(H66>0,"RCT","WDL"))))) -> XFR | L66: =VLOOKUP(D66,'Entity Code'!A:B,2,0) -> LCI | N66: XFR from LCFHR PNC to LCI PNC | O66: 2701-CAMR-000 | P66: N/A | Q66: SS&C to post
B67: 41 | C67: PNC | D67: LCFH REIT | E67: 8026459924 | F67: 45967 | G67: DR | H67: -514000 | I67: '25B6M19419S16CPY | J67: BOOK TRANSFER DEBIT 006CPY ORIGINATOR:LADDER CAPIT | K67: =IF(ISNUMBER(SEARCH("Manual Payment - ",N67,1)),"AP",IF(ISNUMBER(SEARCH("Payment - Concur",N67,1)),"WDL",IF(ISNUMBER(SEARCH("Payroll Transfer",N67,1)),"XFR",IF(ISNUMBER(SEARCH("XFR",N67,1)),"XFR",IF(H67>0,"RCT","WDL"))))) -> XFR | L67: =VLOOKUP(D67,'Entity Code'!A:B,2,0) -> LCFHR | N67: XFR from LCFHR PNC to LCI PNC | O67: 2701-CAMR-000 | P67: N/A | Q67: SS&C to post
B68: 42 | C68: PNC | D68: LCI | E68: 8026496012 | F68: 45967 | G68: DR | H68: -514000 | I68: 'PAB6H19419VJ3RD6 | J68: WIRE TRANSFER ISO AMT:USD 514000.00 STTLMT DATE:11 | K68: =IF(ISNUMBER(SEARCH("Manual Payment - ",N68,1)),"AP",IF(ISNUMBER(SEARCH("Payment - Concur",N68,1)),"WDL",IF(ISNUMBER(SEARCH("Payroll Transfer",N68,1)),"XFR",IF(ISNUMBER(SEARCH("XFR",N68,1)),"XFR",IF(H68>0,"RCT","WDL"))))) -> XFR | L68: =VLOOKUP(D68,'Entity Code'!A:B,2,0) -> LCI | N68: XFR from LCI PNC to LCFP Equity PB | O68: 2701-CAMR-000 | P68: N/A | Q68: SS&C to post
B69: 43 | C69: PNC | D69: CRE EQUITY | E69: 8026496039 | F69: 45967 | G69: CR | H69: 55915.62 | I69: '25B6D4342PG16QNP | J69: WIRE TRANSFER ISO AMT:USD 55915.62 STTLMT DATE:110 | K69: =IF(ISNUMBER(SEARCH("Manual Payment - ",N69,1)),"AP",IF(ISNUMBER(SEARCH("Payment - Concur",N69,1)),"WDL",IF(ISNUMBER(SEARCH("Payroll Transfer",N69,1)),"XFR",IF(ISNUMBER(SEARCH("XFR",N69,1)),"XFR",IF(H69>0,"RCT","WDL"))))) -> RCT | L69: =VLOOKUP(D69,'Entity Code'!A:B,2,0) -> LCREE | N69: Nov RE Remit - BJPL2V | O69: LCREE-1470-0000-000-BJPL2 | P69: N/A | Q69: Ladder to post
B70: 43 | C70: PNC | D70: CRE EQUITY | E70: 8026496039 | F70: 45967 | G70: CR | H70: 50537.45 | I70: '25B6D1604BQ12A5R | J70: WIRE TRANSFER ISO AMT:USD 50537.45 STTLMT DATE:110 | K70: =IF(ISNUMBER(SEARCH("Manual Payment - ",N70,1)),"AP",IF(ISNUMBER(SEARCH("Payment - Concur",N70,1)),"WDL",IF(ISNUMBER(SEARCH("Payroll Transfer",N70,1)),"XFR",IF(ISNUMBER(SEARCH("XFR",N70,1)),"XFR",IF(H70>0,"RCT","WDL"))))) -> RCT | L70: =VLOOKUP(D70,'Entity Code'!A:B,2,0) -> LCREE | N70: Nov RE Remit - BJPL2S | O70: LCREE-1470-0000-000-BJPL2 | P70: N/A | Q70: Ladder to post
B71: 43 | C71: PNC | D71: CRE EQUITY | E71: 8026496039 | F71: 45967 | G71: CR | H71: 44174.89 | I71: '25B6B5043L402XWU | J71: WIRE TRANSFER ISO AMT:USD 44174.89 STTLMT DATE:110 | K71: =IF(ISNUMBER(SEARCH("Manual Payment - ",N71,1)),"AP",IF(ISNUMBER(SEARCH("Payment - Concur",N71,1)),"WDL",IF(ISNUMBER(SEARCH("Payroll Transfer",N71,1)),"XFR",IF(ISNUMBER(SEARCH("XFR",N71,1)),"XFR",IF(H71>0,"RCT","WDL"))))) -> RCT | L71: =VLOOKUP(D71,'Entity Code'!A:B,2,0) -> LCREE | N71: Nov RE Remit - BJPL2M | O71: LCREE-1470-0000-000-BJPL2 | P71: N/A | Q71: Ladder to post
B72: 43 | C72: PNC | D72: CRE EQUITY | E72: 8026496039 | F72: 45967 | G72: CR | H72: 11400.16 | I72: '25B6D2346ES17VMC | J72: WIRE TRANSFER ISO AMT:USD 11400.16 STTLMT DATE:110 | K72: =IF(ISNUMBER(SEARCH("Manual Payment - ",N72,1)),"AP",IF(ISNUMBER(SEARCH("Payment - Concur",N72,1)),"WDL",IF(ISNUMBER(SEARCH("Payroll Transfer",N72,1)),"XFR",IF(ISNUMBER(SEARCH("XFR",N72,1)),"XFR",IF(H72>0,"RCT","WDL"))))) -> RCT | L72: =VLOOKUP(D72,'Entity Code'!A:B,2,0) -> LCREE | N72: Nov RE Remit - LWMIL | O72: LCREE-1470-0000-000-LWMIL | P72: N/A | Q72: Ladder to post
B73: 43 | C73: PNC | D73: CRE EQUITY | E73: 8026496039 | F73: 45967 | G73: CR | H73: 11114.01 | I73: '25B6D05128L043MJ | J73: WIRE TRANSFER ISO AMT:USD 11114.01 STTLMT DATE:110 | K73: =IF(ISNUMBER(SEARCH("Manual Payment - ",N73,1)),"AP",IF(ISNUMBER(SEARCH("Payment - Concur",N73,1)),"WDL",IF(ISNUMBER(SEARCH("Payroll Transfer",N73,1)),"XFR",IF(ISNUMBER(SEARCH("XFR",N73,1)),"XFR",IF(H73>0,"RCT","WDL"))))) -> RCT | L73: =VLOOKUP(D73,'Entity Code'!A:B,2,0) -> LCREE | N73: Nov RE Remit - WGPLM | O73: LCREE-1470-0000-000-WGPLM | P73: N/A | Q73: Ladder to post
B74: 43 | C74: PNC | D74: CRE EQUITY | E74: 8026496039 | F74: 45967 | G74: CR | H74: 8417.64 | I74: '25B6C33229211VS1 | J74: WIRE TRANSFER ISO AMT:USD 8417.64 STTLMT DATE:1106 | K74: =IF(ISNUMBER(SEARCH("Manual Payment - ",N74,1)),"AP",IF(ISNUMBER(SEARCH("Payment - Concur",N74,1)),"WDL",IF(ISNUMBER(SEARCH("Payroll Transfer",N74,1)),"XFR",IF(ISNUMBER(SEARCH("XFR",N74,1)),"XFR",IF(H74>0,"RCT","WDL"))))) -> RCT | L74: =VLOOKUP(D74,'Entity Code'!A:B,2,0) -> LCREE | N74: Nov RE Remit - LWGAR | O74: LCREE-1470-0000-000-LWGAR | P74: N/A | Q74: Ladder to post
B75: 43 | C75: PNC | D75: CRE EQUITY | E75: 8026496039 | F75: 45967 | G75: CR | H75: 7393.74 | I75: '25B6D05002R043IR | J75: WIRE TRANSFER ISO AMT:USD 7393.74 STTLMT DATE:1106 | K75: =IF(ISNUMBER(SEARCH("Manual Payment - ",N75,1)),"AP",IF(ISNUMBER(SEARCH("Payment - Concur",N75,1)),"WDL",IF(ISNUMBER(SEARCH("Payroll Transfer",N75,1)),"XFR",IF(ISNUMBER(SEARCH("XFR",N75,1)),"XFR",IF(H75>0,"RCT","WDL"))))) -> RCT | L75: =VLOOKUP(D75,'Entity Code'!A:B,2,0) -> LCREE | N75: Nov RE Remit - WGAIK | O75: LCREE-1470-0000-000-WGAIK | P75: N/A | Q75: Ladder to post
... B80: 43 | C80: PNC | D80: CRE EQUITY | E80: 8026496039 | F80: 45967 | G80: CR | H80: 40.47 | I80: '25B6E2122I9175K0 | J80: WIRE TRANSFER ISO AMT:USD 40.47 STTLMT DATE:110620 | K80: =IF(ISNUMBER(SEARCH("Manual Payment - ",N80,1)),"AP",IF(ISNUMBER(SEARCH("Payment - Concur",N80,1)),"WDL",IF(ISNUMBER(SEARCH("Payroll Transfer",N80,1)),"XFR",IF(ISNUMBER(SEARCH("XFR",N80,1)),"XFR",IF(H80>0,"RCT","WDL"))))) -> RCT | L80: =VLOOKUP(D80,'Entity Code'!A:B,2,0) -> LCREE | N80: Nov RE Remit - LDGSS | O80: LCREE-1470-0000-000-LDGSS | P80: N/A | Q80: Ladder to post
B81: 44 | C81: JPM | D81: LADDER CAPITAL CRE EQUITY LLC | E81: 528280121 | F81: 45967 | G81: Credit | H81: 55476.06 | I81: 0091934310FC | J81: CHIPS CREDIT | K81: =IF(ISNUMBER(SEARCH("Manual Payment - ",N81,1)),"AP",IF(ISNUMBER(SEARCH("Payment - Concur",N81,1)),"WDL",IF(ISNUMBER(SEARCH("Payroll Transfer",N81,1)),"XFR",IF(ISNUMBER(SEARCH("XFR",N81,1)),"XFR",IF(H81>0,"RCT","WDL"))))) -> RCT | L81: =VLOOKUP(D81,'Entity Code'!A:B,2,0) -> LCREE | N81: Nov RE Remit - DGRAN | O81: LCREE-1470-0000-000-DGRAN | P81: N/A | Q81: Ladder to post
B82: 44 | C82: JPM | D82: LADDER CAPITAL CRE EQUITY LLC | E82: 528280121 | F82: 45967 | G82: Credit | H82: 50398.14 | I82: 0141707310FC | J82: CHIPS CREDIT | K82: =IF(ISNUMBER(SEARCH("Manual Payment - ",N82,1)),"AP",IF(ISNUMBER(SEARCH("Payment - Concur",N82,1)),"WDL",IF(ISNUMBER(SEARCH("Payroll Transfer",N82,1)),"XFR",IF(ISNUMBER(SEARCH("XFR",N82,1)),"XFR",IF(H82>0,"RCT","WDL"))))) -> RCT | L82: =VLOOKUP(D82,'Entity Code'!A:B,2,0) -> LCREE | P82: N/A | Q82: Ladder to post
B83: 44 | C83: JPM | D83: LADDER CAPITAL CRE EQUITY LLC | E83: 528280121 | F83: 45967 | G83: Credit | H83: 37976.8 | I83: 0078826310FC | J83: CHIPS CREDIT | K83: =IF(ISNUMBER(SEARCH("Manual Payment - ",N83,1)),"AP",IF(ISNUMBER(SEARCH("Payment - Concur",N83,1)),"WDL",IF(ISNUMBER(SEARCH("Payroll Transfer",N83,1)),"XFR",IF(ISNUMBER(SEARCH("XFR",N83,1)),"XFR",IF(H83>0,"RCT","WDL"))))) -> RCT | L83: =VLOOKUP(D83,'Entity Code'!A:B,2,0) -> LCREE | N83: Nov RE Remit - BJROT | O83: LCREE-1470-0000-000-BJROT | P83: N/A | Q83: Ladder to post
B84: 44 | C84: JPM | D84: LADDER CAPITAL CRE EQUITY LLC | E84: 528280121 | F84: 45967 | G84: Credit | H84: 37305.35 | I84: 0096010310FC | J84: CHIPS CREDIT | K84: =IF(ISNUMBER(SEARCH("Manual Payment - ",N84,1)),"AP",IF(ISNUMBER(SEARCH("Payment - Concur",N84,1)),"WDL",IF(ISNUMBER(SEARCH("Payroll Transfer",N84,1)),"XFR",IF(ISNUMBER(SEARCH("XFR",N84,1)),"XFR",IF(H84>0,"RCT","WDL"))))) -> RCT | L84: =VLOOKUP(D84,'Entity Code'!A:B,2,0) -> LCREE | N84: Nov RE Remit - DGSUL | O84: LCREE-1470-0000-000-DGSUL | P84: N/A | Q84: Ladder to post
B85: 44 | C85: JPM | D85: LADDER CAPITAL CRE EQUITY LLC | E85: 528280121 | F85: 45967 | G85: Credit | H85: 35652.82 | I85: 0079659310FC | J85: CHIPS CREDIT | K85: =IF(ISNUMBER(SEARCH("Manual Payment - ",N85,1)),"AP",IF(ISNUMBER(SEARCH("Payment - Concur",N85,1)),"WDL",IF(ISNUMBER(SEARCH("Payroll Transfer",N85,1)),"XFR",IF(ISNUMBER(SEARCH("XFR",N85,1)),"XFR",IF(H85>0,"RCT","WDL"))))) -> RCT | L85: =VLOOKUP(D85,'Entity Code'!A:B,2,0) -> LCREE | N85: Nov RE Remit - DGCHI | O85: LCREE-1470-0000-000-DGCHI | P85: N/A | Q85: Ladder to post
B86: 44 | C86: JPM | D86: LADDER CAPITAL CRE EQUITY LLC | E86: 528280121 | F86: 45967 | G86: Credit | H86: 34911.67 | I86: 0088273310FC | J86: CHIPS CREDIT | K86: =IF(ISNUMBER(SEARCH("Manual Payment - ",N86,1)),"AP",IF(ISNUMBER(SEARCH("Payment - Concur",N86,1)),"WDL",IF(ISNUMBER(SEARCH("Payroll Transfer",N86,1)),"XFR",IF(ISNUMBER(SEARCH("XFR",N86,1)),"XFR",IF(H86>0,"RCT","WDL"))))) -> RCT | L86: =VLOOKUP(D86,'Entity Code'!A:B,2,0) -> LCREE | N86: Nov RE Remit - DGPER | O86: LCREE-1470-0000-000-DGPER | P86: N/A | Q86: Ladder to post
B87: 44 | C87: JPM | D87: LADDER CAPITAL CRE EQUITY LLC | E87: 528280121 | F87: 45967 | G87: Credit | H87: 30105.82 | I87: 0129069310FC | J87: CHIPS CREDIT | K87: =IF(ISNUMBER(SEARCH("Manual Payment - ",N87,1)),"AP",IF(ISNUMBER(SEARCH("Payment - Concur",N87,1)),"WDL",IF(ISNUMBER(SEARCH("Payroll Transfer",N87,1)),"XFR",IF(ISNUMBER(SEARCH("XFR",N87,1)),"XFR",IF(H87>0,"RCT","WDL"))))) -> RCT | L87: =VLOOKUP(D87,'Entity Code'!A:B,2,0) -> LCREE | N87: Nov RE Remit - TRANS | O87: LCREE-1470-0000-000-TRANS | P87: N/A | Q87: Ladder to post
B88: 44 | C88: JPM | D88: LADDER CAPITAL CRE EQUITY LLC | E88: 528280121 | F88: 45967 | G88: Credit | H88: 30066.96 | I88: 0104767310FC | J88: CHIPS CREDIT | K88: =IF(ISNUMBER(SEARCH("Manual Payment - ",N88,1)),"AP",IF(ISNUMBER(SEARCH("Payment - Concur",N88,1)),"WDL",IF(ISNUMBER(SEARCH("Payroll Transfer",N88,1)),"XFR",IF(ISNUMBER(SEARCH("XFR",N88,1)),"XFR",IF(H88>0,"RCT","WDL"))))) -> RCT | L88: =VLOOKUP(D88,'Entity Code'!A:B,2,0) -> LCREE | N88: Nov RE Remit - DGCEN | O88: LCREE-1470-0000-000-DGCEN | P88: N/A | Q88: Ladder to post
B89: 44 | C89: JPM | D89: LADDER CAPITAL CRE EQUITY LLC | E89: 528280121 | F89: 45967 | G89: Credit | H89: 23737.19 | I89: 0091937310FC | J89: CHIPS CREDIT | K89: =IF(ISNUMBER(SEARCH("Manual Payment - ",N89,1)),"AP",IF(ISNUMBER(SEARCH("Payment - Concur",N89,1)),"WDL",IF(ISNUMBER(SEARCH("Payroll Transfer",N89,1)),"XFR",IF(ISNUMBER(SEARCH("XFR",N89,1)),"XFR",IF(H89>0,"RCT","WDL"))))) -> RCT | L89: =VLOOKUP(D89,'Entity Code'!A:B,2,0) -> LCREE | N89: Nov RE Remit - DGCHA | O89: LCREE-1470-0000-000-DGCHA | P89: N/A | Q89: Ladder to post
B90: 44 | C90: JPM | D90: LADDER CAPITAL CRE EQUITY LLC | E90: 528280121 | F90: 45967 | G90: Credit | H90: 19742.87 | I90: 0094769310FC | J90: CHIPS CREDIT | K90: =IF(ISNUMBER(SEARCH("Manual Payment - ",N90,1)),"AP",IF(ISNUMBER(SEARCH("Payment - Concur",N90,1)),"WDL",IF(ISNUMBER(SEARCH("Payroll Transfer",N90,1)),"XFR",IF(ISNUMBER(SEARCH("XFR",N90,1)),"XFR",IF(H90>0,"RCT","WDL"))))) -> RCT | L90: =VLOOKUP(D90,'Entity Code'!A:B,2,0) -> LCREE | N90: Nov RE Remit - DGPHI | O90: LCREE-1470-0000-000-DGPHI | P90: N/A | Q90: Ladder to post
B91: 44 | C91: JPM | D91: LADDER CAPITAL CRE EQUITY LLC | E91: 528280121 | F91: 45967 | G91: Credit | H91: 19199.23 | I91: 0079223310FC | J91: CHIPS CREDIT | K91: =IF(ISNUMBER(SEARCH("Manual Payment - ",N91,1)),"AP",IF(ISNUMBER(SEARCH("Payment - Concur",N91,1)),"WDL",IF(ISNUMBER(SEARCH("Payroll Transfer",N91,1)),"XFR",IF(ISNUMBER(SEARCH("XFR",N91,1)),"XFR",IF(H91>0,"RCT","WDL"))))) -> RCT | L91: =VLOOKUP(D91,'Entity Code'!A:B,2,0) -> LCREE | N91: Nov RE Remit - DGSHE | O91: LCREE-1470-0000-000-DGSHE | P91: N/A | Q91: Ladder to post
B92: 44 | C92: JPM | D92: LADDER CAPITAL CRE EQUITY LLC | E92: 528280121 | F92: 45967 | G92: Credit | H92: 15837.41 | I92: 0095662310FC | J92: CHIPS CREDIT | K92: =IF(ISNUMBER(SEARCH("Manual Payment - ",N92,1)),"AP",IF(ISNUMBER(SEARCH("Payment - Concur",N92,1)),"WDL",IF(ISNUMBER(SEARCH("Payroll Transfer",N92,1)),"XFR",IF(ISNUMBER(SEARCH("XFR",N92,1)),"XFR",IF(H92>0,"RCT","WDL"))))) -> RCT | L92: =VLOOKUP(D92,'Entity Code'!A:B,2,0) -> LCREE | N92: Nov RE Remit - WGFAY | O92: LCREE-1470-0000-000-WGFAY | P92: N/A | Q92: Ladder to post
B93: 44 | C93: JPM | D93: LADDER CAPITAL CRE EQUITY LLC | E93: 528280121 | F93: 45967 | G93: Credit | H93: 15796.87 | I93: 0091936310FC | J93: CHIPS CREDIT | K93: =IF(ISNUMBER(SEARCH("Manual Payment - ",N93,1)),"AP",IF(ISNUMBER(SEARCH("Payment - Concur",N93,1)),"WDL",IF(ISNUMBER(SEARCH("Payroll Transfer",N93,1)),"XFR",IF(ISNUMBER(SEARCH("XFR",N93,1)),"XFR",IF(H93>0,"RCT","WDL"))))) -> RCT | L93: =VLOOKUP(D93,'Entity Code'!A:B,2,0) -> LCREE | N93: Nov RE Remit - LTPMS | O93: LCREE-1470-0000-000-LTPMS | P93: N/A | Q93: Ladder to post
B94: 44 | C94: JPM | D94: LADDER CAPITAL CRE EQUITY LLC | E94: 528280121 | F94: 45967 | G94: Credit | H94: 14254.98 | I94: 0094789310FC | J94: CHIPS CREDIT | K94: =IF(ISNUMBER(SEARCH("Manual Payment - ",N94,1)),"AP",IF(ISNUMBER(SEARCH("Payment - Concur",N94,1)),"WDL",IF(ISNUMBER(SEARCH("Payroll Transfer",N94,1)),"XFR",IF(ISNUMBER(SEARCH("XFR",N94,1)),"XFR",IF(H94>0,"RCT","WDL"))))) -> RCT | L94: =VLOOKUP(D94,'Entity Code'!A:B,2,0) -> LCREE | N94: Nov RE Remit - LEKMD | O94: LCREE-1470-0000-000-LEKMD | P94: N/A | Q94: Ladder to post
... B139: 44 | C139: JPM | D139: LADDER CAPITAL CRE EQUITY LLC | E139: 528280121 | F139: 45967 | G139: Credit | H139: 734.31 | I139: 0079220310FC | J139: CHIPS CREDIT | K139: =IF(ISNUMBER(SEARCH("Manual Payment - ",N139,1)),"AP",IF(ISNUMBER(SEARCH("Payment - Concur",N139,1)),"WDL",IF(ISNUMBER(SEARCH("Payroll Transfer",N139,1)),"XFR",IF(ISNUMBER(SEARCH("XFR",N139,1)),"XFR",IF(H139>0,"RCT","WDL"))))) -> RCT | L139: =VLOOKUP(D139,'Entity Code'!A:B,2,0) -> LCREE | N139: Nov RE Remit - DGCAR | O139: LCREE-1470-0000-000-DGCAR | P139: N/A | Q139: Ladder to post
B140: 44 | C140: JPM | D140: LADDER CAPITAL CRE EQUITY LLC | E140: 528280121 | F140: 45967 | G140: Credit | H140: 637.27 | I140: 0104357310FC | J140: CHIPS CREDIT | K140: =IF(ISNUMBER(SEARCH("Manual Payment - ",N140,1)),"AP",IF(ISNUMBER(SEARCH("Payment - Concur",N140,1)),"WDL",IF(ISNUMBER(SEARCH("Payroll Transfer",N140,1)),"XFR",IF(ISNUMBER(SEARCH("XFR",N140,1)),"XFR",IF(H140>0,"RCT","WDL"))))) -> RCT | L140: =VLOOKUP(D140,'Entity Code'!A:B,2,0) -> LCREE | P140: N/A | Q140: Ladder to post
B141: 44 | C141: JPM | D141: LADDER CAPITAL CRE EQUITY LLC | E141: 528280121 | F141: 45967 | G141: Credit | H141: 615.1 | I141: 0097145310FC | J141: CHIPS CREDIT | K141: =IF(ISNUMBER(SEARCH("Manual Payment - ",N141,1)),"AP",IF(ISNUMBER(SEARCH("Payment - Concur",N141,1)),"WDL",IF(ISNUMBER(SEARCH("Payroll Transfer",N141,1)),"XFR",IF(ISNUMBER(SEARCH("XFR",N141,1)),"XFR",IF(H141>0,"RCT","WDL"))))) -> RCT | L141: =VLOOKUP(D141,'Entity Code'!A:B,2,0) -> LCREE | N141: Nov RE Remit - DGPEL | O141: LCREE-1470-0000-000-DGPEL | P141: N/A | Q141: Ladder to post
B142: 44 | C142: JPM | D142: LADDER CAPITAL CRE EQUITY LLC | E142: 528280121 | F142: 45967 | G142: Credit | H142: 500.81 | I142: 0092641310FC | J142: CHIPS CREDIT | K142: =IF(ISNUMBER(SEARCH("Manual Payment - ",N142,1)),"AP",IF(ISNUMBER(SEARCH("Payment - Concur",N142,1)),"WDL",IF(ISNUMBER(SEARCH("Payroll Transfer",N142,1)),"XFR",IF(ISNUMBER(SEARCH("XFR",N142,1)),"XFR",IF(H142>0,"RCT","WDL"))))) -> RCT | L142: =VLOOKUP(D142,'Entity Code'!A:B,2,0) -> LCREE | N142: Nov RE Remit - DGWAB | O142: LCREE-1470-0000-000-DGWAB | P142: N/A | Q142: Ladder to post
B143: 44 | C143: JPM | D143: LADDER CAPITAL CRE EQUITY LLC | E143: 528280121 | F143: 45967 | G143: Credit | H143: 486.21 | I143: 0121811310FC | J143: CHIPS CREDIT | K143: =IF(ISNUMBER(SEARCH("Manual Payment - ",N143,1)),"AP",IF(ISNUMBER(SEARCH("Payment - Concur",N143,1)),"WDL",IF(ISNUMBER(SEARCH("Payroll Transfer",N143,1)),"XFR",IF(ISNUMBER(SEARCH("XFR",N143,1)),"XFR",IF(H143>0,"RCT","WDL"))))) -> RCT | L143: =VLOOKUP(D143,'Entity Code'!A:B,2,0) -> LCREE | P143: N/A | Q143: Ladder to post
B144: 44 | C144: JPM | D144: LADDER CAPITAL CRE EQUITY LLC | E144: 528280121 | F144: 45967 | G144: Credit | H144: 428.6 | I144: 0088274310FC | J144: CHIPS CREDIT | K144: =IF(ISNUMBER(SEARCH("Manual Payment - ",N144,1)),"AP",IF(ISNUMBER(SEARCH("Payment - Concur",N144,1)),"WDL",IF(ISNUMBER(SEARCH("Payroll Transfer",N144,1)),"XFR",IF(ISNUMBER(SEARCH("XFR",N144,1)),"XFR",IF(H144>0,"RCT","WDL"))))) -> RCT | L144: =VLOOKUP(D144,'Entity Code'!A:B,2,0) -> LCREE | N144: Nov RE Remit - DGUNI | O144: LCREE-1470-0000-000-DGUNI | P144: N/A | Q144: Ladder to post
B145: 44 | C145: JPM | D145: LADDER CAPITAL CRE EQUITY LLC | E145: 528280121 | F145: 45967 | G145: Credit | H145: 295.36 | I145: 0095764310FC | J145: CHIPS CREDIT | K145: =IF(ISNUMBER(SEARCH("Manual Payment - ",N145,1)),"AP",IF(ISNUMBER(SEARCH("Payment - Concur",N145,1)),"WDL",IF(ISNUMBER(SEARCH("Payroll Transfer",N145,1)),"XFR",IF(ISNUMBER(SEARCH("XFR",N145,1)),"XFR",IF(H145>0,"RCT","WDL"))))) -> RCT | L145: =VLOOKUP(D145,'Entity Code'!A:B,2,0) -> LCREE | N145: Nov RE Remit - DGSTC | O145: LCREE-1470-0000-000-DGSTC | P145: N/A | Q145: Ladder to post
B146: 44 | C146: JPM | D146: LADDER CAPITAL CRE EQUITY LLC | E146: 528280121 | F146: 45967 | G146: Credit | H146: 245.95 | I146: 0141741310FC | J146: CHIPS CREDIT | K146: =IF(ISNUMBER(SEARCH("Manual Payment - ",N146,1)),"AP",IF(ISNUMBER(SEARCH("Payment - Concur",N146,1)),"WDL",IF(ISNUMBER(SEARCH("Payroll Transfer",N146,1)),"XFR",IF(ISNUMBER(SEARCH("XFR",N146,1)),"XFR",IF(H146>0,"RCT","WDL"))))) -> RCT | L146: =VLOOKUP(D146,'Entity Code'!A:B,2,0) -> LCREE | N146: Nov RE Remit - DGROC | O146: LCREE-1470-0000-000-DGROC | P146: N/A | Q146: Ladder to post
B147: 44 | C147: JPM | D147: LADDER CAPITAL CRE EQUITY LLC | E147: 528280121 | F147: 45967 | G147: Credit | H147: 210.38 | I147: 0088498310FC | J147: CHIPS CREDIT | K147: =IF(ISNUMBER(SEARCH("Manual Payment - ",N147,1)),"AP",IF(ISNUMBER(SEARCH("Payment - Concur",N147,1)),"WDL",IF(ISNUMBER(SEARCH("Payroll Transfer",N147,1)),"XFR",IF(ISNUMBER(SEARCH("XFR",N147,1)),"XFR",IF(H147>0,"RCT","WDL"))))) -> RCT | L147: =VLOOKUP(D147,'Entity Code'!A:B,2,0) -> LCREE | N147: Nov RE Remit - DGOGD | O147: LCREE-1470-0000-000-DGOGD | P147: N/A | Q147: Ladder to post
B148: 44 | C148: JPM | D148: LADDER CAPITAL CRE EQUITY LLC | E148: 528280121 | F148: 45967 | G148: Credit | H148: 101.82 | I148: 0089104310FC | J148: CHIPS CREDIT | K148: =IF(ISNUMBER(SEARCH("Manual Payment - ",N148,1)),"AP",IF(ISNUMBER(SEARCH("Payment - Concur",N148,1)),"WDL",IF(ISNUMBER(SEARCH("Payroll Transfer",N148,1)),"XFR",IF(ISNUMBER(SEARCH("XFR",N148,1)),"XFR",IF(H148>0,"RCT","WDL"))))) -> RCT | L148: =VLOOKUP(D148,'Entity Code'!A:B,2,0) -> LCREE | N148: Nov RE Remit - DGFOL | O148: LCREE-1470-0000-000-DGFOL | P148: N/A | Q148: Ladder to post
B149: 45 | C149: JPM | D149: LADDER CAPITAL CRE EQUITY LLC | E149: 528280121 | F149: 45967 | G149: Debit | H149: -7089.16 | I149: 9820300310JO | J149: FEDWIRE DEBIT | K149: =IF(ISNUMBER(SEARCH("Manual Payment - ",N149,1)),"AP",IF(ISNUMBER(SEARCH("Payment - Concur",N149,1)),"WDL",IF(ISNUMBER(SEARCH("Payroll Transfer",N149,1)),"XFR",IF(ISNUMBER(SEARCH("XFR",N149,1)),"XFR",IF(H149>0,"RCT","WDL"))))) -> WDL | L149: =VLOOKUP(D149,'Entity Code'!A:B,2,0) -> LCREE | N149: Nov RE Shortfall - DGSPR | O149: LCREE-1460-0000-000-DGSPR | P149: N/A | Q149: Ladder to post
B150: 45 | C150: JPM | D150: LADDER CAPITAL CRE EQUITY LLC | E150: 528280121 | F150: 45967 | G150: Debit | H150: -7053.73 | I150: 9820000310JO | J150: FEDWIRE DEBIT | K150: =IF(ISNUMBER(SEARCH("Manual Payment - ",N150,1)),"AP",IF(ISNUMBER(SEARCH("Payment - Concur",N150,1)),"WDL",IF(ISNUMBER(SEARCH("Payroll Transfer",N150,1)),"XFR",IF(ISNUMBER(SEARCH("XFR",N150,1)),"XFR",IF(H150>0,"RCT","WDL"))))) -> WDL | L150: =VLOOKUP(D150,'Entity Code'!A:B,2,0) -> LCREE | N150: Nov RE Shortfall - DGHAN | O150: LCREE-1460-0000-000-DGHAN | P150: N/A | Q150: Ladder to post
B151: 45 | C151: JPM | D151: LADDER CAPITAL CRE EQUITY LLC | E151: 528280121 | F151: 45967 | G151: Debit | H151: -6987.69 | I151: 9820500310JO | J151: FEDWIRE DEBIT | K151: =IF(ISNUMBER(SEARCH("Manual Payment - ",N151,1)),"AP",IF(ISNUMBER(SEARCH("Payment - Concur",N151,1)),"WDL",IF(ISNUMBER(SEARCH("Payroll Transfer",N151,1)),"XFR",IF(ISNUMBER(SEARCH("XFR",N151,1)),"XFR",IF(H151>0,"RCT","WDL"))))) -> WDL | L151: =VLOOKUP(D151,'Entity Code'!A:B,2,0) -> LCREE | N151: Nov RE Shortfall - DGPAW | O151: LCREE-1460-0000-000-DGPAW | P151: N/A | Q151: Ladder to post
B152: 45 | C152: JPM | D152: LADDER CAPITAL CRE EQUITY LLC | E152: 528280121 | F152: 45967 | G152: Debit | H152: -6148.71 | I152: 9820600310JO | J152: FEDWIRE DEBIT | K152: =IF(ISNUMBER(SEARCH("Manual Payment - ",N152,1)),"AP",IF(ISNUMBER(SEARCH("Payment - Concur",N152,1)),"WDL",IF(ISNUMBER(SEARCH("Payroll Transfer",N152,1)),"XFR",IF(ISNUMBER(SEARCH("XFR",N152,1)),"XFR",IF(H152>0,"RCT","WDL"))))) -> WDL | L152: =VLOOKUP(D152,'Entity Code'!A:B,2,0) -> LCREE | N152: Nov RE Shortfall - DGMGR | O152: LCREE-1460-0000-000-DGMGR | P152: N/A | Q152: Ladder to post
B153: 45 | C153: JPM | D153: LADDER CAPITAL CRE EQUITY LLC | E153: 528280121 | F153: 45967 | G153: Debit | H153: -6045.6 | I153: 9820800310JO | J153: FEDWIRE DEBIT | K153: =IF(ISNUMBER(SEARCH("Manual Payment - ",N153,1)),"AP",IF(ISNUMBER(SEARCH("Payment - Concur",N153,1)),"WDL",IF(ISNUMBER(SEARCH("Payroll Transfer",N153,1)),"XFR",IF(ISNUMBER(SEARCH("XFR",N153,1)),"XFR",IF(H153>0,"RCT","WDL"))))) -> WDL | L153: =VLOOKUP(D153,'Entity Code'!A:B,2,0) -> LCREE | N153: Nov RE Shortfall - DGRID | O153: LCREE-1460-0000-000-DGRID | P153: N/A | Q153: Ladder to post
B154: 45 | C154: JPM | D154: LADDER CAPITAL CRE EQUITY LLC | E154: 528280121 | F154: 45967 | G154: Debit | H154: -5897.99 | I154: 9820100310JO | J154: FEDWIRE DEBIT | K154: =IF(ISNUMBER(SEARCH("Manual Payment - ",N154,1)),"AP",IF(ISNUMBER(SEARCH("Payment - Concur",N154,1)),"WDL",IF(ISNUMBER(SEARCH("Payroll Transfer",N154,1)),"XFR",IF(ISNUMBER(SEARCH("XFR",N154,1)),"XFR",IF(H154>0,"RCT","WDL"))))) -> WDL | L154: =VLOOKUP(D154,'Entity Code'!A:B,2,0) -> LCREE | N154: Nov RE Shortfall - DGLAM | O154: LCREE-1460-0000-000-DGLAM | P154: N/A | Q154: Ladder to post
B155: 45 | C155: JPM | D155: LADDER CAPITAL CRE EQUITY LLC | E155: 528280121 | F155: 45967 | G155: Debit | H155: -5497.95 | I155: 9819900310JO | J155: FEDWIRE DEBIT | K155: =IF(ISNUMBER(SEARCH("Manual Payment - ",N155,1)),"AP",IF(ISNUMBER(SEARCH("Payment - Concur",N155,1)),"WDL",IF(ISNUMBER(SEARCH("Payroll Transfer",N155,1)),"XFR",IF(ISNUMBER(SEARCH("XFR",N155,1)),"XFR",IF(H155>0,"RCT","WDL"))))) -> WDL | L155: =VLOOKUP(D155,'Entity Code'!A:B,2,0) -> LCREE | N155: Nov RE Shortfall - DGGLA | O155: LCREE-1460-0000-000-DGGLA | P155: N/A | Q155: Ladder to post
... B158: 45 | C158: JPM | D158: LADDER CAPITAL CRE EQUITY LLC | E158: 528280121 | F158: 45967 | G158: Debit | H158: -350 | I158: 9820400310JO | J158: FEDWIRE DEBIT | K158: =IF(ISNUMBER(SEARCH("Manual Payment - ",N158,1)),"AP",IF(ISNUMBER(SEARCH("Payment - Concur",N158,1)),"WDL",IF(ISNUMBER(SEARCH("Payroll Transfer",N158,1)),"XFR",IF(ISNUMBER(SEARCH("XFR",N158,1)),"XFR",IF(H158>0,"RCT","WDL"))))) -> WDL | L158: =VLOOKUP(D158,'Entity Code'!A:B,2,0) -> LCREE | N158: Nov RE Shortfall - DGSAN | O158: LCREE-1460-0000-000-DGSAN | P158: N/A | Q158: Ladder to post

Sheet Cash Entries 11-6
A1: ENTITY | B1: YEARMONTH | C1: SOURCE | D1: BATCH ID | E1: BATCH DESCRIPTION | F1: BATCHDATE | G1: DR_AMT | H1: CR AMT | I1: TRXDATE | J1: DIST REFERENCE | K1: GPACCT
A2: GPGRO | B2: =Checklist!$B$1 -> 202511 | C2: GJ | D2: =Checklist!$B$8 -> DC1106251 | E2: =D2 -> DC1106251 | F2: =Checklist!$A$8 -> 45967 | G2: 3621790.7 | H2: 0 | I2: =$F$2 -> 45967 | J2: Harps - Grove OK Mortgage Debt Payoff | K2: LCREE-1460-0000-000-GPGRO
A3: GPGRO | B3: =Checklist!$B$1 -> 202511 | C3: GJ | D3: =D2 -> DC1106251 | E3: =D3 -> DC1106251 | F3: =$F$2 -> 45967 | G3: 0 | H3: 3621790.7 | I3: =$F$2 -> 45967 | J3: Harps - Grove OK Mortgage Debt Payoff | K3: LCREE-1065-0008-000-
A4: DGWIL | B4: =Checklist!$B$1 -> 202511 | C4: GJ | D4: DC1106252 | E4: =D4 -> DC1106252 | F4: =$F$2 -> 45967 | G4: 901339.33 | H4: 0 | I4: =$F$2 -> 45967 | J4: DG - Wilmington IL Mortgage Debt Payoff | K4: LCREE-1460-0000-000-DGWIL
A5: DGWIL | B5: =Checklist!$B$1 -> 202511 | C5: GJ | D5: =D4 -> DC1106252 | E5: =D5 -> DC1106252 | F5: =$F$2 -> 45967 | G5: 0 | H5: 901339.33 | I5: =$F$2 -> 45967 | J5: DG - Wilmington IL Mortgage Debt Payoff | K5: LCREE-1065-0008-000-
A6: DGFAR | B6: =Checklist!$B$1 -> 202511 | C6: GJ | D6: DC1106253 | E6: =D6 -> DC1106253 | F6: =$F$2 -> 45967 | G6: 894856.79 | H6: 0 | I6: =$F$2 -> 45967 | J6: DG - Farmington IL Mortgage Debt Payoff | K6: LCREE-1460-0000-000-DGFAR
A7: DGFAR | B7: =Checklist!$B$1 -> 202511 | C7: GJ | D7: =D6 -> DC1106253 | E7: =D7 -> DC1106253 | F7: =$F$2 -> 45967 | G7: 0 | H7: 894856.79 | I7: =$F$2 -> 45967 | J7: DG - Farmington IL Mortgage Debt Payoff | K7: LCREE-1065-0008-000-
A8: GPBLO | B8: =Checklist!$B$1 -> 202511 | C8: GJ | D8: DC1106254 | E8: =D8 -> DC1106254 | F8: =$F$2 -> 45967 | G8: 816503.21 | H8: 0 | I8: =$F$2 -> 45967 | J8: DG - Bloomington IL Mortgage Debt Payoff | K8: LCREE-1460-0000-000-GPBLO
A9: GPBLO | B9: =Checklist!$B$1 -> 202511 | C9: GJ | D9: =D8 -> DC1106254 | E9: =D9 -> DC1106254 | F9: =$F$2 -> 45967 | G9: 0 | H9: 816503.21 | I9: =$F$2 -> 45967 | J9: DG - Bloomington IL Mortgage Debt Payoff | K9: LCREE-1065-0008-000-
A10: GPMON | B10: =Checklist!$B$1 -> 202511 | C10: GJ | D10: DC1106255 | E10: =D10 -> DC1106255 | F10: =$F$2 -> 45967 | G10: 770801.43 | H10: 0 | I10: =$F$2 -> 45967 | J10: DG - Montrose MN Mortgage Debt Payoff | K10: LCREE-1460-0000-000-GPMON
A11: GPMON | B11: =Checklist!$B$1 -> 202511 | C11: GJ | D11: =D10 -> DC1106255 | E11: =D11 -> DC1106255 | F11: =$F$2 -> 45967 | G11: 0 | H11: 770801.43 | I11: =$F$2 -> 45967 | J11: DG - Montrose MN Mortgage Debt Payoff | K11: LCREE-1065-0008-000-
A12: GPTRO | B12: =Checklist!$B$1 -> 202511 | C12: GJ | D12: DC1106256 | E12: =D12 -> DC1106256 | F12: =$F$2 -> 45967 | G12: 738150.98 | H12: 0 | I12: =$F$2 -> 45967 | J12: DG - Troy MO Mortgage Debt Payoff | K12: LCREE-1460-0000-000-GPTRO
A13: GPTRO | B13: =Checklist!$B$1 -> 202511 | C13: GJ | D13: =D12 -> DC1106256 | E13: =D13 -> DC1106256 | F13: =$F$2 -> 45967 | G13: 0 | H13: 738150.98 | I13: =$F$2 -> 45967 | J13: DG - Troy MO Mortgage Debt Payoff | K13: LCREE-1065-0008-000-
A14: GPDAN | B14: =Checklist!$B$1 -> 202511 | C14: GJ | D14: DC1106257 | E14: =D14 -> DC1106257 | F14: =$F$2 -> 45967 | G14: 738125.68 | H14: 0 | I14: =$F$2 -> 45967 | J14: DG - Danville IL Mortgage Debt Payoff | K14: LCREE-1460-0000-000-GPDAN
A15: GPDAN | B15: =Checklist!$B$1 -> 202511 | C15: GJ | D15: =D14 -> DC1106257 | E15: =D15 -> DC1106257 | F15: =$F$2 -> 45967 | G15: 0 | H15: 738125.68 | I15: =$F$2 -> 45967 | J15: DG - Danville IL Mortgage Debt Payoff | K15: LCREE-1065-0008-000-
A16: LCREE | B16: =Checklist!$B$1 -> 202511 | C16: GJ | D16: DC1106258 | E16: =D16 -> DC1106258 | F16: =$F$2 -> 45967 | G16: 448415.46 | H16: 0 | I16: =$F$2 -> 45967 | J16: BofA Tracts C and G M&T Owners Account | K16: LCREE-1460-0000-000-BOAJV
A17: LCREE | B17: =Checklist!$B$1 -> 202511 | C17: GJ | D17: =D16 -> DC1106258 | E17: =D17 -> DC1106258 | F17: =$F$2 -> 45967 | G17: 0 | H17: 448415.46 | I17: =$F$2 -> 45967 | J17: BofA Tracts C and G M&T Owners Account | K17: LCREE-1065-0008-000-
A18: BOAJV | B18: =Checklist!$B$1 -> 202511 | C18: GJ | D18: =D17 -> DC1106258 | E18: =D18 -> DC1106258 | F18: =$F$2 -> 45967 | G18: 448415.46 | H18: 0 | I18: =$F$2 -> 45967 | J18: BofA Tracts C and G M&T Owners Account | K18: BOAJV-1001-0001-540-
A19: BOAJV | B19: =Checklist!$B$1 -> 202511 | C19: GJ | D19: =D18 -> DC1106258 | E19: =D19 -> DC1106258 | F19: =$F$2 -> 45967 | G19: 0 | H19: 448415.46 | I19: =$F$2 -> 45967 | J19: BofA Tracts C and G M&T Owners Account | K19: BOAJV-3660-0000-540-LCREE
A20: LCREE | B20: =Checklist!$B$1 -> 202511 | C20: GJ | D20: DC1106259 | E20: =D20 -> DC1106259 | F20: =$F$2 -> 45967 | G20: 243629.92 | H20: 0 | I20: =$F$2 -> 45967 | J20: BofA Tract E M&T Owners Account | K20: LCREE-1460-0000-000-BOAJV
A21: LCREE | B21: =Checklist!$B$1 -> 202511 | C21: GJ | D21: =D20 -> DC1106259 | E21: =D21 -> DC1106259 | F21: =$F$2 -> 45967 | G21: 0 | H21: 243629.92 | I21: =$F$2 -> 45967 | J21: BofA Tract E M&T Owners Account | K21: LCREE-1065-0008-000-
A22: BOAJV | B22: =Checklist!$B$1 -> 202511 | C22: GJ | D22: =D21 -> DC1106259 | E22: =D22 -> DC1106259 | F22: =$F$2 -> 45967 | G22: 243629.92 | H22: 0 | I22: =$F$2 -> 45967 | J22: BofA Tract E M&T Owners Account | K22: BOAJV-1001-0001-540-
A23: BOAJV | B23: =Checklist!$B$1 -> 202511 | C23: GJ | D23: =D22 -> DC1106259 | E23: =D23 -> DC1106259 | F23: =$F$2 -> 45967 | G23: 0 | H23: 243629.92 | I23: =$F$2 -> 45967 | J23: BofA Tract E M&T Owners Account | K23: BOAJV-3660-0000-540-LCREE
A24: LCREE | B24: =Checklist!$B$1 -> 202511 | C24: GJ | D24: DC11062510 | E24: =D24 -> DC11062510 | F24: =$F$2 -> 45967 | G24: 16917.97 | H24: 0 | I24: =$F$2 -> 45967 | J24: Check Deposited Return - DG - Effingham IL
A25: LCREE | B25: =Checklist!$B$1 -> 202511 | C25: GJ | D25: =D24 -> DC11062510 | E25: =D25 -> DC11062510 | F25: =$F$2 -> 45967 | G25: 0 | H25: 16917.97 | I25: =$F$2 -> 45967 | J25: Check Deposited Return - DG - Effingham IL | K25: LCREE-1043-0000-000-
A26: LCREE | B26: =Checklist!$B$1 -> 202511 | C26: GJ | D26: DC11062511 | E26: =D26 -> DC11062511 | F26: =$F$2 -> 45967 | G26: 243629.92 | H26: 0 | I26: =$F$2 -> 45967 | J26: Bank of America Campus Jacksonville Tract E | K26: LCREE-1065-0008-000-
A27: LCREE | B27: =Checklist!$B$1 -> 202511 | C27: GJ | D27: =D26 -> DC11062511 | E27: =D27 -> DC11062511 | F27: =$F$2 -> 45967 | G27: 0 | H27: 243629.92 | I27: =$F$2 -> 45967 | J27: Bank of America Campus Jacksonville Tract E | K27: LCREE-1470-0000-000-BOAJV
A28: BOAJV | B28: =Checklist!$B$1 -> 202511 | C28: GJ | D28: =D27 -> DC11062511 | E28: =D28 -> DC11062511 | F28: =$F$2 -> 45967 | G28: 243629.92 | H28: 0 | I28: =$F$2 -> 45967 | J28: Bank of America Campus Jacksonville Tract E | K28: BOAJV-3670-0000-540-LCREE
A29: BOAJV | B29: =Checklist!$B$1 -> 202511 | C29: GJ | D29: =D28 -> DC11062511 | E29: =D29 -> DC11062511 | F29: =$F$2 -> 45967 | G29: 0 | H29: 243629.92 | I29: =$F$2 -> 45967 | J29: Bank of America Campus Jacksonville Tract E | K29: BOAJV-1001-0001-540-
A30: LCREE | B30: =Checklist!$B$1 -> 202511 | C30: GJ | D30: DC11062512 | E30: =D30 -> DC11062512 | F30: =$F$2 -> 45967 | G30: 448415.46 | H30: 0 | I30: =$F$2 -> 45967 | J30: Bank of America Campus Jacksonville Tracts C and G | K30: LCREE-1065-0008-000-
A31: LCREE | B31: =Checklist!$B$1 -> 202511 | C31: GJ | D31: =D30 -> DC11062512 | E31: =D31 -> DC11062512 | F31: =$F$2 -> 45967 | G31: 0 | H31: 448415.46 | I31: =$F$2 -> 45967 | J31: Bank of America Campus Jacksonville Tracts C and G | K31: LCREE-1470-0000-000-BOAJV
A32: BOAJV | B32: =Checklist!$B$1 -> 202511 | C32: GJ | D32: =D31 -> DC11062512 | E32: =D32 -> DC11062512 | F32: =$F$2 -> 45967 | G32: 448415.46 | H32: 0 | I32: =$F$2 -> 45967 | J32: Bank of America Campus Jacksonville Tracts C and G | K32: BOAJV-3670-0000-540-LCREE
A33: BOAJV | B33: =Checklist!$B$1 -> 202511 | C33: GJ | D33: =D32 -> DC11062512 | E33: =D33 -> DC11062512 | F33: =$F$2 -> 45967 | G33: 0 | H33: 448415.46 | I33: =$F$2 -> 45967 | J33: Bank of America Campus Jacksonville Tracts C and G | K33: BOAJV-1001-0001-540-
A34: LCREE | B34: =Checklist!$B$1 -> 202511 | C34: GJ | D34: DC11062513 | E34: =D34 -> DC11062513 | F34: =$F$2 -> 45967 | G34: 8100000 | H34: 0 | I34: =$F$2 -> 45967 | J34: XFR from LCFHR PNC to LCREE PNC | K34: LCREE-1065-0008-000-
A35: LCREE | B35: =Checklist!$B$1 -> 202511 | C35: GJ | D35: =D34 -> DC11062513 | E35: =D35 -> DC11062513 | F35: =$F$2 -> 45967 | G35: 0 | H35: 8100000 | I35: =$F$2 -> 45967 | J35: XFR from LCFHR PNC to LCREE PNC | K35: LCFHR-1065-0002-000-
A36: LCREE | B36: =Checklist!$B$1 -> 202511 | C36: GJ | D36: DC11062514 | E36: =D36 -> DC11062514 | F36: =$F$2 -> 45967 | G36: 830000 | H36: 0 | I36: =$F$2 -> 45967 | J36: XFR from LCREE to LCFHR Trading | K36: LCFHR-1046-0000-000-
A37: LCREE | B37: =Checklist!$B$1 -> 202511 | C37: GJ | D37: =D36 -> DC11062514 | E37: =D37 -> DC11062514 | F37: =$F$2 -> 45967 | G37: 0 | H37: 830000 | I37: =$F$2 -> 45967 | J37: XFR from LCREE to LCFHR Trading | K37: LCREE-1043-0000-000-
A38: LCREE | B38: =Checklist!$B$1 -> 202511 | C38: GJ | D38: DC11062515 | E38: =D38 -> DC11062515 | F38: =$F$2 -> 45967 | G38: 55915.62 | H38: 0 | I38: =$F$2 -> 45967 | J38: Nov RE Remit - BJPL2V | K38: LCREE-1065-0008-000-
A39: LCREE | B39: =Checklist!$B$1 -> 202511 | C39: GJ | D39: =D38 -> DC11062515 | E39: =D39 -> DC11062515 | F39: =$F$2 -> 45967 | G39: 50537.45 | H39: 0 | I39: =$F$2 -> 45967 | J39: Nov RE Remit - BJPL2S | K39: LCREE-1065-0008-000-
A40: LCREE | B40: =Checklist!$B$1 -> 202511 | C40: GJ | D40: =D39 -> DC11062515 | E40: =D40 -> DC11062515 | F40: =$F$2 -> 45967 | G40: 44174.89 | H40: 0 | I40: =$F$2 -> 45967 | J40: Nov RE Remit - BJPL2M | K40: LCREE-1065-0008-000-
A41: LCREE | B41: =Checklist!$B$1 -> 202511 | C41: GJ | D41: =D40 -> DC11062515 | E41: =D41 -> DC11062515 | F41: =$F$2 -> 45967 | G41: 11400.16 | H41: 0 | I41: =$F$2 -> 45967 | J41: Nov RE Remit - LWMIL | K41: LCREE-1065-0008-000-
A42: LCREE | B42: =Checklist!$B$1 -> 202511 | C42: GJ | D42: =D41 -> DC11062515 | E42: =D42 -> DC11062515 | F42: =$F$2 -> 45967 | G42: 11114.01 | H42: 0 | I42: =$F$2 -> 45967 | J42: Nov RE Remit - WGPLM | K42: LCREE-1065-0008-000-
A43: LCREE | B43: =Checklist!$B$1 -> 202511 | C43: GJ | D43: =D42 -> DC11062515 | E43: =D43 -> DC11062515 | F43: =$F$2 -> 45967 | G43: 8417.64 | H43: 0 | I43: =$F$2 -> 45967 | J43: Nov RE Remit - LWGAR | K43: LCREE-1065-0008-000-
A44: LCREE | B44: =Checklist!$B$1 -> 202511 | C44: GJ | D44: =D43 -> DC11062515 | E44: =D44 -> DC11062515 | F44: =$F$2 -> 45967 | G44: 7393.74 | H44: 0 | I44: =$F$2 -> 45967 | J44: Nov RE Remit - WGAIK | K44: LCREE-1065-0008-000-
A45: LCREE | B45: =Checklist!$B$1 -> 202511 | C45: GJ | D45: =D44 -> DC11062515 | E45: =D45 -> DC11062515 | F45: =$F$2 -> 45967 | G45: 6170.69 | H45: 0 | I45: =$F$2 -> 45967 | J45: Nov RE Remit - LDTOK | K45: LCREE-1065-0008-000-
A46: LCREE | B46: =Checklist!$B$1 -> 202511 | C46: GJ | D46: =D45 -> DC11062515 | E46: =D46 -> DC11062515 | F46: =$F$2 -> 45967 | G46: 5815.25 | H46: 0 | I46: =$F$2 -> 45967 | J46: Nov RE Remit - WGABI | K46: LCREE-1065-0008-000-
A47: LCREE | B47: =Checklist!$B$1 -> 202511 | C47: GJ | D47: =D46 -> DC11062515 | E47: =D47 -> DC11062515 | F47: =$F$2 -> 45967 | G47: 5786.41 | H47: 0 | I47: =$F$2 -> 45967 | J47: Nov RE Remit - WGMTA | K47: LCREE-1065-0008-000-
A48: LCREE | B48: =Checklist!$B$1 -> 202511 | C48: GJ | D48: =D47 -> DC11062515 | E48: =D48 -> DC11062515 | F48: =$F$2 -> 45967 | G48: 379.73 | H48: 0 | I48: =$F$2 -> 45967 | J48: Nov RE Remit - DOCFL | K48: LCREE-1065-0008-000-
A49: LCREE | B49: =Checklist!$B$1 -> 202511 | C49: GJ | D49: =D48 -> DC11062515 | E49: =D49 -> DC11062515 | F49: =$F$2 -> 45967 | G49: 40.47 | H49: 0 | I49: =$F$2 -> 45967 | J49: Nov RE Remit - LDGSS | K49: LCREE-1065-0008-000-
A50: LCREE | B50: =Checklist!$B$1 -> 202511 | C50: GJ | D50: =D49 -> DC11062515 | E50: =D50 -> DC11062515 | F50: =$F$2 -> 45967 | G50: 0 | H50: 55915.62 | I50: =$F$2 -> 45967 | J50: Nov RE Remit - BJPL2V | K50: LCREE-1470-0000-000-BJPL2
... A61: LCREE | B61: =Checklist!$B$1 -> 202511 | C61: GJ | D61: =D60 -> DC11062515 | E61: =D61 -> DC11062515 | F61: =$F$2 -> 45967 | G61: 0 | H61: 40.47 | I61: =$F$2 -> 45967 | J61: Nov RE Remit - LDGSS | K61: LCREE-1470-0000-000-LDGSS
A62: LCREE | B62: =Checklist!$B$1 -> 202511 | C62: GJ | D62: DC11062516 | E62: =D62 -> DC11062516 | F62: =$F$2 -> 45967 | G62: 55476.06 | H62: 0 | I62: =$F$2 -> 45967 | J62: Nov RE Remit - DGRAN | K62: LCREE-1043-0000-000-
A63: LCREE | B63: =Checklist!$B$1 -> 202511 | C63: GJ | D63: =D62 -> DC11062516 | E63: =D63 -> DC11062516 | F63: =$F$2 -> 45967 | G63: 50398.14 | H63: 0 | I63: =$F$2 -> 45967 | K63: LCREE-1043-0000-000-
A64: LCREE | B64: =Checklist!$B$1 -> 202511 | C64: GJ | D64: =D63 -> DC11062516 | E64: =D64 -> DC11062516 | F64: =$F$2 -> 45967 | G64: 37976.8 | H64: 0 | I64: =$F$2 -> 45967 | J64: Nov RE Remit - BJROT | K64: LCREE-1043-0000-000-
A65: LCREE | B65: =Checklist!$B$1 -> 202511 | C65: GJ | D65: =D64 -> DC11062516 | E65: =D65 -> DC11062516 | F65: =$F$2 -> 45967 | G65: 37305.35 | H65: 0 | I65: =$F$2 -> 45967 | J65: Nov RE Remit - DGSUL | K65: LCREE-1043-0000-000-
A66: LCREE | B66: =Checklist!$B$1 -> 202511 | C66: GJ | D66: =D65 -> DC11062516 | E66: =D66 -> DC11062516 | F66: =$F$2 -> 45967 | G66: 35652.82 | H66: 0 | I66: =$F$2 -> 45967 | J66: Nov RE Remit - DGCHI | K66: LCREE-1043-0000-000-
A67: LCREE | B67: =Checklist!$B$1 -> 202511 | C67: GJ | D67: =D66 -> DC11062516 | E67: =D67 -> DC11062516 | F67: =$F$2 -> 45967 | G67: 34911.67 | H67: 0 | I67: =$F$2 -> 45967 | J67: Nov RE Remit - DGPER | K67: LCREE-1043-0000-000-
A68: LCREE | B68: =Checklist!$B$1 -> 202511 | C68: GJ | D68: =D67 -> DC11062516 | E68: =D68 -> DC11062516 | F68: =$F$2 -> 45967 | G68: 30105.82 | H68: 0 | I68: =$F$2 -> 45967 | J68: Nov RE Remit - TRANS | K68: LCREE-1043-0000-000-
A69: LCREE | B69: =Checklist!$B$1 -> 202511 | C69: GJ | D69: =D68 -> DC11062516 | E69: =D69 -> DC11062516 | F69: =$F$2 -> 45967 | G69: 30066.96 | H69: 0 | I69: =$F$2 -> 45967 | J69: Nov RE Remit - DGCEN | K69: LCREE-1043-0000-000-
A70: LCREE | B70: =Checklist!$B$1 -> 202511 | C70: GJ | D70: =D69 -> DC11062516 | E70: =D70 -> DC11062516 | F70: =$F$2 -> 45967 | G70: 23737.19 | H70: 0 | I70: =$F$2 -> 45967 | J70: Nov RE Remit - DGCHA | K70: LCREE-1043-0000-000-
A71: LCREE | B71: =Checklist!$B$1 -> 202511 | C71: GJ | D71: =D70 -> DC11062516 | E71: =D71 -> DC11062516 | F71: =$F$2 -> 45967 | G71: 19742.87 | H71: 0 | I71: =$F$2 -> 45967 | J71: Nov RE Remit - DGPHI | K71: LCREE-1043-0000-000-
A72: LCREE | B72: =Checklist!$B$1 -> 202511 | C72: GJ | D72: =D71 -> DC11062516 | E72: =D72 -> DC11062516 | F72: =$F$2 -> 45967 | G72: 19199.23 | H72: 0 | I72: =$F$2 -> 45967 | J72: Nov RE Remit - DGSHE | K72: LCREE-1043-0000-000-
A73: LCREE | B73: =Checklist!$B$1 -> 202511 | C73: GJ | D73: =D72 -> DC11062516 | E73: =D73 -> DC11062516 | F73: =$F$2 -> 45967 | G73: 15837.41 | H73: 0 | I73: =$F$2 -> 45967 | J73: Nov RE Remit - WGFAY | K73: LCREE-1043-0000-000-
A74: LCREE | B74: =Checklist!$B$1 -> 202511 | C74: GJ | D74: =D73 -> DC11062516 | E74: =D74 -> DC11062516 | F74: =$F$2 -> 45967 | G74: 15796.87 | H74: 0 | I74: =$F$2 -> 45967 | J74: Nov RE Remit - LTPMS | K74: LCREE-1043-0000-000-
A75: LCREE | B75: =Checklist!$B$1 -> 202511 | C75: GJ | D75: =D74 -> DC11062516 | E75: =D75 -> DC11062516 | F75: =$F$2 -> 45967 | G75: 14254.98 | H75: 0 | I75: =$F$2 -> 45967 | J75: Nov RE Remit - LEKMD | K75: LCREE-1043-0000-000-
... A120: LCREE | B120: =Checklist!$B$1 -> 202511 | C120: GJ | D120: =D119 -> DC11062516 | E120: =D120 -> DC11062516 | F120: =$F$2 -> 45967 | G120: 734.31 | H120: 0 | I120: =$F$2 -> 45967 | J120: Nov RE Remit - DGCAR | K120: LCREE-1043-0000-000-
A121: LCREE | B121: =Checklist!$B$1 -> 202511 | C121: GJ | D121: =D120 -> DC11062516 | E121: =D121 -> DC11062516 | F121: =$F$2 -> 45967 | G121: 637.27 | H121: 0 | I121: =$F$2 -> 45967 | K121: LCREE-1043-0000-000-
A122: LCREE | B122: =Checklist!$B$1 -> 202511 | C122: GJ | D122: =D121 -> DC11062516 | E122: =D122 -> DC11062516 | F122: =$F$2 -> 45967 | G122: 615.1 | H122: 0 | I122: =$F$2 -> 45967 | J122: Nov RE Remit - DGPEL | K122: LCREE-1043-0000-000-
A123: LCREE | B123: =Checklist!$B$1 -> 202511 | C123: GJ | D123: =D122 -> DC11062516 | E123: =D123 -> DC11062516 | F123: =$F$2 -> 45967 | G123: 500.81 | H123: 0 | I123: =$F$2 -> 45967 | J123: Nov RE Remit - DGWAB | K123: LCREE-1043-0000-000-
A124: LCREE | B124: =Checklist!$B$1 -> 202511 | C124: GJ | D124: =D123 -> DC11062516 | E124: =D124 -> DC11062516 | F124: =$F$2 -> 45967 | G124: 486.21 | H124: 0 | I124: =$F$2 -> 45967 | K124: LCREE-1043-0000-000-
A125: LCREE | B125: =Checklist!$B$1 -> 202511 | C125: GJ | D125: =D124 -> DC11062516 | E125: =D125 -> DC11062516 | F125: =$F$2 -> 45967 | G125: 428.6 | H125: 0 | I125: =$F$2 -> 45967 | J125: Nov RE Remit - DGUNI | K125: LCREE-1043-0000-000-
A126: LCREE | B126: =Checklist!$B$1 -> 202511 | C126: GJ | D126: =D125 -> DC11062516 | E126: =D126 -> DC11062516 | F126: =$F$2 -> 45967 | G126: 295.36 | H126: 0 | I126: =$F$2 -> 45967 | J126: Nov RE Remit - DGSTC | K126: LCREE-1043-0000-000-
A127: LCREE | B127: =Checklist!$B$1 -> 202511 | C127: GJ | D127: =D126 -> DC11062516 | E127: =D127 -> DC11062516 | F127: =$F$2 -> 45967 | G127: 245.95 | H127: 0 | I127: =$F$2 -> 45967 | J127: Nov RE Remit - DGROC | K127: LCREE-1043-0000-000-
A128: LCREE | B128: =Checklist!$B$1 -> 202511 | C128: GJ | D128: =D127 -> DC11062516 | E128: =D128 -> DC11062516 | F128: =$F$2 -> 45967 | G128: 210.38 | H128: 0 | I128: =$F$2 -> 45967 | J128: Nov RE Remit - DGOGD | K128: LCREE-1043-0000-000-
A129: LCREE | B129: =Checklist!$B$1 -> 202511 | C129: GJ | D129: =D128 -> DC11062516 | E129: =D129 -> DC11062516 | F129: =$F$2 -> 45967 | G129: 101.82 | H129: 0 | I129: =$F$2 -> 45967 | J129: Nov RE Remit - DGFOL | K129: LCREE-1043-0000-000-
A130: LCREE | B130: =Checklist!$B$1 -> 202511 | C130: GJ | D130: =D129 -> DC11062516 | E130: =D130 -> DC11062516 | F130: =$F$2 -> 45967 | G130: 0 | H130: 55476.06 | I130: =$F$2 -> 45967 | J130: Nov RE Remit - DGRAN | K130: LCREE-1470-0000-000-DGRAN
A131: LCREE | B131: =Checklist!$B$1 -> 202511 | C131: GJ | D131: =D130 -> DC11062516 | E131: =D131 -> DC11062516 | F131: =$F$2 -> 45967 | G131: 0 | H131: 50398.14 | I131: =$F$2 -> 45967
A132: LCREE | B132: =Checklist!$B$1 -> 202511 | C132: GJ | D132: =D131 -> DC11062516 | E132: =D132 -> DC11062516 | F132: =$F$2 -> 45967 | G132: 0 | H132: 37976.8 | I132: =$F$2 -> 45967 | J132: Nov RE Remit - BJROT | K132: LCREE-1470-0000-000-BJROT
A133: LCREE | B133: =Checklist!$B$1 -> 202511 | C133: GJ | D133: =D132 -> DC11062516 | E133: =D133 -> DC11062516 | F133: =$F$2 -> 45967 | G133: 0 | H133: 37305.35 | I133: =$F$2 -> 45967 | J133: Nov RE Remit - DGSUL | K133: LCREE-1470-0000-000-DGSUL
A134: LCREE | B134: =Checklist!$B$1 -> 202511 | C134: GJ | D134: =D133 -> DC11062516 | E134: =D134 -> DC11062516 | F134: =$F$2 -> 45967 | G134: 0 | H134: 35652.82 | I134: =$F$2 -> 45967 | J134: Nov RE Remit - DGCHI | K134: LCREE-1470-0000-000-DGCHI
A135: LCREE | B135: =Checklist!$B$1 -> 202511 | C135: GJ | D135: =D134 -> DC11062516 | E135: =D135 -> DC11062516 | F135: =$F$2 -> 45967 | G135: 0 | H135: 34911.67 | I135: =$F$2 -> 45967 | J135: Nov RE Remit - DGPER | K135: LCREE-1470-0000-000-DGPER
A136: LCREE | B136: =Checklist!$B$1 -> 202511 | C136: GJ | D136: =D135 -> DC11062516 | E136: =D136 -> DC11062516 | F136: =$F$2 -> 45967 | G136: 0 | H136: 30105.82 | I136: =$F$2 -> 45967 | J136: Nov RE Remit - TRANS | K136: LCREE-1470-0000-000-TRANS
A137: LCREE | B137: =Checklist!$B$1 -> 202511 | C137: GJ | D137: =D136 -> DC11062516 | E137: =D137 -> DC11062516 | F137: =$F$2 -> 45967 | G137: 0 | H137: 30066.96 | I137: =$F$2 -> 45967 | J137: Nov RE Remit - DGCEN | K137: LCREE-1470-0000-000-DGCEN
A138: LCREE | B138: =Checklist!$B$1 -> 202511 | C138: GJ | D138: =D137 -> DC11062516 | E138: =D138 -> DC11062516 | F138: =$F$2 -> 45967 | G138: 0 | H138: 23737.19 | I138: =$F$2 -> 45967 | J138: Nov RE Remit - DGCHA | K138: LCREE-1470-0000-000-DGCHA
A139: LCREE | B139: =Checklist!$B$1 -> 202511 | C139: GJ | D139: =D138 -> DC11062516 | E139: =D139 -> DC11062516 | F139: =$F$2 -> 45967 | G139: 0 | H139: 19742.87 | I139: =$F$2 -> 45967 | J139: Nov RE Remit - DGPHI | K139: LCREE-1470-0000-000-DGPHI
A140: LCREE | B140: =Checklist!$B$1 -> 202511 | C140: GJ | D140: =D139 -> DC11062516 | E140: =D140 -> DC11062516 | F140: =$F$2 -> 45967 | G140: 0 | H140: 19199.23 | I140: =$F$2 -> 45967 | J140: Nov RE Remit - DGSHE | K140: LCREE-1470-0000-000-DGSHE
A141: LCREE | B141: =Checklist!$B$1 -> 202511 | C141: GJ | D141: =D140 -> DC11062516 | E141: =D141 -> DC11062516 | F141: =$F$2 -> 45967 | G141: 0 | H141: 15837.41 | I141: =$F$2 -> 45967 | J141: Nov RE Remit - WGFAY | K141: LCREE-1470-0000-000-WGFAY
A142: LCREE | B142: =Checklist!$B$1 -> 202511 | C142: GJ | D142: =D141 -> DC11062516 | E142: =D142 -> DC11062516 | F142: =$F$2 -> 45967 | G142: 0 | H142: 15796.87 | I142: =$F$2 -> 45967 | J142: Nov RE Remit - LTPMS | K142: LCREE-1470-0000-000-LTPMS
A143: LCREE | B143: =Checklist!$B$1 -> 202511 | C143: GJ | D143: =D142 -> DC11062516 | E143: =D143 -> DC11062516 | F143: =$F$2 -> 45967 | G143: 0 | H143: 14254.98 | I143: =$F$2 -> 45967 | J143: Nov RE Remit - LEKMD | K143: LCREE-1470-0000-000-LEKMD
... A188: LCREE | B188: =Checklist!$B$1 -> 202511 | C188: GJ | D188: =D187 -> DC11062516 | E188: =D188 -> DC11062516 | F188: =$F$2 -> 45967 | G188: 0 | H188: 734.31 | I188: =$F$2 -> 45967 | J188: Nov RE Remit - DGCAR | K188: LCREE-1470-0000-000-DGCAR
A189: LCREE | B189: =Checklist!$B$1 -> 202511 | C189: GJ | D189: =D188 -> DC11062516 | E189: =D189 -> DC11062516 | F189: =$F$2 -> 45967 | G189: 0 | H189: 637.27 | I189: =$F$2 -> 45967
A190: LCREE | B190: =Checklist!$B$1 -> 202511 | C190: GJ | D190: =D189 -> DC11062516 | E190: =D190 -> DC11062516 | F190: =$F$2 -> 45967 | G190: 0 | H190: 615.1 | I190: =$F$2 -> 45967 | J190: Nov RE Remit - DGPEL | K190: LCREE-1470-0000-000-DGPEL
A191: LCREE | B191: =Checklist!$B$1 -> 202511 | C191: GJ | D191: =D190 -> DC11062516 | E191: =D191 -> DC11062516 | F191: =$F$2 -> 45967 | G191: 0 | H191: 500.81 | I191: =$F$2 -> 45967 | J191: Nov RE Remit - DGWAB | K191: LCREE-1470-0000-000-DGWAB
A192: LCREE | B192: =Checklist!$B$1 -> 202511 | C192: GJ | D192: =D191 -> DC11062516 | E192: =D192 -> DC11062516 | F192: =$F$2 -> 45967 | G192: 0 | H192: 486.21 | I192: =$F$2 -> 45967
A193: LCREE | B193: =Checklist!$B$1 -> 202511 | C193: GJ | D193: =D192 -> DC11062516 | E193: =D193 -> DC11062516 | F193: =$F$2 -> 45967 | G193: 0 | H193: 428.6 | I193: =$F$2 -> 45967 | J193: Nov RE Remit - DGUNI | K193: LCREE-1470-0000-000-DGUNI
A194: LCREE | B194: =Checklist!$B$1 -> 202511 | C194: GJ | D194: =D193 -> DC11062516 | E194: =D194 -> DC11062516 | F194: =$F$2 -> 45967 | G194: 0 | H194: 295.36 | I194: =$F$2 -> 45967 | J194: Nov RE Remit - DGSTC | K194: LCREE-1470-0000-000-DGSTC
A195: LCREE | B195: =Checklist!$B$1 -> 202511 | C195: GJ | D195: =D194 -> DC11062516 | E195: =D195 -> DC11062516 | F195: =$F$2 -> 45967 | G195: 0 | H195: 245.95 | I195: =$F$2 -> 45967 | J195: Nov RE Remit - DGROC | K195: LCREE-1470-0000-000-DGROC
A196: LCREE | B196: =Checklist!$B$1 -> 202511 | C196: GJ | D196: =D195 -> DC11062516 | E196: =D196 -> DC11062516 | F196: =$F$2 -> 45967 | G196: 0 | H196: 210.38 | I196: =$F$2 -> 45967 | J196: Nov RE Remit - DGOGD | K196: LCREE-1470-0000-000-DGOGD
A197: LCREE | B197: =Checklist!$B$1 -> 202511 | C197: GJ | D197: =D196 -> DC11062516 | E197: =D197 -> DC11062516 | F197: =$F$2 -> 45967 | G197: 0 | H197: 101.82 | I197: =$F$2 -> 45967 | J197: Nov RE Remit - DGFOL | K197: LCREE-1470-0000-000-DGFOL
A198: LCREE | B198: =Checklist!$B$1 -> 202511 | C198: GJ | D198: DC11062517 | E198: =D198 -> DC11062517 | F198: =$F$2 -> 45967 | G198: 7089.16 | H198: 0 | I198: =$F$2 -> 45967 | J198: Nov RE Shortfall - DGSPR | K198: LCREE-1460-0000-000-DGSPR
...

Sheet Cash Activity 11-7
A1: ="Daily Bank Activity - "&MONTH(Checklist!A9)&"/"&DAY(Checklist!A9)&"/"&YEAR(Checklist!A9) -> Daily Bank Activity - 11/7/2025
A2: Credit (+) / Debit (-)
B4: # | C4: Bank | D4: Acct Name | E4: Acct # | F4: Date | G4: Type | H4: Amount | I4: Bank Ref | J4: Bank Stmt Description | K4: Trans Type | L4: Entity | M4: AIT | N4: Short Description | O4: GL Account 1 | P4: GL Account 2 | Q4: Posted?
B5: 1 | C5: PNC | D5: LCFH REIT | E5: 8026459924 | F5: 45968 | G5: CR | H5: 405.16 | I5: '00000000000 | J5: PNC SWEEP INTEREST @ 0.000000 EFFECTIVE DATE 11-06 | K5: =IF(ISNUMBER(SEARCH("Manual Payment - ",N5,1)),"AP",IF(ISNUMBER(SEARCH("Payment - Concur",N5,1)),"WDL",IF(ISNUMBER(SEARCH("Payroll Transfer",N5,1)),"XFR",IF(ISNUMBER(SEARCH("XFR",N5,1)),"XFR",IF(H5>0,"RCT","WDL"))))) -> RCT | L5: =VLOOKUP(D5,'Entity Code'!A:B,2,0) -> LCFHR | N5: Overnight interest sweep PNC LCFHR account. No entry required | O5: N/A | P5: N/A | Q5: N/A
B6: 2 | C6: PNC | D6: LCFH REIT | E6: 8026459924 | F6: 45968 | G6: CR | H6: 4694670.1 | I6: '00000000000 | J6: SWEEP TRANSFR FROM INVESTMENT ACCT 8026459924 | K6: =IF(ISNUMBER(SEARCH("Manual Payment - ",N6,1)),"AP",IF(ISNUMBER(SEARCH("Payment - Concur",N6,1)),"WDL",IF(ISNUMBER(SEARCH("Payroll Transfer",N6,1)),"XFR",IF(ISNUMBER(SEARCH("XFR",N6,1)),"XFR",IF(H6>0,"RCT","WDL"))))) -> RCT | L6: =VLOOKUP(D6,'Entity Code'!A:B,2,0) -> LCFHR | N6: Overnight interest sweep PNC LCFHR account. No entry required | O6: N/A | P6: N/A | Q6: N/A
B7: 3 | C7: PNC | D7: LCFH REIT | E7: 8026459924 | F7: 45968 | G7: DR | H7: -4590075.3 | I7: '00000000000 | J7: SWEEP TO INVESTMENT ACCT# 8026459924 | K7: =IF(ISNUMBER(SEARCH("Manual Payment - ",N7,1)),"AP",IF(ISNUMBER(SEARCH("Payment - Concur",N7,1)),"WDL",IF(ISNUMBER(SEARCH("Payroll Transfer",N7,1)),"XFR",IF(ISNUMBER(SEARCH("XFR",N7,1)),"XFR",IF(H7>0,"RCT","WDL"))))) -> WDL | L7: =VLOOKUP(D7,'Entity Code'!A:B,2,0) -> LCFHR | N7: Overnight interest sweep PNC LCFHR account. No entry required | O7: N/A | P7: N/A | Q7: N/A
B8: 4 | C8: PNC | D8: LCC | E8: 8026482868 | F8: 45968 | G8: DR | H8: -105400 | I8: 'PAB7D1429GGJ096I | J8: WIRE TRANSFER ISO AMT:USD 105400.00 STTLMT DATE:11 | K8: =IF(ISNUMBER(SEARCH("Manual Payment - ",N8,1)),"AP",IF(ISNUMBER(SEARCH("Payment - Concur",N8,1)),"WDL",IF(ISNUMBER(SEARCH("Payroll Transfer",N8,1)),"XFR",IF(ISNUMBER(SEARCH("XFR",N8,1)),"XFR",IF(H8>0,"RCT","WDL"))))) -> WDL | L8: =VLOOKUP(D8,'Entity Code'!A:B,2,0) -> LCC | N8: Stock Repurchase | O8: LCC -3595-0000-000- | P8: N/A | Q8: SS&C to post
B9: 5 | C9: JPM | D9: LADDER CAPITAL CRE EQUITY LLC | E9: 528280121 | F9: 45968 | G9: Debit | H9: -7892.43 | I9: 6095200311JO | J9: FEDWIRE DEBIT | K9: =IF(ISNUMBER(SEARCH("Manual Payment - ",N9,1)),"AP",IF(ISNUMBER(SEARCH("Payment - Concur",N9,1)),"WDL",IF(ISNUMBER(SEARCH("Payroll Transfer",N9,1)),"XFR",IF(ISNUMBER(SEARCH("XFR",N9,1)),"XFR",IF(H9>0,"RCT","WDL"))))) -> WDL | L9: =VLOOKUP(D9,'Entity Code'!A:B,2,0) -> LCREE | N9: Nov RE Shortfall - DGSUN | O9: LCREE-1460-0000-000-DGSUN | P9: N/A | Q9: Ladder to post
B10: 5 | C10: JPM | D10: LADDER CAPITAL CRE EQUITY LLC | E10: 528280121 | F10: 45968 | G10: Debit | H10: -6427.05 | I10: 6095400311JO | J10: FEDWIRE DEBIT | K10: =IF(ISNUMBER(SEARCH("Manual Payment - ",N10,1)),"AP",IF(ISNUMBER(SEARCH("Payment - Concur",N10,1)),"WDL",IF(ISNUMBER(SEARCH("Payroll Transfer",N10,1)),"XFR",IF(ISNUMBER(SEARCH("XFR",N10,1)),"XFR",IF(H10>0,"RCT","WDL"))))) -> WDL | L10: =VLOOKUP(D10,'Entity Code'!A:B,2,0) -> LCREE | N10: Nov RE Shortfall - DGDEN | O10: LCREE-1460-0000-000-DGDEN | P10: N/A | Q10: Ladder to post
B11: 5 | C11: JPM | D11: LADDER CAPITAL CRE EQUITY LLC | E11: 528280121 | F11: 45968 | G11: Debit | H11: -6416.87 | I11: 6095300311JO | J11: FEDWIRE DEBIT | K11: =IF(ISNUMBER(SEARCH("Manual Payment - ",N11,1)),"AP",IF(ISNUMBER(SEARCH("Payment - Concur",N11,1)),"WDL",IF(ISNUMBER(SEARCH("Payroll Transfer",N11,1)),"XFR",IF(ISNUMBER(SEARCH("XFR",N11,1)),"XFR",IF(H11>0,"RCT","WDL"))))) -> WDL | L11: =VLOOKUP(D11,'Entity Code'!A:B,2,0) -> LCREE | N11: Nov RE Shortfall - DGPOR | O11: LCREE-1460-0000-000-DGPOR | P11: N/A | Q11: Ladder to post
B12: 5 | C12: JPM | D12: LADDER CAPITAL CRE EQUITY LLC | E12: 528280121 | F12: 45968 | G12: Debit | H12: -5868.97 | I12: 6095500311JO | J12: FEDWIRE DEBIT | K12: =IF(ISNUMBER(SEARCH("Manual Payment - ",N12,1)),"AP",IF(ISNUMBER(SEARCH("Payment - Concur",N12,1)),"WDL",IF(ISNUMBER(SEARCH("Payroll Transfer",N12,1)),"XFR",IF(ISNUMBER(SEARCH("XFR",N12,1)),"XFR",IF(H12>0,"RCT","WDL"))))) -> WDL | L12: =VLOOKUP(D12,'Entity Code'!A:B,2,0) -> LCREE | N12: Nov RE Shortfall - DGJEF | O12: LCREE-1460-0000-000-DGJEF | P12: N/A | Q12: Ladder to post
B13: 6 | C13: JPM | D13: LADDER CAPITAL FINANCE LLC OPERATIN | E13: 865357602 | F13: 45968 | G13: Credit | H13: 119029.27 | I13: 1233231311FF | J13: FEDWIRE CREDIT | K13: =IF(ISNUMBER(SEARCH("Manual Payment - ",N13,1)),"AP",IF(ISNUMBER(SEARCH("Payment - Concur",N13,1)),"WDL",IF(ISNUMBER(SEARCH("Payroll Transfer",N13,1)),"XFR",IF(ISNUMBER(SEARCH("XFR",N13,1)),"XFR",IF(H13>0,"RCT","WDL"))))) -> RCT | L13: =VLOOKUP(D13,'Entity Code'!A:B,2,0) -> LCF | N13: Meridian Mark Owner's Account Reimbursement | O13: MERID-1001-0000-540- | P13: N/A | Q13: Ladder to post
B14: 7 | C14: PNC | D14: LCREF | E14: 8026497285 | F14: 45968 | G14: CR | H14: 2000000 | I14: '25B7M09565Q17RSH | J14: WIRE TRANSFER ISO AMT:USD 2000000.00 STTLMT DATE:1 | K14: =IF(ISNUMBER(SEARCH("Manual Payment - ",N14,1)),"AP",IF(ISNUMBER(SEARCH("Payment - Concur",N14,1)),"WDL",IF(ISNUMBER(SEARCH("Payroll Transfer",N14,1)),"XFR",IF(ISNUMBER(SEARCH("XFR",N14,1)),"XFR",IF(H14>0,"RCT","WDL"))))) -> RCT | L14: =VLOOKUP(D14,'Entity Code'!A:B,2,0) -> LCREF | N14: Meridian Mark Owner's Account Excess Funds | O14: MERID-1001-0000-540- | P14: N/A | Q14: Ladder to post
B15: 8 | C15: PNC | D15: LCC | E15: 8026482868 | F15: 45968 | G15: CR | H15: 105000 | I15: '25B7I1429KP15I8U | J15: BOOK TRANSFER CREDIT 005I8U ORIGINATOR:LADDER CAPI | K15: =IF(ISNUMBER(SEARCH("Manual Payment - ",N15,1)),"AP",IF(ISNUMBER(SEARCH("Payment - Concur",N15,1)),"WDL",IF(ISNUMBER(SEARCH("Payroll Transfer",N15,1)),"XFR",IF(ISNUMBER(SEARCH("XFR",N15,1)),"XFR",IF(H15>0,"RCT","WDL"))))) -> XFR | L15: =VLOOKUP(D15,'Entity Code'!A:B,2,0) -> LCC | N15: XFR from LCFHR PNC to LCC | O15: 2701-CAMR-000 | P15: N/A | Q15: SS&C to post
B16: 8 | C16: PNC | D16: LCFH REIT | E16: 8026459924 | F16: 45968 | G16: DR | H16: -105000 | I16: '25B7I1429KP15I8U | J16: BOOK TRANSFER DEBIT 005I8U ORIGINATOR:LADDER CAPIT | K16: =IF(ISNUMBER(SEARCH("Manual Payment - ",N16,1)),"AP",IF(ISNUMBER(SEARCH("Payment - Concur",N16,1)),"WDL",IF(ISNUMBER(SEARCH("Payroll Transfer",N16,1)),"XFR",IF(ISNUMBER(SEARCH("XFR",N16,1)),"XFR",IF(H16>0,"RCT","WDL"))))) -> XFR | L16: =VLOOKUP(D16,'Entity Code'!A:B,2,0) -> LCFHR | N16: XFR from LCFHR PNC to LCC | O16: 2701-CAMR-000 | P16: N/A | Q16: SS&C to post
B17: 9 | C17: JPM | D17: LADDER CAPITAL CRE EQUITY LLC | E17: 528280121 | F17: 45968 | G17: Credit | H17: 7500 | I17: 0133520311FC | J17: CHIPS CREDIT | K17: =IF(ISNUMBER(SEARCH("Manual Payment - ",N17,1)),"AP",IF(ISNUMBER(SEARCH("Payment - Concur",N17,1)),"WDL",IF(ISNUMBER(SEARCH("Payroll Transfer",N17,1)),"XFR",IF(ISNUMBER(SEARCH("XFR",N17,1)),"XFR",IF(H17>0,"RCT","WDL"))))) -> XFR | L17: =VLOOKUP(D17,'Entity Code'!A:B,2,0) -> LCREE | N17: XFR from LCREE PNC to LCREE | O17: LCREE-1065-0008-000- | P17: N/A | Q17: Ladder to post
B18: 9 | C18: PNC | D18: CRE EQUITY | E18: 8026496039 | F18: 45968 | G18: DR | H18: -7500 | I18: 'PAB7D1429O3H2ZNG | J18: WIRE TRANSFER ISO AMT:USD 7500.00 STTLMT DATE:1107 | K18: =IF(ISNUMBER(SEARCH("Manual Payment - ",N18,1)),"AP",IF(ISNUMBER(SEARCH("Payment - Concur",N18,1)),"WDL",IF(ISNUMBER(SEARCH("Payroll Transfer",N18,1)),"XFR",IF(ISNUMBER(SEARCH("XFR",N18,1)),"XFR",IF(H18>0,"RCT","WDL"))))) -> XFR | L18: =VLOOKUP(D18,'Entity Code'!A:B,2,0) -> LCREE | N18: XFR from LCREE PNC to LCREE | O18: LCREE-1043-0000-000- | P18: N/A | Q18: Ladder to post
B19: 10 | C19: JPM | D19: LADDER CAPITAL CRE EQUITY LLC | E19: 528280121 | F19: 45968 | G19: Credit | H19: 3000 | I19: 1002936311SB | J19: ATS CREDIT MEMO | K19: =IF(ISNUMBER(SEARCH("Manual Payment - ",N19,1)),"AP",IF(ISNUMBER(SEARCH("Payment - Concur",N19,1)),"WDL",IF(ISNUMBER(SEARCH("Payroll Transfer",N19,1)),"XFR",IF(ISNUMBER(SEARCH("XFR",N19,1)),"XFR",IF(H19>0,"RCT","WDL"))))) -> XFR | L19: =VLOOKUP(D19,'Entity Code'!A:B,2,0) -> LCREE | N19: XFR from LCFHR Trading to LCREE | O19: LCFHR-1046-0000-000- | P19: N/A | Q19: Ladder to post
B20: 10 | C20: JPM | D20: Ladder Capital Finance Holdings REIT | E20: 657597873 | F20: 45968 | G20: Debit | H20: -3000 | I20: 1002936311SB | J20: ATS DEBIT MEMO | K20: =IF(ISNUMBER(SEARCH("Manual Payment - ",N20,1)),"AP",IF(ISNUMBER(SEARCH("Payment - Concur",N20,1)),"WDL",IF(ISNUMBER(SEARCH("Payroll Transfer",N20,1)),"XFR",IF(ISNUMBER(SEARCH("XFR",N20,1)),"XFR",IF(H20>0,"RCT","WDL"))))) -> XFR | L20: =VLOOKUP(D20,'Entity Code'!A:B,2,0) -> LCFHR | N20: XFR from LCFHR Trading to LCREE | O20: LCREE-1043-0000-000- | P20: N/A | Q20: Ladder to post
B21: 11 | C21: JPM | D21: LADDER CAPITAL FINANCE LLC OPERATIN | E21: 865357602 | F21: 45968 | G21: Credit | H21: 600000 | I21: 0147955311FC | J21: CHIPS CREDIT | K21: =IF(ISNUMBER(SEARCH("Manual Payment - ",N21,1)),"AP",IF(ISNUMBER(SEARCH("Payment - Concur",N21,1)),"WDL",IF(ISNUMBER(SEARCH("Payroll Transfer",N21,1)),"XFR",IF(ISNUMBER(SEARCH("XFR",N21,1)),"XFR",IF(H21>0,"RCT","WDL"))))) -> XFR | L21: =VLOOKUP(D21,'Entity Code'!A:B,2,0) -> LCF | N21: XFR from LCF PNC to LCF Operating | O21: 2701-CAMR-000 | P21: N/A | Q21: SS&C to post
B22: 11 | C22: PNC | D22: Ladder Capital Finance | E22: 8026459916 | F22: 45968 | G22: DR | H22: -600000 | I22: 'PAB7F3959PAJ2TBF | J22: WIRE TRANSFER ISO AMT:USD 600000.00 STTLMT DATE:11 | K22: =IF(ISNUMBER(SEARCH("Manual Payment - ",N22,1)),"AP",IF(ISNUMBER(SEARCH("Payment - Concur",N22,1)),"WDL",IF(ISNUMBER(SEARCH("Payroll Transfer",N22,1)),"XFR",IF(ISNUMBER(SEARCH("XFR",N22,1)),"XFR",IF(H22>0,"RCT","WDL"))))) -> XFR | L22: =VLOOKUP(D22,'Entity Code'!A:B,2,0) -> LCF | N22: XFR from LCF PNC to LCF Operating | O22: 2701-CAMR-000 | P22: N/A | Q22: SS&C to post
B23: 12 | C23: JPM | D23: LADDER CAPITAL FINANCE LLC OPERATIN | E23: 865357602 | F23: 45968 | G23: Debit | H23: -50000 | I23: 7753200311JO | J23: FEDWIRE DEBIT | K23: =IF(ISNUMBER(SEARCH("Manual Payment - ",N23,1)),"AP",IF(ISNUMBER(SEARCH("Payment - Concur",N23,1)),"WDL",IF(ISNUMBER(SEARCH("Payroll Transfer",N23,1)),"XFR",IF(ISNUMBER(SEARCH("XFR",N23,1)),"XFR",IF(H23>0,"RCT","WDL"))))) -> AP | L23: =VLOOKUP(D23,'Entity Code'!A:B,2,0) -> LCF | N23: Manual Payment - SASM & F LLP | O23: N/A | P23: N/A | Q23: Ladder to post
B24: 13 | C24: JPM | D24: LADDER CAPITAL FINANCE LLC OPERATIN | E24: 865357602 | F24: 45968 | G24: Debit | H24: -32382 | I24: 7753100311JO | J24: FEDWIRE DEBIT | K24: =IF(ISNUMBER(SEARCH("Manual Payment - ",N24,1)),"AP",IF(ISNUMBER(SEARCH("Payment - Concur",N24,1)),"WDL",IF(ISNUMBER(SEARCH("Payroll Transfer",N24,1)),"XFR",IF(ISNUMBER(SEARCH("XFR",N24,1)),"XFR",IF(H24>0,"RCT","WDL"))))) -> AP | L24: =VLOOKUP(D24,'Entity Code'!A:B,2,0) -> LCF | N24: Manual Payment - Moore & Van Allen | O24: N/A | P24: N/A | Q24: Ladder to post
B25: 14 | C25: JPM | D25: LADDER CAPITAL FINANCE LLC OPERATIN | E25: 865357602 | F25: 45968 | G25: Debit | H25: -119029.67 | I25: 3112112287TC | J25: EFT DEBIT | K25: =IF(ISNUMBER(SEARCH("Manual Payment - ",N25,1)),"AP",IF(ISNUMBER(SEARCH("Payment - Concur",N25,1)),"WDL",IF(ISNUMBER(SEARCH("Payroll Transfer",N25,1)),"XFR",IF(ISNUMBER(SEARCH("XFR",N25,1)),"XFR",IF(H25>0,"RCT","WDL"))))) -> WDL | L25: =VLOOKUP(D25,'Entity Code'!A:B,2,0) -> LCF | N25: Hamilton County Meridian Mark I Tax Bill | P25: N/A | Q25: Ladder to post
B26: 15 | C26: JPM | D26: LADDER CAPITAL FINANCE LLC OPERATIN | E26: 865357602 | F26: 45968 | G26: Debit | H26: -1 | I26: 3112112289TC | J26: EFT DEBIT | K26: =IF(ISNUMBER(SEARCH("Manual Payment - ",N26,1)),"AP",IF(ISNUMBER(SEARCH("Payment - Concur",N26,1)),"WDL",IF(ISNUMBER(SEARCH("Payroll Transfer",N26,1)),"XFR",IF(ISNUMBER(SEARCH("XFR",N26,1)),"XFR",IF(H26>0,"RCT","WDL"))))) -> WDL | L26: =VLOOKUP(D26,'Entity Code'!A:B,2,0) -> LCF | N26: Hamilton County Meridian Mark I Tax Bill Processing Fees | P26: N/A | Q26: Ladder to post
B27: 16 | C27: JPM | D27: LADDER CAPITAL FINANCE LLC OPERATIN | E27: 865357602 | F27: 45968 | G27: Debit | H27: -341575.53 | I27: 3115205055TC | J27: DEBIT ACH SETTLEMENT | K27: =IF(ISNUMBER(SEARCH("Manual Payment - ",N27,1)),"AP",IF(ISNUMBER(SEARCH("Payment - Concur",N27,1)),"WDL",IF(ISNUMBER(SEARCH("Payroll Transfer",N27,1)),"XFR",IF(ISNUMBER(SEARCH("XFR",N27,1)),"XFR",IF(H27>0,"RCT","WDL"))))) -> AP | L27: =VLOOKUP(D27,'Entity Code'!A:B,2,0) -> LCF | N27: Manual Payment - Corp Pay | O27: N/A | P27: N/A | Q27: Ladder to post

Sheet Cash Entries 11-7
A1: ENTITY | B1: YEARMONTH | C1: SOURCE | D1: BATCH ID | E1: BATCH DESCRIPTION | F1: BATCHDATE | G1: DR_AMT | H1: CR AMT | I1: TRXDATE | J1: DIST REFERENCE | K1: GPACCT
A2: LCREE | B2: =Checklist!$B$1 -> 202511 | C2: GJ | D2: =Checklist!$B$10 -> DC1107251 | E2: =D2 -> DC1107251 | F2: =Checklist!$A$9 -> 45968 | G2: 7500 | H2: 0 | I2: =$F$2 -> 45968 | J2: XFR from LCREE PNC to LCREE | K2: LCREE-1043-0000-000-
A3: LCREE | B3: =Checklist!$B$1 -> 202511 | C3: GJ | D3: =D2 -> DC1107251 | E3: =D3 -> DC1107251 | F3: =$F$2 -> 45968 | G3: 0 | H3: 7500 | I3: =$F$2 -> 45968 | J3: XFR from LCREE PNC to LCREE | K3: LCREE-1065-0008-000-
A4: LCREE | B4: =Checklist!$B$1 -> 202511 | C4: GJ | D4: DC1107252 | E4: =D4 -> DC1107252 | F4: =$F$2 -> 45968 | G4: 3000 | H4: 0 | I4: =$F$2 -> 45968 | J4: XFR from LCFHR Trading to LCREE | K4: LCREE-1043-0000-000-
A5: LCREE | B5: =Checklist!$B$1 -> 202511 | C5: GJ | D5: =D4 -> DC1107252 | E5: =D5 -> DC1107252 | F5: =$F$2 -> 45968 | G5: 0 | H5: 3000 | I5: =$F$2 -> 45968 | J5: XFR from LCFHR Trading to LCREE | K5: LCFHR-1046-0000-000-
A6: LCREE | B6: =Checklist!$B$1 -> 202511 | C6: GJ | D6: DC1107253 | E6: =D6 -> DC1107253 | F6: =$F$2 -> 45968 | G6: 7892.43 | H6: 0 | I6: =$F$2 -> 45968 | J6: Nov RE Shortfall - DGSUN | K6: LCREE-1460-0000-000-DGSUN
A7: LCREE | B7: =Checklist!$B$1 -> 202511 | C7: GJ | D7: =D6 -> DC1107253 | E7: =D7 -> DC1107253 | F7: =$F$2 -> 45968 | G7: 6427.05 | H7: 0 | I7: =$F$2 -> 45968 | J7: Nov RE Shortfall - DGDEN | K7: LCREE-1460-0000-000-DGDEN
A8: LCREE | B8: =Checklist!$B$1 -> 202511 | C8: GJ | D8: =D7 -> DC1107253 | E8: =D8 -> DC1107253 | F8: =$F$2 -> 45968 | G8: 6416.87 | H8: 0 | I8: =$F$2 -> 45968 | J8: Nov RE Shortfall - DGPOR | K8: LCREE-1460-0000-000-DGPOR
A9: LCREE | B9: =Checklist!$B$1 -> 202511 | C9: GJ | D9: =D8 -> DC1107253 | E9: =D9 -> DC1107253 | F9: =$F$2 -> 45968 | G9: 5868.97 | H9: 0 | I9: =$F$2 -> 45968 | J9: Nov RE Shortfall - DGJEF | K9: LCREE-1460-0000-000-DGJEF
A10: LCREE | B10: =Checklist!$B$1 -> 202511 | C10: GJ | D10: =D9 -> DC1107253 | E10: =D10 -> DC1107253 | F10: =$F$2 -> 45968 | G10: 0 | H10: 7892.43 | I10: =$F$2 -> 45968 | J10: Nov RE Shortfall - DGSUN | K10: LCREE-1043-0000-000-
A11: LCREE | B11: =Checklist!$B$1 -> 202511 | C11: GJ | D11: =D10 -> DC1107253 | E11: =D11 -> DC1107253 | F11: =$F$2 -> 45968 | G11: 0 | H11: 6427.05 | I11: =$F$2 -> 45968 | J11: Nov RE Shortfall - DGDEN | K11: LCREE-1043-0000-000-
A12: LCREE | B12: =Checklist!$B$1 -> 202511 | C12: GJ | D12: =D11 -> DC1107253 | E12: =D12 -> DC1107253 | F12: =$F$2 -> 45968 | G12: 0 | H12: 6416.87 | I12: =$F$2 -> 45968 | J12: Nov RE Shortfall - DGPOR | K12: LCREE-1043-0000-000-
A13: LCREE | B13: =Checklist!$B$1 -> 202511 | C13: GJ | D13: =D12 -> DC1107253 | E13: =D13 -> DC1107253 | F13: =$F$2 -> 45968 | G13: 0 | H13: 5868.97 | I13: =$F$2 -> 45968 | J13: Nov RE Shortfall - DGJEF | K13: LCREE-1043-0000-000-
A14: LCF | B14: =Checklist!$B$1 -> 202511 | C14: GJ | D14: DC1107254 | E14: =D14 -> DC1107254 | F14: =$F$2 -> 45968 | G14: 119029.27 | H14: 0 | I14: =$F$2 -> 45968 | J14: Meridian Mark Owner's Account Reimbursement | K14: LCF -1027-0000-000-
A15: LCF | B15: =Checklist!$B$1 -> 202511 | C15: GJ | D15: =D14 -> DC1107254 | E15: =D15 -> DC1107254 | F15: =$F$2 -> 45968 | G15: 0 | H15: 119029.27 | I15: =$F$2 -> 45968 | J15: Meridian Mark Owner's Account Reimbursement | K15: LCF -1470-0000-000-MERID
A16: MERID | B16: =Checklist!$B$1 -> 202511 | C16: GJ | D16: =D15 -> DC1107254 | E16: =D16 -> DC1107254 | F16: =$F$2 -> 45968 | G16: 119029.27 | H16: 0 | I16: =$F$2 -> 45968 | J16: Meridian Mark Owner's Account Reimbursement | K16: MERID-3670-0000-000-LCF
A17: MERID | B17: =Checklist!$B$1 -> 202511 | C17: GJ | D17: =D16 -> DC1107254 | E17: =D17 -> DC1107254 | F17: =$F$2 -> 45968 | G17: 0 | H17: 119029.27 | I17: =$F$2 -> 45968 | J17: Meridian Mark Owner's Account Reimbursement | K17: MERID-1001-0000-540-
A18: LCREF | B18: =Checklist!$B$1 -> 202511 | C18: GJ | D18: DC1107255 | E18: =D18 -> DC1107255 | F18: =$F$2 -> 45968 | G18: 2000000 | H18: 0 | I18: =$F$2 -> 45968 | J18: Meridian Mark Owner's Account Excess Funds | K18: LCREF-1065-0008-000-
A19: LCREF | B19: =Checklist!$B$1 -> 202511 | C19: GJ | D19: =D18 -> DC1107255 | E19: =D19 -> DC1107255 | F19: =$F$2 -> 45968 | G19: 0 | H19: 2000000 | I19: =$F$2 -> 45968 | J19: Meridian Mark Owner's Account Excess Funds | K19: LCREF-1470-0000-000-MERID
A20: MERID | B20: =Checklist!$B$1 -> 202511 | C20: GJ | D20: =D19 -> DC1107255 | E20: =D20 -> DC1107255 | F20: =$F$2 -> 45968 | G20: 2000000 | H20: 0 | I20: =$F$2 -> 45968 | J20: Meridian Mark Owner's Account Excess Funds | K20: MERID-3670-0000-000-LCREF
A21: MERID | B21: =Checklist!$B$1 -> 202511 | C21: GJ | D21: =D20 -> DC1107255 | E21: =D21 -> DC1107255 | F21: =$F$2 -> 45968 | G21: 0 | H21: 2000000 | I21: =$F$2 -> 45968 | J21: Meridian Mark Owner's Account Excess Funds | K21: MERID-1001-0000-540-
A22: LCF | B22: =Checklist!$B$1 -> 202511 | C22: GJ | D22: DC1107256 | E22: =D22 -> DC1107256 | F22: =$F$2 -> 45968 | G22: 119029.67 | H22: 0 | I22: =$F$2 -> 45968 | J22: Hamilton County Meridian Mark II Tax Bill | K22: LCF -1460-0000-000-MERID
A23: LCF | B23: =Checklist!$B$1 -> 202511 | C23: GJ | D23: =D22 -> DC1107256 | E23: =D23 -> DC1107256 | F23: =$F$2 -> 45968 | G23: 0 | H23: 119029.67 | I23: =$F$2 -> 45968 | J23: Hamilton County Meridian Mark II Tax Bill | K23: LCF -1027-0000-000-
A24: MERID | B24: =Checklist!$B$1 -> 202511 | C24: GJ | D24: =D23 -> DC1107256 | E24: =D24 -> DC1107256 | F24: =$F$2 -> 45968 | G24: 119029.67 | H24: 0 | I24: =$F$2 -> 45968 | J24: Hamilton County Meridian Mark II Tax Bill | K24: MERID-3660-0000-000-LCF
A25: MERID | B25: =Checklist!$B$1 -> 202511 | C25: GJ | D25: =D24 -> DC1107256 | E25: =D25 -> DC1107256 | F25: =$F$2 -> 45968 | G25: 0 | H25: 119029.67 | I25: =$F$2 -> 45968 | J25: Hamilton County Meridian Mark II Tax Bill
A26: LCF | B26: =Checklist!$B$1 -> 202511 | C26: GJ | D26: DC1107257 | E26: =D26 -> DC1107257 | F26: =$F$2 -> 45968 | G26: 1 | H26: 0 | I26: =$F$2 -> 45968 | J26: Hamilton County Meridian Mark II Tax Bill Processing Fee | K26: LCF -1460-0000-000-MERID
A27: LCF | B27: =Checklist!$B$1 -> 202511 | C27: GJ | D27: =D26 -> DC1107257 | E27: =D27 -> DC1107257 | F27: =$F$2 -> 45968 | G27: 0 | H27: 1 | I27: =$F$2 -> 45968 | J27: Hamilton County Meridian Mark II Tax Bill Processing Fee | K27: LCF -1027-0000-000-
A28: MERID | B28: =Checklist!$B$1 -> 202511 | C28: GJ | D28: =D27 -> DC1107257 | E28: =D28 -> DC1107257 | F28: =$F$2 -> 45968 | G28: 1 | H28: 0 | I28: =$F$2 -> 45968 | J28: Hamilton County Meridian Mark II Tax Bill Processing Fee | K28: MERID-3660-0000-000-LCF
A29: MERID | B29: =Checklist!$B$1 -> 202511 | C29: GJ | D29: =D28 -> DC1107257 | E29: =D29 -> DC1107257 | F29: =$F$2 -> 45968 | G29: 0 | H29: 1 | I29: =$F$2 -> 45968 | J29: Hamilton County Meridian Mark II Tax Bill Processing Fee

Sheet Cash Activity 11 - 10
A1: ="Daily Bank Activity - "&MONTH(Checklist!A10)&"/"&DAY(Checklist!A10)&"/"&YEAR(Checklist!A10) -> Daily Bank Activity - 11/10/2025
A2: Credit (+) / Debit (-)
B4: # | C4: Bank | D4: Acct Name | E4: Acct # | F4: Date | G4: Type | H4: Amount | I4: Bank Ref | J4: Bank Stmt Description | K4: Trans Type | L4: Entity | M4: AIT | N4: Short Description | O4: GL Account 1 | P4: GL Account 2 | Q4: Posted?
B5: 1 | C5: PNC | D5: LCFH REIT | E5: 8026459924 | F5: 45971 | G5: CR | H5: 1188.39 | I5: '00000000000 | J5: PNC SWEEP INTEREST @ 0.000000 EFFECTIVE DATE 11-07 | K5: =IF(ISNUMBER(SEARCH("Manual Payment - ",N5,1)),"AP",IF(ISNUMBER(SEARCH("Payment - Concur",N5,1)),"WDL",IF(ISNUMBER(SEARCH("Payroll Transfer",N5,1)),"XFR",IF(ISNUMBER(SEARCH("XFR",N5,1)),"XFR",IF(H5>0,"RCT","WDL"))))) -> RCT | L5: =VLOOKUP(D5,'Entity Code'!A:B,2,0) -> LCFHR | N5: Overnight interest sweep PNC LCFHR account. No entry required | O5: N/A | P5: N/A | Q5: N/A
B6: 2 | C6: PNC | D6: LCFH REIT | E6: 8026459924 | F6: 45971 | G6: CR | H6: 4590075.3 | I6: '00000000000 | J6: SWEEP TRANSFR FROM INVESTMENT ACCT 8026459924 | K6: =IF(ISNUMBER(SEARCH("Manual Payment - ",N6,1)),"AP",IF(ISNUMBER(SEARCH("Payment - Concur",N6,1)),"WDL",IF(ISNUMBER(SEARCH("Payroll Transfer",N6,1)),"XFR",IF(ISNUMBER(SEARCH("XFR",N6,1)),"XFR",IF(H6>0,"RCT","WDL"))))) -> RCT | L6: =VLOOKUP(D6,'Entity Code'!A:B,2,0) -> LCFHR | N6: Overnight interest sweep PNC LCFHR account. No entry required | O6: N/A | P6: N/A | Q6: N/A
B7: 3 | C7: PNC | D7: LCFH REIT | E7: 8026459924 | F7: 45971 | G7: DR | H7: -14078264 | I7: '00000000000 | J7: SWEEP TO INVESTMENT ACCT# 8026459924 | K7: =IF(ISNUMBER(SEARCH("Manual Payment - ",N7,1)),"AP",IF(ISNUMBER(SEARCH("Payment - Concur",N7,1)),"WDL",IF(ISNUMBER(SEARCH("Payroll Transfer",N7,1)),"XFR",IF(ISNUMBER(SEARCH("XFR",N7,1)),"XFR",IF(H7>0,"RCT","WDL"))))) -> WDL | L7: =VLOOKUP(D7,'Entity Code'!A:B,2,0) -> LCFHR | N7: Overnight interest sweep PNC LCFHR account. No entry required | O7: N/A | P7: N/A | Q7: N/A
B8: 4 | C8: JPM | D8: LADDER CAPITAL CRE EQUITY LLC | E8: 528280121 | F8: 45971 | G8: Credit | H8: 19213.38 | I8: 0233281314FF | J8: FEDWIRE CREDIT | K8: =IF(ISNUMBER(SEARCH("Manual Payment - ",N8,1)),"AP",IF(ISNUMBER(SEARCH("Payment - Concur",N8,1)),"WDL",IF(ISNUMBER(SEARCH("Payroll Transfer",N8,1)),"XFR",IF(ISNUMBER(SEARCH("XFR",N8,1)),"XFR",IF(H8>0,"RCT","WDL"))))) -> RCT | L8: =VLOOKUP(D8,'Entity Code'!A:B,2,0) -> LCREE | N8: Excess Funds - DGEFF | O8: LCREE-1470-0000-000-DGEFF | P8: N/A | Q8: Ladder to post
B9: 5 | C9: PNC | D9: LCF Borrower Deposits | E9: 8026478877 | F9: 45971 | G9: CR | H9: 30000 | I9: '25BAH30485WZ62SY | J9: WIRE TRANSFER ISO AMT:USD 30000.00 STTLMT DATE:111 | K9: =IF(ISNUMBER(SEARCH("Manual Payment - ",N9,1)),"AP",IF(ISNUMBER(SEARCH("Payment - Concur",N9,1)),"WDL",IF(ISNUMBER(SEARCH("Payroll Transfer",N9,1)),"XFR",IF(ISNUMBER(SEARCH("XFR",N9,1)),"XFR",IF(H9>0,"RCT","WDL"))))) -> RCT | L9: =VLOOKUP(D9,'Entity Code'!A:B,2,0) -> LCF | N9: Loan Deposit - The Sage at 1955 (2nd Deposit) | O9: 2701-LMS0-000 | P9: N/A | Q9: SS&C to post
B10: 6 | C10: PNC | D10: LCF Borrower Deposits | E10: 8026478877 | F10: 45971 | G10: CR | H10: 85000 | I10: '25BAL18549MZ7UJC | J10: WIRE TRANSFER ISO AMT:USD 85000.00 STTLMT DATE:111 | K10: =IF(ISNUMBER(SEARCH("Manual Payment - ",N10,1)),"AP",IF(ISNUMBER(SEARCH("Payment - Concur",N10,1)),"WDL",IF(ISNUMBER(SEARCH("Payroll Transfer",N10,1)),"XFR",IF(ISNUMBER(SEARCH("XFR",N10,1)),"XFR",IF(H10>0,"RCT","WDL"))))) -> RCT | L10: =VLOOKUP(D10,'Entity Code'!A:B,2,0) -> LCF | N10: Loan Deposit - Dalmore Apartments | O10: 2701-LMS0-000 | P10: N/A | Q10: SS&C to post
B11: 7 | C11: JPM | D11: TUEBOR REIT INC | E11: 780181777 | F11: 45971 | G11: Credit | H11: 150000 | I11: 0152596314FC | J11: CHIPS CREDIT | K11: =IF(ISNUMBER(SEARCH("Manual Payment - ",N11,1)),"AP",IF(ISNUMBER(SEARCH("Payment - Concur",N11,1)),"WDL",IF(ISNUMBER(SEARCH("Payroll Transfer",N11,1)),"XFR",IF(ISNUMBER(SEARCH("XFR",N11,1)),"XFR",IF(H11>0,"RCT","WDL"))))) -> RCT | L11: =VLOOKUP(D11,'Entity Code'!A:B,2,0) -> TUERI | N11: HAP Harlem Proceeds | O11: 2701-LMS0-000 | P11: N/A | Q11: SS&C to post
B12: 8 | C12: PNC | D12: CRE EQUITY | E12: 8026496039 | F12: 45971 | G12: CR | H12: 822429.43 | I12: '25311005450383 | J12: ACH CREDIT RECEIVED - Cust ID: 0003201685 Desc: CO | K12: =IF(ISNUMBER(SEARCH("Manual Payment - ",N12,1)),"AP",IF(ISNUMBER(SEARCH("Payment - Concur",N12,1)),"WDL",IF(ISNUMBER(SEARCH("Payroll Transfer",N12,1)),"XFR",IF(ISNUMBER(SEARCH("XFR",N12,1)),"XFR",IF(H12>0,"RCT","WDL"))))) -> RCT | L12: =VLOOKUP(D12,'Entity Code'!A:B,2,0) -> LCREE | N12: Rental Income & Tax Reimbursement | O12: Various | P12: N/A | Q12: Ladder to post
B13: 9 | C13: JPM | D13: TUEBOR REIT INC | E13: 780181777 | F13: 45971 | G13: Credit | H13: 324288.54 | I13: 0169812314FC | J13: CHIPS CREDIT | K13: =IF(ISNUMBER(SEARCH("Manual Payment - ",N13,1)),"AP",IF(ISNUMBER(SEARCH("Payment - Concur",N13,1)),"WDL",IF(ISNUMBER(SEARCH("Payroll Transfer",N13,1)),"XFR",IF(ISNUMBER(SEARCH("XFR",N13,1)),"XFR",IF(H13>0,"RCT","WDL"))))) -> RCT | L13: =VLOOKUP(D13,'Entity Code'!A:B,2,0) -> TUERI | N13: Loan P&I Remit | O13: 2701-LMS0-000 | P13: N/A | Q13: SS&C to post
B14: 10 | C14: PNC | D14: LCREF | E14: 8026497285 | F14: 45971 | G14: CR | H14: 3218018.2 | I14: '25BAM2215PK00JMA | J14: WIRE TRANSFER ISO AMT:USD 3218018.21 STTLMT DATE:1 | K14: =IF(ISNUMBER(SEARCH("Manual Payment - ",N14,1)),"AP",IF(ISNUMBER(SEARCH("Payment - Concur",N14,1)),"WDL",IF(ISNUMBER(SEARCH("Payroll Transfer",N14,1)),"XFR",IF(ISNUMBER(SEARCH("XFR",N14,1)),"XFR",IF(H14>0,"RCT","WDL"))))) -> RCT | L14: =VLOOKUP(D14,'Entity Code'!A:B,2,0) -> LCREF | N14: Loan P&I Remit | O14: 2701-LMS0-000 | P14: N/A | Q14: SS&C to post
B15: 11 | C15: PNC | D15: LCREF | E15: 8026497285 | F15: 45971 | G15: CR | H15: 476723.21 | I15: '25BAL40112P069H2 | J15: WIRE TRANSFER ISO AMT:USD 476723.21 STTLMT DATE:11 | K15: =IF(ISNUMBER(SEARCH("Manual Payment - ",N15,1)),"AP",IF(ISNUMBER(SEARCH("Payment - Concur",N15,1)),"WDL",IF(ISNUMBER(SEARCH("Payroll Transfer",N15,1)),"XFR",IF(ISNUMBER(SEARCH("XFR",N15,1)),"XFR",IF(H15>0,"RCT","WDL"))))) -> RCT | L15: =VLOOKUP(D15,'Entity Code'!A:B,2,0) -> LCREF | N15: Loan P&I Remit - Situs | O15: 2701-LMS0-000 | P15: N/A | Q15: SS&C to post
B16: 12 | C16: PNC | D16: LCR 3 | E16: 8026496047 | F16: 45971 | G16: CR | H16: 3653238.3 | I16: '25BAM2118OL03ZJ0 | J16: WIRE TRANSFER ISO AMT:USD 3653238.28 STTLMT DATE:1 | K16: =IF(ISNUMBER(SEARCH("Manual Payment - ",N16,1)),"AP",IF(ISNUMBER(SEARCH("Payment - Concur",N16,1)),"WDL",IF(ISNUMBER(SEARCH("Payroll Transfer",N16,1)),"XFR",IF(ISNUMBER(SEARCH("XFR",N16,1)),"XFR",IF(H16>0,"RCT","WDL"))))) -> RCT | L16: =VLOOKUP(D16,'Entity Code'!A:B,2,0) -> LCR3 | N16: Loan P&I Remit | O16: 2701-LMS0-000 | P16: N/A | Q16: SS&C to post
B17: 13 | C17: PNC | D17: LCR 3 | E17: 8026496047 | F17: 45971 | G17: CR | H17: 2186100 | I17: '25BAL401156Z5RKT | J17: WIRE TRANSFER ISO AMT:USD 2186100.01 STTLMT DATE:1 | K17: =IF(ISNUMBER(SEARCH("Manual Payment - ",N17,1)),"AP",IF(ISNUMBER(SEARCH("Payment - Concur",N17,1)),"WDL",IF(ISNUMBER(SEARCH("Payroll Transfer",N17,1)),"XFR",IF(ISNUMBER(SEARCH("XFR",N17,1)),"XFR",IF(H17>0,"RCT","WDL"))))) -> RCT | L17: =VLOOKUP(D17,'Entity Code'!A:B,2,0) -> LCR3 | N17: Loan P&I Remit - Situs | O17: 2701-LMS0-000 | P17: N/A | Q17: SS&C to post
B18: 14 | C18: PNC | D18: Ladder Capital Finance | E18: 8026459916 | F18: 45971 | G18: CR | H18: 1069275 | I18: '25BAM21213S00XJ4 | J18: WIRE TRANSFER ISO AMT:USD 1069275.04 STTLMT DATE:1 | K18: =IF(ISNUMBER(SEARCH("Manual Payment - ",N18,1)),"AP",IF(ISNUMBER(SEARCH("Payment - Concur",N18,1)),"WDL",IF(ISNUMBER(SEARCH("Payroll Transfer",N18,1)),"XFR",IF(ISNUMBER(SEARCH("XFR",N18,1)),"XFR",IF(H18>0,"RCT","WDL"))))) -> RCT | L18: =VLOOKUP(D18,'Entity Code'!A:B,2,0) -> LCF | N18: Loan P&I Remit | O18: 2701-LMS0-000 | P18: N/A | Q18: SS&C to post
B19: 15 | C19: PNC | D19: LCFH REIT | E19: 8026459924 | F19: 45971 | G19: CR | H19: 10000000 | I19: '25BAE4450O301LF8 | J19: WIRE TRANSFER ISO STTLMT DATE:11102025 CLR SYS REF | K19: =IF(ISNUMBER(SEARCH("Manual Payment - ",N19,1)),"AP",IF(ISNUMBER(SEARCH("Payment - Concur",N19,1)),"WDL",IF(ISNUMBER(SEARCH("Payroll Transfer",N19,1)),"XFR",IF(ISNUMBER(SEARCH("XFR",N19,1)),"XFR",IF(H19>0,"RCT","WDL"))))) -> XFR | L19: =VLOOKUP(D19,'Entity Code'!A:B,2,0) -> LCFHR | N19: XFR from LCFHR BNY to LCFHR PNC | O19: 2701-CAMR-000 | P19: N/A | Q19: SS&C to post
B20: 16 | C20: PNC | D20: LCFH REIT | E20: 8026459924 | F20: 45971 | G20: DR | H20: -10170000 | I20: 'PABAA1208JVJ44T4 | J20: WIRE TRANSFER ISO AMT:USD 10170000.00 STTLMT DATE: | K20: =IF(ISNUMBER(SEARCH("Manual Payment - ",N20,1)),"AP",IF(ISNUMBER(SEARCH("Payment - Concur",N20,1)),"WDL",IF(ISNUMBER(SEARCH("Payroll Transfer",N20,1)),"XFR",IF(ISNUMBER(SEARCH("XFR",N20,1)),"XFR",IF(H20>0,"RCT","WDL"))))) -> XFR | L20: =VLOOKUP(D20,'Entity Code'!A:B,2,0) -> LCFHR | N20: XFR from LCFHR PNC to LCFP3 | O20: 2701-CAMR-000 | P20: N/A | Q20: SS&C to post
B21: 17 | C21: PNC | D21: LCI | E21: 8026496012 | F21: 45971 | G21: CR | H21: 1000000 | I21: '25BAF1208BVZ3YUI | J21: BOOK TRANSFER CREDIT 003YUI ORIGINATOR:LADDER CAPI | K21: =IF(ISNUMBER(SEARCH("Manual Payment - ",N21,1)),"AP",IF(ISNUMBER(SEARCH("Payment - Concur",N21,1)),"WDL",IF(ISNUMBER(SEARCH("Payroll Transfer",N21,1)),"XFR",IF(ISNUMBER(SEARCH("XFR",N21,1)),"XFR",IF(H21>0,"RCT","WDL"))))) -> XFR | L21: =VLOOKUP(D21,'Entity Code'!A:B,2,0) -> LCI | N21: XFR from LCFHR PNC to LCI PNC | O21: 2701-CAMR-000 | P21: N/A | Q21: SS&C to post
B22: 17 | C22: PNC | D22: LCFH REIT | E22: 8026459924 | F22: 45971 | G22: DR | H22: -1000000 | I22: '25BAF1208BVZ3YUI | J22: BOOK TRANSFER DEBIT 003YUI ORIGINATOR:LADDER CAPIT | K22: =IF(ISNUMBER(SEARCH("Manual Payment - ",N22,1)),"AP",IF(ISNUMBER(SEARCH("Payment - Concur",N22,1)),"WDL",IF(ISNUMBER(SEARCH("Payroll Transfer",N22,1)),"XFR",IF(ISNUMBER(SEARCH("XFR",N22,1)),"XFR",IF(H22>0,"RCT","WDL"))))) -> XFR | L22: =VLOOKUP(D22,'Entity Code'!A:B,2,0) -> LCFHR | N22: XFR from LCFHR PNC to LCI PNC | O22: 2701-CAMR-000 | P22: N/A | Q22: SS&C to post
B23: 18 | C23: PNC | D23: LCI | E23: 8026496012 | F23: 45971 | G23: DR | H23: -1000000 | I23: 'PABAA12085EJ1QSG | J23: WIRE TRANSFER ISO AMT:USD 1000000.00 STTLMT DATE:1 | K23: =IF(ISNUMBER(SEARCH("Manual Payment - ",N23,1)),"AP",IF(ISNUMBER(SEARCH("Payment - Concur",N23,1)),"WDL",IF(ISNUMBER(SEARCH("Payroll Transfer",N23,1)),"XFR",IF(ISNUMBER(SEARCH("XFR",N23,1)),"XFR",IF(H23>0,"RCT","WDL"))))) -> XFR | L23: =VLOOKUP(D23,'Entity Code'!A:B,2,0) -> LCI | N23: XFR from LCI PNC to LCFP | O23: 2701-CAMR-000 | P23: N/A | Q23: SS&C to post
B24: 19 | C24: PNC | D24: LADDER CRE PARENT | E24: 8026497277 | F24: 45971 | G24: CR | H24: 2000000 | I24: '25BAF12086H06OOU | J24: BOOK TRANSFER CREDIT 006OOU ORIGINATOR:LADDER CRE | K24: =IF(ISNUMBER(SEARCH("Manual Payment - ",N24,1)),"AP",IF(ISNUMBER(SEARCH("Payment - Concur",N24,1)),"WDL",IF(ISNUMBER(SEARCH("Payroll Transfer",N24,1)),"XFR",IF(ISNUMBER(SEARCH("XFR",N24,1)),"XFR",IF(H24>0,"RCT","WDL"))))) -> RCT | L24: =VLOOKUP(D24,'Entity Code'!A:B,2,0) -> LCREP | N24: Dividend Payment | O24: LCREP-1470-0000-000-LCREF | P24: N/A | Q24: Ladder to post
B25: 19 | C25: PNC | D25: LCREF | E25: 8026497285 | F25: 45971 | G25: DR | H25: -2000000 | I25: '25BAF12086H06OOU | J25: BOOK TRANSFER DEBIT 006OOU ORIGINATOR:LADDER CRE F | K25: =IF(ISNUMBER(SEARCH("Manual Payment - ",N25,1)),"AP",IF(ISNUMBER(SEARCH("Payment - Concur",N25,1)),"WDL",IF(ISNUMBER(SEARCH("Payroll Transfer",N25,1)),"XFR",IF(ISNUMBER(SEARCH("XFR",N25,1)),"XFR",IF(H25>0,"RCT","WDL"))))) -> WDL | L25: =VLOOKUP(D25,'Entity Code'!A:B,2,0) -> LCREF | N25: Dividend Payment | O25: LCREF-3670-0000-000-LCREP | P25: N/A | Q25: Ladder to post
... B35: 24 | C35: PNC | D35: LC TRS I | E35: 8026495984 | F35: 45971 | G35: DR | H35: -600000 | I35: '25BAF12080OZ5PUD | J35: BOOK TRANSFER DEBIT 005PUD ORIGINATOR:LC TRS I LLC | K35: =IF(ISNUMBER(SEARCH("Manual Payment - ",N35,1)),"AP",IF(ISNUMBER(SEARCH("Payment - Concur",N35,1)),"WDL",IF(ISNUMBER(SEARCH("Payroll Transfer",N35,1)),"XFR",IF(ISNUMBER(SEARCH("XFR",N35,1)),"XFR",IF(H35>0,"RCT","WDL"))))) -> XFR | L35: =VLOOKUP(D35,'Entity Code'!A:B,2,0) -> LTRS1 | N35: XFR from TRS1 PNC to LCF PNC | O35: 2701-CAMR-000 | P35: N/A | Q35: SS&C to post
B36: 25 | C36: PNC | D36: LCF Payroll | E36: 8147891123 | F36: 45971 | G36: CR | H36: 585496.6 | I36: '25BAF1208D710DZF | J36: BOOK TRANSFER CREDIT 000DZF ORIGINATOR:LADDER CAPI | K36: =IF(ISNUMBER(SEARCH("Manual Payment - ",N36,1)),"AP",IF(ISNUMBER(SEARCH("Payment - Concur",N36,1)),"WDL",IF(ISNUMBER(SEARCH("Payroll Transfer",N36,1)),"XFR",IF(ISNUMBER(SEARCH("XFR",N36,1)),"XFR",IF(H36>0,"RCT","WDL"))))) -> XFR | L36: =VLOOKUP(D36,'Entity Code'!A:B,2,0) -> LCF | N36: Payroll Transfer | O36: =IFERROR(VLOOKUP(E37,'Bank Account'!A:B,2,FALSE),VLOOKUP(_xlfn.NUMBERVALUE(E37),'Bank Account'!A:B,2,FALSE)) -> LCF -1065-0001-000- | P36: N/A | Q36: Ladder to post
B37: 25 | C37: PNC | D37: Ladder Capital Finance | E37: 8026459916 | F37: 45971 | G37: DR | H37: -585496.6 | I37: '25BAF1208D710DZF | J37: BOOK TRANSFER DEBIT 000DZF ORIGINATOR:LADDER CAPIT | K37: =IF(ISNUMBER(SEARCH("Manual Payment - ",N37,1)),"AP",IF(ISNUMBER(SEARCH("Payment - Concur",N37,1)),"WDL",IF(ISNUMBER(SEARCH("Payroll Transfer",N37,1)),"XFR",IF(ISNUMBER(SEARCH("XFR",N37,1)),"XFR",IF(H37>0,"RCT","WDL"))))) -> XFR | L37: =VLOOKUP(D37,'Entity Code'!A:B,2,0) -> LCF | N37: Payroll Transfer | O37: =IFERROR(VLOOKUP(E36,'Bank Account'!A:B,2,FALSE),VLOOKUP(_xlfn.NUMBERVALUE(E36),'Bank Account'!A:B,2,FALSE)) -> LCF -1006-0000-000- | P37: N/A | Q37: Ladder to post
B38: 26 | C38: PNC | D38: LCI | E38: 8026496012 | F38: 45971 | G38: CR | H38: 233000 | I38: '25BAL3722MIZ6LNK | J38: BOOK TRANSFER CREDIT 006LNK ORIGINATOR:LADDER CAPI | K38: =IF(ISNUMBER(SEARCH("Manual Payment - ",N38,1)),"AP",IF(ISNUMBER(SEARCH("Payment - Concur",N38,1)),"WDL",IF(ISNUMBER(SEARCH("Payroll Transfer",N38,1)),"XFR",IF(ISNUMBER(SEARCH("XFR",N38,1)),"XFR",IF(H38>0,"RCT","WDL"))))) -> XFR | L38: =VLOOKUP(D38,'Entity Code'!A:B,2,0) -> LCI | N38: XFR from LCFHR PNC to LCI PNC | O38: 2701-CAMR-000 | P38: N/A | Q38: SS&C to post
B39: 26 | C39: PNC | D39: LCFH REIT | E39: 8026459924 | F39: 45971 | G39: DR | H39: -233000 | I39: '25BAL3722MIZ6LNK | J39: BOOK TRANSFER DEBIT 006LNK ORIGINATOR:LADDER CAPIT | K39: =IF(ISNUMBER(SEARCH("Manual Payment - ",N39,1)),"AP",IF(ISNUMBER(SEARCH("Payment - Concur",N39,1)),"WDL",IF(ISNUMBER(SEARCH("Payroll Transfer",N39,1)),"XFR",IF(ISNUMBER(SEARCH("XFR",N39,1)),"XFR",IF(H39>0,"RCT","WDL"))))) -> XFR | L39: =VLOOKUP(D39,'Entity Code'!A:B,2,0) -> LCFHR | N39: XFR from LCFHR PNC to LCI PNC | O39: 2701-CAMR-000 | P39: N/A | Q39: SS&C to post
B40: 27 | C40: PNC | D40: LCI | E40: 8026496012 | F40: 45971 | G40: DR | H40: -233000 | I40: 'PABAG3722DPH4IOY | J40: WIRE TRANSFER ISO AMT:USD 233000.00 STTLMT DATE:11 | K40: =IF(ISNUMBER(SEARCH("Manual Payment - ",N40,1)),"AP",IF(ISNUMBER(SEARCH("Payment - Concur",N40,1)),"WDL",IF(ISNUMBER(SEARCH("Payroll Transfer",N40,1)),"XFR",IF(ISNUMBER(SEARCH("XFR",N40,1)),"XFR",IF(H40>0,"RCT","WDL"))))) -> XFR | L40: =VLOOKUP(D40,'Entity Code'!A:B,2,0) -> LCI | N40: XFR from LCI PNC to LCFP Equity PB | O40: 2701-CAMR-000 | P40: N/A | Q40: SS&C to post
B41: 28 | C41: PNC | D41: LCFH REIT | E41: 8026459924 | F41: 45971 | G41: CR | H41: 5847000 | I41: '25BAM4548DE17ETF | J41: BOOK TRANSFER CREDIT 007ETF ORIGINATOR:LADDER CAPI | K41: =IF(ISNUMBER(SEARCH("Manual Payment - ",N41,1)),"AP",IF(ISNUMBER(SEARCH("Payment - Concur",N41,1)),"WDL",IF(ISNUMBER(SEARCH("Payroll Transfer",N41,1)),"XFR",IF(ISNUMBER(SEARCH("XFR",N41,1)),"XFR",IF(H41>0,"RCT","WDL"))))) -> XFR | L41: =VLOOKUP(D41,'Entity Code'!A:B,2,0) -> LCFHR | N41: XFR from LCR3 PNC to LCFHR PNC | O41: 2701-CAMR-000 | P41: N/A | Q41: SS&C to post
B42: 28 | C42: PNC | D42: LCR 3 | E42: 8026496047 | F42: 45971 | G42: DR | H42: -5847000 | I42: '25BAM4548DE17ETF | J42: BOOK TRANSFER DEBIT 007ETF ORIGINATOR:LADDER CAPIT | K42: =IF(ISNUMBER(SEARCH("Manual Payment - ",N42,1)),"AP",IF(ISNUMBER(SEARCH("Payment - Concur",N42,1)),"WDL",IF(ISNUMBER(SEARCH("Payroll Transfer",N42,1)),"XFR",IF(ISNUMBER(SEARCH("XFR",N42,1)),"XFR",IF(H42>0,"RCT","WDL"))))) -> XFR | L42: =VLOOKUP(D42,'Entity Code'!A:B,2,0) -> LCR3 | N42: XFR from LCR3 PNC to LCFHR PNC | O42: 2701-CAMR-000 | P42: N/A | Q42: SS&C to post
B43: 29 | C43: PNC | D43: LADDER CRE PARENT | E43: 8026497277 | F43: 45971 | G43: CR | H43: 3700000 | I43: '25BAM4548AFZ29LT | J43: BOOK TRANSFER CREDIT 0029LT ORIGINATOR:LADDER CRE | K43: =IF(ISNUMBER(SEARCH("Manual Payment - ",N43,1)),"AP",IF(ISNUMBER(SEARCH("Payment - Concur",N43,1)),"WDL",IF(ISNUMBER(SEARCH("Payroll Transfer",N43,1)),"XFR",IF(ISNUMBER(SEARCH("XFR",N43,1)),"XFR",IF(H43>0,"RCT","WDL"))))) -> RCT | L43: =VLOOKUP(D43,'Entity Code'!A:B,2,0) -> LCREP | N43: Dividend Payment | O43: LCREP-1470-0000-000-LCREF | P43: N/A | Q43: Ladder to post
B44: 29 | C44: PNC | D44: LCREF | E44: 8026497285 | F44: 45971 | G44: DR | H44: -3700000 | I44: '25BAM4548AFZ29LT | J44: BOOK TRANSFER DEBIT 0029LT ORIGINATOR:LADDER CRE F | K44: =IF(ISNUMBER(SEARCH("Manual Payment - ",N44,1)),"AP",IF(ISNUMBER(SEARCH("Payment - Concur",N44,1)),"WDL",IF(ISNUMBER(SEARCH("Payroll Transfer",N44,1)),"XFR",IF(ISNUMBER(SEARCH("XFR",N44,1)),"XFR",IF(H44>0,"RCT","WDL"))))) -> WDL | L44: =VLOOKUP(D44,'Entity Code'!A:B,2,0) -> LCREF | N44: Dividend Payment | O44: LCREF-3670-0000-000-LCREP | P44: N/A | Q44: Ladder to post
B45: 30 | C45: PNC | D45: LCFH REIT | E45: 8026459924 | F45: 45971 | G45: CR | H45: 3663000 | I45: '25BAM4622DK13MY0 | J45: BOOK TRANSFER CREDIT 003MY0 ORIGINATOR:LADDER CRE | K45: =IF(ISNUMBER(SEARCH("Manual Payment - ",N45,1)),"AP",IF(ISNUMBER(SEARCH("Payment - Concur",N45,1)),"WDL",IF(ISNUMBER(SEARCH("Payroll Transfer",N45,1)),"XFR",IF(ISNUMBER(SEARCH("XFR",N45,1)),"XFR",IF(H45>0,"RCT","WDL"))))) -> RCT | L45: =VLOOKUP(D45,'Entity Code'!A:B,2,0) -> LCFHR | N45: Partnership Distribution | O45: MID2R-1470-0000-000-LCREP | P45: N/A | Q45: Ladder to post
B46: 30 | C46: PNC | D46: LADDER CRE PARENT | E46: 8026497277 | F46: 45971 | G46: DR | H46: -3663000 | I46: '25BAM4622DK13MY0 | J46: BOOK TRANSFER DEBIT 003MY0 ORIGINATOR:LADDER CRE P | K46: =IF(ISNUMBER(SEARCH("Manual Payment - ",N46,1)),"AP",IF(ISNUMBER(SEARCH("Payment - Concur",N46,1)),"WDL",IF(ISNUMBER(SEARCH("Payroll Transfer",N46,1)),"XFR",IF(ISNUMBER(SEARCH("XFR",N46,1)),"XFR",IF(H46>0,"RCT","WDL"))))) -> WDL | L46: =VLOOKUP(D46,'Entity Code'!A:B,2,0) -> LCREP | N46: Partnership Distribution | O46: LCREP-3670-0000-000-MID2R | P46: N/A | Q46: Ladder to post
B47: 31 | C47: PNC | D47: Ladder Capital Finance | E47: 8026459916 | F47: 45971 | G47: CR | H47: 37000 | I47: '25BAM4622DV147Y2 | J47: BOOK TRANSFER CREDIT 0047Y2 ORIGINATOR:LADDER CRE | K47: =IF(ISNUMBER(SEARCH("Manual Payment - ",N47,1)),"AP",IF(ISNUMBER(SEARCH("Payment - Concur",N47,1)),"WDL",IF(ISNUMBER(SEARCH("Payroll Transfer",N47,1)),"XFR",IF(ISNUMBER(SEARCH("XFR",N47,1)),"XFR",IF(H47>0,"RCT","WDL"))))) -> RCT | L47: =VLOOKUP(D47,'Entity Code'!A:B,2,0) -> LCF | N47: Partnership Distribution | O47: LMID2-1470-0000-000-LCREP | P47: N/A | Q47: Ladder to post
B48: 31 | C48: PNC | D48: LADDER CRE PARENT | E48: 8026497277 | F48: 45971 | G48: DR | H48: -37000 | I48: '25BAM4622DV147Y2 | J48: BOOK TRANSFER DEBIT 0047Y2 ORIGINATOR:LADDER CRE P | K48: =IF(ISNUMBER(SEARCH("Manual Payment - ",N48,1)),"AP",IF(ISNUMBER(SEARCH("Payment - Concur",N48,1)),"WDL",IF(ISNUMBER(SEARCH("Payroll Transfer",N48,1)),"XFR",IF(ISNUMBER(SEARCH("XFR",N48,1)),"XFR",IF(H48>0,"RCT","WDL"))))) -> WDL | L48: =VLOOKUP(D48,'Entity Code'!A:B,2,0) -> LCREP | N48: Partnership Distribution | O48: LCREP-3670-0000-000-LMID2 | P48: N/A | Q48: Ladder to post
B49: 32 | C49: JPM | D49: LADDER CAPITAL FINANCE LLC OPERATIN | E49: 865357602 | F49: 45971 | G49: Credit | H49: 1 | I49: 0529951314EZ | J49: BOOK TRANSFER CREDIT | K49: =IF(ISNUMBER(SEARCH("Manual Payment - ",N49,1)),"AP",IF(ISNUMBER(SEARCH("Payment - Concur",N49,1)),"WDL",IF(ISNUMBER(SEARCH("Payroll Transfer",N49,1)),"XFR",IF(ISNUMBER(SEARCH("XFR",N49,1)),"XFR",IF(H49>0,"RCT","WDL"))))) -> XFR | L49: =VLOOKUP(D49,'Entity Code'!A:B,2,0) -> LCF | N49: XFR from LCF PNC to LCF Operating | O49: 2701-CAMR-000 | P49: N/A | Q49: SS&C to post
B50: 32 | C50: PNC | D50: Ladder Capital Finance | E50: 8026459916 | F50: 45971 | G50: DR | H50: -1 | I50: '25BAH0511A8139NW | J50: WIRE TRANSFER ISO STTLMT DATE:11102025 CLR SYS REF | K50: =IF(ISNUMBER(SEARCH("Manual Payment - ",N50,1)),"AP",IF(ISNUMBER(SEARCH("Payment - Concur",N50,1)),"WDL",IF(ISNUMBER(SEARCH("Payroll Transfer",N50,1)),"XFR",IF(ISNUMBER(SEARCH("XFR",N50,1)),"XFR",IF(H50>0,"RCT","WDL"))))) -> XFR | L50: =VLOOKUP(D50,'Entity Code'!A:B,2,0) -> LCF | N50: XFR from LCF PNC to LCF Operating | O50: 2701-CAMR-000 | P50: N/A | Q50: SS&C to post
B51: 33 | C51: JPM | D51: LADDER CAPITAL FINANCE LLC OPERATIN | E51: 865357602 | F51: 45971 | G51: Debit | H51: -20876 | I51: 3144671070TC | J51: DEBIT ACH SETTLEMENT | K51: =IF(ISNUMBER(SEARCH("Manual Payment - ",N51,1)),"AP",IF(ISNUMBER(SEARCH("Payment - Concur",N51,1)),"WDL",IF(ISNUMBER(SEARCH("Payroll Transfer",N51,1)),"XFR",IF(ISNUMBER(SEARCH("XFR",N51,1)),"XFR",IF(H51>0,"RCT","WDL"))))) -> AP | L51: =VLOOKUP(D51,'Entity Code'!A:B,2,0) -> LCF | N51: Manual Payment - Corp Pay | O51: N/A | P51: N/A | Q51: Ladder to post

Sheet Cash Entries 11 - 10
A1: ENTITY | B1: YEARMONTH | C1: SOURCE | D1: BATCH ID | E1: BATCH DESCRIPTION | F1: BATCHDATE | G1: DR_AMT | H1: CR AMT | I1: TRXDATE | J1: DIST REFERENCE | K1: GPACCT
A2: LCREE | B2: =Checklist!$B$1 -> 202511 | C2: GJ | D2: =Checklist!$B$9 -> DC1110251 | E2: =D2 -> DC1110251 | F2: =Checklist!$A$10 -> 45971 | G2: 19213.38 | H2: 0 | I2: =$F$2 -> 45971 | J2: Excess Funds - DGEFF | K2: LCREE-1043-0000-000-
A3: LCREE | B3: =Checklist!$B$1 -> 202511 | C3: GJ | D3: =D2 -> DC1110251 | E3: =D3 -> DC1110251 | F3: =$F$2 -> 45971 | G3: 0 | H3: 19213.38 | I3: =$F$2 -> 45971 | J3: Excess Funds - DGEFF | K3: LCREE-1470-0000-000-DGEFF
A4: LCF | B4: =Checklist!$B$1 -> 202511 | C4: GJ | D4: DC1110252 | E4: =D4 -> DC1110252 | F4: =$F$2 -> 45971 | G4: 585496.6 | H4: 0 | I4: =$F$2 -> 45971 | J4: Payroll Transfer | K4: LCF -1006-0000-000-
A5: LCF | B5: =Checklist!$B$1 -> 202511 | C5: GJ | D5: =D4 -> DC1110252 | E5: =D5 -> DC1110252 | F5: =$F$2 -> 45971 | G5: 0 | H5: 585496.6 | I5: =$F$2 -> 45971 | J5: Payroll Transfer | K5: LCF -1065-0001-000-
A6: LCREP | B6: =Checklist!$B$1 -> 202511 | C6: GJ | D6: DC1110253 | E6: =D6 -> DC1110253 | F6: =$F$2 -> 45971 | G6: 2000000 | H6: 0 | I6: =$F$2 -> 45971 | J6: Dividend Payment | K6: LCREP-1065-0011-000-
A7: LCREP | B7: =Checklist!$B$1 -> 202511 | C7: GJ | D7: =D6 -> DC1110253 | E7: =D7 -> DC1110253 | F7: =$F$2 -> 45971 | G7: 0 | H7: =G6 -> 2000000 | I7: =$F$2 -> 45971 | J7: Dividend Payment | K7: LCREP-1470-0000-000-LCREF
A8: LCREF | B8: =Checklist!$B$1 -> 202511 | C8: GJ | D8: =D7 -> DC1110253 | E8: =D8 -> DC1110253 | F8: =$F$2 -> 45971 | G8: 0 | H8: =G6 -> 2000000 | I8: =$F$2 -> 45971 | J8: Dividend Payment | K8: LCREF-1065-0008-000-
A9: LCREF | B9: =Checklist!$B$1 -> 202511 | C9: GJ | D9: =D8 -> DC1110253 | E9: =D9 -> DC1110253 | F9: =$F$2 -> 45971 | G9: =G6 -> 2000000 | H9: 0 | I9: =$F$2 -> 45971 | J9: Dividend Payment | K9: LCREF-3670-0000-000-LCREP
A10: LCFHR | B10: =Checklist!$B$1 -> 202511 | C10: GJ | D10: =D9 -> DC1110253 | E10: =D10 -> DC1110253 | F10: =$F$2 -> 45971 | G10: 1980000 | H10: 0 | I10: =$F$2 -> 45971 | J10: Partnership Distribution | K10: LCFHR-1065-0002-000-
A11: LCFHR | B11: =Checklist!$B$1 -> 202511 | C11: GJ | D11: =D10 -> DC1110253 | E11: =D11 -> DC1110253 | F11: =$F$2 -> 45971 | G11: 0 | H11: =G10 -> 1980000 | I11: =$F$2 -> 45971 | J11: Partnership Distribution | K11: MID2R-1470-0000-000-LCREP
A12: LCREP | B12: =Checklist!$B$1 -> 202511 | C12: GJ | D12: =D11 -> DC1110253 | E12: =D12 -> DC1110253 | F12: =$F$2 -> 45971 | G12: 0 | H12: =G10 -> 1980000 | I12: =$F$2 -> 45971 | J12: Partnership Distribution | K12: LCREP-1065-0011-000-
A13: LCREP | B13: =Checklist!$B$1 -> 202511 | C13: GJ | D13: =D12 -> DC1110253 | E13: =D13 -> DC1110253 | F13: =$F$2 -> 45971 | G13: =G10 -> 1980000 | H13: 0 | I13: =$F$2 -> 45971 | J13: Partnership Distribution | K13: LCREP-3670-0000-000-MID2R
A14: LCF | B14: =Checklist!$B$1 -> 202511 | C14: GJ | D14: =D13 -> DC1110253 | E14: =D14 -> DC1110253 | F14: =$F$2 -> 45971 | G14: 20000 | H14: 0 | I14: =$F$2 -> 45971 | J14: Partnership Distribution | K14: LCF -1065-0001-000-
A15: LCF | B15: =Checklist!$B$1 -> 202511 | C15: GJ | D15: =D14 -> DC1110253 | E15: =D15 -> DC1110253 | F15: =$F$2 -> 45971 | G15: 0 | H15: =G14 -> 20000 | I15: =$F$2 -> 45971 | J15: Partnership Distribution | K15: LMID2-1470-0000-000-LCREP
A16: LCREP | B16: =Checklist!$B$1 -> 202511 | C16: GJ | D16: =D15 -> DC1110253 | E16: =D16 -> DC1110253 | F16: =$F$2 -> 45971 | G16: 0 | H16: =G14 -> 20000 | I16: =$F$2 -> 45971 | J16: Partnership Distribution | K16: LCREP-1065-0011-000-
A17: LCREP | B17: =Checklist!$B$1 -> 202511 | C17: GJ | D17: =D16 -> DC1110253 | E17: =D17 -> DC1110253 | F17: =$F$2 -> 45971 | G17: =G14 -> 20000 | H17: 0 | I17: =$F$2 -> 45971 | J17: Partnership Distribution | K17: LCREP-3670-0000-000-LMID2
A18: LCREP | B18: =Checklist!$B$1 -> 202511 | C18: GJ | D18: DC1110254 | E18: =D18 -> DC1110254 | F18: =$F$2 -> 45971 | G18: 3700000 | H18: 0 | I18: =$F$2 -> 45971 | J18: Dividend Payment | K18: LCREP-1065-0011-000-
A19: LCREP | B19: =Checklist!$B$1 -> 202511 | C19: GJ | D19: =D18 -> DC1110254 | E19: =D19 -> DC1110254 | F19: =$F$2 -> 45971 | G19: 0 | H19: =G18 -> 3700000 | I19: =$F$2 -> 45971 | J19: Dividend Payment | K19: LCREP-1470-0000-000-LCREF
A20: LCREF | B20: =Checklist!$B$1 -> 202511 | C20: GJ | D20: =D19 -> DC1110254 | E20: =D20 -> DC1110254 | F20: =$F$2 -> 45971 | G20: 0 | H20: =G18 -> 3700000 | I20: =$F$2 -> 45971 | J20: Dividend Payment | K20: LCREF-1065-0008-000-
A21: LCREF | B21: =Checklist!$B$1 -> 202511 | C21: GJ | D21: =D20 -> DC1110254 | E21: =D21 -> DC1110254 | F21: =$F$2 -> 45971 | G21: =G18 -> 3700000 | H21: 0 | I21: =$F$2 -> 45971 | J21: Dividend Payment | K21: LCREF-3670-0000-000-LCREP
A22: LCFHR | B22: =Checklist!$B$1 -> 202511 | C22: GJ | D22: =D21 -> DC1110254 | E22: =D22 -> DC1110254 | F22: =$F$2 -> 45971 | G22: 3663000 | H22: 0 | I22: =$F$2 -> 45971 | J22: Partnership Distribution | K22: LCFHR-1065-0002-000-
A23: LCFHR | B23: =Checklist!$B$1 -> 202511 | C23: GJ | D23: =D22 -> DC1110254 | E23: =D23 -> DC1110254 | F23: =$F$2 -> 45971 | G23: 0 | H23: =G22 -> 3663000 | I23: =$F$2 -> 45971 | J23: Partnership Distribution | K23: MID2R-1470-0000-000-LCREP
A24: LCREP | B24: =Checklist!$B$1 -> 202511 | C24: GJ | D24: =D23 -> DC1110254 | E24: =D24 -> DC1110254 | F24: =$F$2 -> 45971 | G24: 0 | H24: =G22 -> 3663000 | I24: =$F$2 -> 45971 | J24: Partnership Distribution | K24: LCREP-1065-0011-000-
A25: LCREP | B25: =Checklist!$B$1 -> 202511 | C25: GJ | D25: =D24 -> DC1110254 | E25: =D25 -> DC1110254 | F25: =$F$2 -> 45971 | G25: =G22 -> 3663000 | H25: 0 | I25: =$F$2 -> 45971 | J25: Partnership Distribution | K25: LCREP-3670-0000-000-MID2R
A26: LCF | B26: =Checklist!$B$1 -> 202511 | C26: GJ | D26: =D25 -> DC1110254 | E26: =D26 -> DC1110254 | F26: =$F$2 -> 45971 | G26: 37000 | H26: 0 | I26: =$F$2 -> 45971 | J26: Partnership Distribution | K26: LCF -1065-0001-000-
A27: LCF | B27: =Checklist!$B$1 -> 202511 | C27: GJ | D27: =D26 -> DC1110254 | E27: =D27 -> DC1110254 | F27: =$F$2 -> 45971 | G27: 0 | H27: =G26 -> 37000 | I27: =$F$2 -> 45971 | J27: Partnership Distribution | K27: LMID2-1470-0000-000-LCREP
A28: LCREP | B28: =Checklist!$B$1 -> 202511 | C28: GJ | D28: =D27 -> DC1110254 | E28: =D28 -> DC1110254 | F28: =$F$2 -> 45971 | G28: 0 | H28: =G26 -> 37000 | I28: =$F$2 -> 45971 | J28: Partnership Distribution | K28: LCREP-1065-0011-000-
A29: LCREP | B29: =Checklist!$B$1 -> 202511 | C29: GJ | D29: =D28 -> DC1110254 | E29: =D29 -> DC1110254 | F29: =$F$2 -> 45971 | G29: =G26 -> 37000 | H29: 0 | I29: =$F$2 -> 45971 | J29: Partnership Distribution | K29: LCREP-3670-0000-000-LMID2
A30: LCREE | B30: =Checklist!$B$1 -> 202511 | C30: GJ | D30: DC1110255 | E30: =D30 -> DC1110255 | F30: =$F$2 -> 45971 | G30: 822429.43 | H30: 0 | I30: =$F$2 -> 45971 | J30: Rental Income & Tax Reimbursement | K30: LCREE-1065-0008-000-
A31: LCREE | B31: =Checklist!$B$1 -> 202511 | C31: GJ | D31: =D30 -> DC1110255 | E31: =D31 -> DC1110255 | F31: =$F$2 -> 45971 | G31: 0 | H31: 7777.65 | I31: =$F$2 -> 45971 | J31: Rental Income - DGMGR | K31: LCREE-1470-0000-000-DGMGR
A32: LCREE | B32: =Checklist!$B$1 -> 202511 | C32: GJ | D32: =D31 -> DC1110255 | E32: =D32 -> DC1110255 | F32: =$F$2 -> 45971 | G32: 0 | H32: 8736.89 | I32: =$F$2 -> 45971 | J32: Rental Income - DGCHI | K32: LCREE-1470-0000-000-DGCHI
A33: LCREE | B33: =Checklist!$B$1 -> 202511 | C33: GJ | D33: =D32 -> DC1110255 | E33: =D33 -> DC1110255 | F33: =$F$2 -> 45971 | G33: 0 | H33: 6838.27 | I33: =$F$2 -> 45971 | J33: Rental Income - DGSHE | K33: LCREE-1470-0000-000-DGSHE
A34: LCREE | B34: =Checklist!$B$1 -> 202511 | C34: GJ | D34: =D33 -> DC1110255 | E34: =D34 -> DC1110255 | F34: =$F$2 -> 45971 | G34: 0 | H34: 9047.01 | I34: =$F$2 -> 45971 | J34: Rental Income - DGSUL | K34: LCREE-1470-0000-000-DGSUL
A35: LCREE | B35: =Checklist!$B$1 -> 202511 | C35: GJ | D35: =D34 -> DC1110255 | E35: =D35 -> DC1110255 | F35: =$F$2 -> 45971 | G35: 0 | H35: 8024.52 | I35: =$F$2 -> 45971 | J35: Rental Income - DGDIM | K35: LCREE-1470-0000-000-DGDIM
A36: LCREE | B36: =Checklist!$B$1 -> 202511 | C36: GJ | D36: =D35 -> DC1110255 | E36: =D36 -> DC1110255 | F36: =$F$2 -> 45971 | G36: 0 | H36: 7783.95 | I36: =$F$2 -> 45971 | J36: Rental Income - DGPLE | K36: LCREE-1470-0000-000-DGPLE
A37: LCREE | B37: =Checklist!$B$1 -> 202511 | C37: GJ | D37: =D36 -> DC1110255 | E37: =D37 -> DC1110255 | F37: =$F$2 -> 45971 | G37: 0 | H37: 7958.33 | I37: =$F$2 -> 45971 | J37: Rental Income - DGSPR | K37: LCREE-1470-0000-000-DGSPR
A38: LCREE | B38: =Checklist!$B$1 -> 202511 | C38: GJ | D38: =D37 -> DC1110255 | E38: =D38 -> DC1110255 | F38: =$F$2 -> 45971 | G38: 0 | H38: 7008.29 | I38: =$F$2 -> 45971 | J38: Rental Income - DGRED | K38: LCREE-1470-0000-000-DGRED
A39: LCREE | B39: =Checklist!$B$1 -> 202511 | C39: GJ | D39: =D38 -> DC1110255 | E39: =D39 -> DC1110255 | F39: =$F$2 -> 45971 | G39: 0 | H39: 7961.57 | I39: =$F$2 -> 45971 | J39: Rental Income - DGHAM | K39: LCREE-1470-0000-000-DGHAM
A40: LCREE | B40: =Checklist!$B$1 -> 202511 | C40: GJ | D40: =D39 -> DC1110255 | E40: =D40 -> DC1110255 | F40: =$F$2 -> 45971 | G40: 0 | H40: 8222.42 | I40: =$F$2 -> 45971 | J40: Rental Income - DGCLI | K40: LCREE-1470-0000-000-DGCLI
A41: LCREE | B41: =Checklist!$B$1 -> 202511 | C41: GJ | D41: =D40 -> DC1110255 | E41: =D41 -> DC1110255 | F41: =$F$2 -> 45971 | G41: 0 | H41: 8305.87 | I41: =$F$2 -> 45971 | J41: Rental Income - DGPER | K41: LCREE-1470-0000-000-DGPER
A42: LCREE | B42: =Checklist!$B$1 -> 202511 | C42: GJ | D42: =D41 -> DC1110255 | E42: =D42 -> DC1110255 | F42: =$F$2 -> 45971 | G42: 0 | H42: 7150.61 | I42: =$F$2 -> 45971 | J42: Rental Income - DGLAM | K42: LCREE-1470-0000-000-DGLAM
... A138: LCREE | B138: =Checklist!$B$1 -> 202511 | C138: GJ | D138: =D137 -> DC1110255 | E138: =D138 -> DC1110255 | F138: =$F$2 -> 45971 | G138: 0 | H138: 7562.65 | I138: =$F$2 -> 45971 | J138: Rental Income - DGNEW | K138: LCREE-1470-0000-000-DGNEW
A139: LCREE | B139: =Checklist!$B$1 -> 202511 | C139: GJ | D139: =D138 -> DC1110255 | E139: =D139 -> DC1110255 | F139: =$F$2 -> 45971 | G139: 0 | H139: 6499.3 | I139: =$F$2 -> 45971 | J139: Rental Income - DGBAT | K139: LCREE-1470-0000-000-DGBAT | L139: June-25 rent
A140: DGPIN | B140: =Checklist!$B$1 -> 202511 | C140: GJ | D140: =D139 -> DC1110255 | E140: =D140 -> DC1110255 | F140: =$F$2 -> 45971 | G140: 17899 | H140: 0 | I140: =$F$2 -> 45971 | J140: Tax Reimbursement - DGPIN | K140: DGPIN-1900-0000-000-LCREE
A141: DGPAY | B141: =Checklist!$B$1 -> 202511 | C141: GJ | D141: =D140 -> DC1110255 | E141: =D141 -> DC1110255 | F141: =$F$2 -> 45971 | G141: 8807 | H141: 0 | I141: =$F$2 -> 45971 | J141: Tax Reimbursement - DGPAY | K141: DGPAY-1900-0000-000-LCREE
A142: DGISL | B142: =Checklist!$B$1 -> 202511 | C142: GJ | D142: =D141 -> DC1110255 | E142: =D142 -> DC1110255 | F142: =$F$2 -> 45971 | G142: 10672 | H142: 0 | I142: =$F$2 -> 45971 | J142: Tax Reimbursement - DGISL | K142: DGISL-1900-0000-000-LCREE
A143: DGBAT | B143: =Checklist!$B$1 -> 202511 | C143: GJ | D143: =D142 -> DC1110255 | E143: =D143 -> DC1110255 | F143: =$F$2 -> 45971 | G143: 6894 | H143: 0 | I143: =$F$2 -> 45971 | J143: Tax Reimbursement - DGBAT | K143: DGBAT-1900-0000-000-LCREE
A144: DGWAR | B144: =Checklist!$B$1 -> 202511 | C144: GJ | D144: =D143 -> DC1110255 | E144: =D144 -> DC1110255 | F144: =$F$2 -> 45971 | G144: 8484 | H144: 0 | I144: =$F$2 -> 45971 | J144: Tax Reimbursement - DGWAR | K144: DGWAR-1900-0000-000-LCREE
A145: DGSTF | B145: =Checklist!$B$1 -> 202511 | C145: GJ | D145: =D144 -> DC1110255 | E145: =D145 -> DC1110255 | F145: =$F$2 -> 45971 | G145: 18585.56 | H145: 0 | I145: =$F$2 -> 45971 | J145: Tax Reimbursement - DGSTF | K145: DGSTF-1900-0000-000-LCREE
A146: LCREE | B146: =Checklist!$B$1 -> 202511 | C146: GJ | D146: =D145 -> DC1110255 | E146: =D146 -> DC1110255 | F146: =$F$2 -> 45971 | G146: 0 | H146: 17899 | I146: =$F$2 -> 45971 | J146: Tax Reimbursement - DGPIN | K146: LCREE-1900-0000-000-DGPIN
A147: LCREE | B147: =Checklist!$B$1 -> 202511 | C147: GJ | D147: =D146 -> DC1110255 | E147: =D147 -> DC1110255 | F147: =$F$2 -> 45971 | G147: 0 | H147: 8807 | I147: =$F$2 -> 45971 | J147: Tax Reimbursement - DGPAY | K147: LCREE-1900-0000-000-DGPAY
A148: LCREE | B148: =Checklist!$B$1 -> 202511 | C148: GJ | D148: =D147 -> DC1110255 | E148: =D148 -> DC1110255 | F148: =$F$2 -> 45971 | G148: 0 | H148: 10672 | I148: =$F$2 -> 45971 | J148: Tax Reimbursement - DGISL | K148: LCREE-1900-0000-000-DGISL
A149: LCREE | B149: =Checklist!$B$1 -> 202511 | C149: GJ | D149: =D148 -> DC1110255 | E149: =D149 -> DC1110255 | F149: =$F$2 -> 45971 | G149: 0 | H149: 6894 | I149: =$F$2 -> 45971 | J149: Tax Reimbursement - DGBAT | K149: LCREE-1900-0000-000-DGBAT
A150: LCREE | B150: =Checklist!$B$1 -> 202511 | C150: GJ | D150: =D149 -> DC1110255 | E150: =D150 -> DC1110255 | F150: =$F$2 -> 45971 | G150: 0 | H150: 8484 | I150: =$F$2 -> 45971 | J150: Tax Reimbursement - DGWAR | K150: LCREE-1900-0000-000-DGWAR
A151: LCREE | B151: =Checklist!$B$1 -> 202511 | C151: GJ | D151: =D150 -> DC1110255 | E151: =D151 -> DC1110255 | F151: =$F$2 -> 45971 | G151: 0 | H151: 18585.56 | I151: =$F$2 -> 45971 | J151: Tax Reimbursement - DGSTF | K151: LCREE-1900-0000-000-DGSTF
A152: LCREE | B152: =Checklist!$B$1 -> 202511 | C152: GJ | D152: =D151 -> DC1110255 | E152: =D152 -> DC1110255 | F152: =$F$2 -> 45971 | I152: =$F$2 -> 45971
A153: LCREE | B153: =Checklist!$B$1 -> 202511 | C153: GJ | D153: =D152 -> DC1110255 | E153: =D153 -> DC1110255 | F153: =$F$2 -> 45971 | I153: =$F$2 -> 45971
A154: LCREE | B154: =Checklist!$B$1 -> 202511 | C154: GJ | D154: =D153 -> DC1110255 | E154: =D154 -> DC1110255 | F154: =$F$2 -> 45971 | I154: =$F$2 -> 45971
A155: LCREE | B155: =Checklist!$B$1 -> 202511 | C155: GJ | D155: =D154 -> DC1110255 | E155: =D155 -> DC1110255 | F155: =$F$2 -> 45971 | I155: =$F$2 -> 45971
A156: LCREE | B156: =Checklist!$B$1 -> 202511 | C156: GJ | D156: =D155 -> DC1110255 | E156: =D156 -> DC1110255 | F156: =$F$2 -> 45971 | I156: =$F$2 -> 45971
A157: LCREE | B157: =Checklist!$B$1 -> 202511 | C157: GJ | D157: =D156 -> DC1110255 | E157: =D157 -> DC1110255 | F157: =$F$2 -> 45971 | I157: =$F$2 -> 45971
A158: LCREE | B158: =Checklist!$B$1 -> 202511 | C158: GJ | D158: =D157 -> DC1110255 | E158: =D158 -> DC1110255 | F158: =$F$2 -> 45971 | I158: =$F$2 -> 45971
A159: LCREE | B159: =Checklist!$B$1 -> 202511 | C159: GJ | D159: =D158 -> DC1110255 | E159: =D159 -> DC1110255 | F159: =$F$2 -> 45971 | I159: =$F$2 -> 45971
A160: LCREE | B160: =Checklist!$B$1 -> 202511 | C160: GJ | D160: =D159 -> DC1110255 | E160: =D160 -> DC1110255 | F160: =$F$2 -> 45971 | I160: =$F$2 -> 45971
A161: LCREE | B161: =Checklist!$B$1 -> 202511 | C161: GJ | D161: =D160 -> DC1110255 | E161: =D161 -> DC1110255 | F161: =$F$2 -> 45971 | I161: =$F$2 -> 45971
A162: LCREE | B162: =Checklist!$B$1 -> 202511 | C162: GJ | D162: =D161 -> DC1110255 | E162: =D162 -> DC1110255 | F162: =$F$2 -> 45971 | I162: =$F$2 -> 45971
A163: LCREE | B163: =Checklist!$B$1 -> 202511 | C163: GJ | D163: =D162 -> DC1110255 | E163: =D163 -> DC1110255 | F163: =$F$2 -> 45971 | I163: =$F$2 -> 45971
... A166: LCREE | B166: =Checklist!$B$1 -> 202511 | C166: GJ | D166: =D165 -> DC1110255 | E166: =D166 -> DC1110255 | F166: =$F$2 -> 45971 | I166: =$F$2 -> 45971

Sheet Cash Activity 11-12
A1: ="Daily Bank Activity - "&MONTH(Checklist!A11)&"/"&DAY(Checklist!A11)&"/"&YEAR(Checklist!A11) -> Daily Bank Activity - 11/12/2025
A2: Credit (+) / Debit (-)
B4: # | C4: Bank | D4: Acct Name | E4: Acct # | F4: Date | G4: Type | H4: Amount | I4: Bank Ref | J4: Bank Stmt Description | K4: Trans Type | L4: Entity | M4: AIT | N4: Short Description | O4: GL Account 1 | P4: GL Account 2 | Q4: Posted?
B5: 1 | C5: PNC | D5: LCFH REIT | E5: 8026459924 | F5: 45973 | G5: CR | H5: 2429.95 | I5: '00000000000 | J5: PNC SWEEP INTEREST @ 0.000000 EFFECTIVE DATE 11-10 | K5: =IF(ISNUMBER(SEARCH("Manual Payment - ",N5,1)),"AP",IF(ISNUMBER(SEARCH("Payment - Concur",N5,1)),"WDL",IF(ISNUMBER(SEARCH("Payroll Transfer",N5,1)),"XFR",IF(ISNUMBER(SEARCH("XFR",N5,1)),"XFR",IF(H5>0,"RCT","WDL"))))) -> RCT | L5: =VLOOKUP(D5,'Entity Code'!A:B,2,0) -> LCFHR | N5: Overnight interest sweep PNC LCFHR account. No entry required | O5: N/A | P5: N/A | Q5: N/A
B6: 2 | C6: PNC | D6: LCFH REIT | E6: 8026459924 | F6: 45973 | G6: CR | H6: 14078264 | I6: '00000000000 | J6: SWEEP TRANSFR FROM INVESTMENT ACCT 8026459924 | K6: =IF(ISNUMBER(SEARCH("Manual Payment - ",N6,1)),"AP",IF(ISNUMBER(SEARCH("Payment - Concur",N6,1)),"WDL",IF(ISNUMBER(SEARCH("Payroll Transfer",N6,1)),"XFR",IF(ISNUMBER(SEARCH("XFR",N6,1)),"XFR",IF(H6>0,"RCT","WDL"))))) -> RCT | L6: =VLOOKUP(D6,'Entity Code'!A:B,2,0) -> LCFHR | N6: Overnight interest sweep PNC LCFHR account. No entry required | O6: N/A | P6: N/A | Q6: N/A
B7: 3 | C7: PNC | D7: LCFH REIT | E7: 8026459924 | F7: 45973 | G7: DR | H7: -14480162 | I7: '00000000000 | J7: SWEEP TO INVESTMENT ACCT# 8026459924 | K7: =IF(ISNUMBER(SEARCH("Manual Payment - ",N7,1)),"AP",IF(ISNUMBER(SEARCH("Payment - Concur",N7,1)),"WDL",IF(ISNUMBER(SEARCH("Payroll Transfer",N7,1)),"XFR",IF(ISNUMBER(SEARCH("XFR",N7,1)),"XFR",IF(H7>0,"RCT","WDL"))))) -> WDL | L7: =VLOOKUP(D7,'Entity Code'!A:B,2,0) -> LCFHR | N7: Overnight interest sweep PNC LCFHR account. No entry required | O7: N/A | P7: N/A | Q7: N/A
B8: 4 | C8: PNC | D8: LCF Payroll | E8: 8147891123 | F8: 45973 | G8: DR | H8: -585496.6 | I8: '25BC20618C4Z848P | J8: WIRE TRANSFER ISO STTLMT DATE:11122025 CLR SYS REF | K8: =IF(ISNUMBER(SEARCH("Manual Payment - ",N8,1)),"AP",IF(ISNUMBER(SEARCH("Payment - Concur",N8,1)),"WDL",IF(ISNUMBER(SEARCH("Payroll Transfer",N8,1)),"XFR",IF(ISNUMBER(SEARCH("XFR",N8,1)),"XFR",IF(H8>0,"RCT","WDL"))))) -> WDL | L8: =VLOOKUP(D8,'Entity Code'!A:B,2,0) -> LCF | N8: Payroll - Trinet | O8: LCF -1745-0000-000- | P8: N/A | Q8: Ladder to post
B9: 5 | C9: PNC | D9: LCREF | E9: 8026497285 | F9: 45973 | G9: DR | H9: -437030 | I9: 'PABCE51208HJ2VJ6 | J9: WIRE TRANSFER ISO AMT:USD 437030.00 STTLMT DATE:11 | K9: =IF(ISNUMBER(SEARCH("Manual Payment - ",N9,1)),"AP",IF(ISNUMBER(SEARCH("Payment - Concur",N9,1)),"WDL",IF(ISNUMBER(SEARCH("Payroll Transfer",N9,1)),"XFR",IF(ISNUMBER(SEARCH("XFR",N9,1)),"XFR",IF(H9>0,"RCT","WDL"))))) -> WDL | L9: =VLOOKUP(D9,'Entity Code'!A:B,2,0) -> LCREF | N9: Clark Tower - Future Advance #8 | O9: 2701-LMS0-000 | P9: N/A | Q9: SS&C to post
B10: 6 | C10: PNC | D10: LCC | E10: 8026482868 | F10: 45973 | G10: DR | H10: -81770.7 | I10: 'PABCC05308IH2TQ2 | J10: WIRE TRANSFER ISO AMT:USD 81770.70 STTLMT DATE:111 | K10: =IF(ISNUMBER(SEARCH("Manual Payment - ",N10,1)),"AP",IF(ISNUMBER(SEARCH("Payment - Concur",N10,1)),"WDL",IF(ISNUMBER(SEARCH("Payroll Transfer",N10,1)),"XFR",IF(ISNUMBER(SEARCH("XFR",N10,1)),"XFR",IF(H10>0,"RCT","WDL"))))) -> WDL | L10: =VLOOKUP(D10,'Entity Code'!A:B,2,0) -> LCC | N10: Stock Repurchase | O10: LCC -3595-0000-000- | P10: N/A | Q10: SS&C to post
B11: 7 | C11: JPM | D11: LC TRS I LLC | E11: 657597907 | F11: 45973 | G11: Debit | H11: -400 | I11: 8472000316JO | J11: FEDWIRE DEBIT | K11: =IF(ISNUMBER(SEARCH("Manual Payment - ",N11,1)),"AP",IF(ISNUMBER(SEARCH("Payment - Concur",N11,1)),"WDL",IF(ISNUMBER(SEARCH("Payroll Transfer",N11,1)),"XFR",IF(ISNUMBER(SEARCH("XFR",N11,1)),"XFR",IF(H11>0,"RCT","WDL"))))) -> WDL | L11: =VLOOKUP(D11,'Entity Code'!A:B,2,0) -> LTRS1 | N11: FINRA Account Transfer | O11: 2701-CAMR-000 | P11: N/A | Q11: SS&C to post
B12: 8 | C12: PNC | D12: LCFH REIT | E12: 8026459924 | F12: 45973 | G12: CR | H12: 145.17 | I12: '25BCJ3001MZ0027N | J12: WIRE TRANSFER ISO STTLMT DATE:11122025 CLR SYS REF | K12: =IF(ISNUMBER(SEARCH("Manual Payment - ",N12,1)),"AP",IF(ISNUMBER(SEARCH("Payment - Concur",N12,1)),"WDL",IF(ISNUMBER(SEARCH("Payroll Transfer",N12,1)),"XFR",IF(ISNUMBER(SEARCH("XFR",N12,1)),"XFR",IF(H12>0,"RCT","WDL"))))) -> RCT | L12: =VLOOKUP(D12,'Entity Code'!A:B,2,0) -> LCFHR | N12: BMO Securities Repo Margin Interest | O12: 2701-CAMR-000 | P12: N/A | Q12: SS&C to post
B13: 9 | C13: PNC | D13: LCFH REIT | E13: 8026459924 | F13: 45973 | G13: CR | H13: 1703.01 | I13: '25BCH5356JA15FTE | J13: WIRE TRANSFER ISO AMT:USD 1703.01 STTLMT DATE:1112 | K13: =IF(ISNUMBER(SEARCH("Manual Payment - ",N13,1)),"AP",IF(ISNUMBER(SEARCH("Payment - Concur",N13,1)),"WDL",IF(ISNUMBER(SEARCH("Payroll Transfer",N13,1)),"XFR",IF(ISNUMBER(SEARCH("XFR",N13,1)),"XFR",IF(H13>0,"RCT","WDL"))))) -> RCT | L13: =VLOOKUP(D13,'Entity Code'!A:B,2,0) -> LCFHR | N13: WF Securities Repo Margin Interest | O13: 2701-CAMR-000 | P13: N/A | Q13: SS&C to post
B14: 10 | C14: PNC | D14: LCF Borrower Deposits | E14: 8026478877 | F14: 45973 | G14: CR | H14: 15000 | I14: '25BCL10525V16NGD | J14: WIRE TRANSFER ISO AMT:USD 15000.00 STTLMT DATE:111 | K14: =IF(ISNUMBER(SEARCH("Manual Payment - ",N14,1)),"AP",IF(ISNUMBER(SEARCH("Payment - Concur",N14,1)),"WDL",IF(ISNUMBER(SEARCH("Payroll Transfer",N14,1)),"XFR",IF(ISNUMBER(SEARCH("XFR",N14,1)),"XFR",IF(H14>0,"RCT","WDL"))))) -> RCT | L14: =VLOOKUP(D14,'Entity Code'!A:B,2,0) -> LCF | N14: Loan Deposit - Gainesville Portfolio (6 separate loans) | O14: 2701-LMS0-000 | P14: N/A | Q14: SS&C to post
B15: 11 | C15: PNC | D15: LCF Borrower Deposits | E15: 8026478877 | F15: 45973 | G15: CR | H15: 285000 | I15: '25BCL5633OP01FD1 | J15: WIRE TRANSFER ISO AMT:USD 285000.00 STTLMT DATE:11 | K15: =IF(ISNUMBER(SEARCH("Manual Payment - ",N15,1)),"AP",IF(ISNUMBER(SEARCH("Payment - Concur",N15,1)),"WDL",IF(ISNUMBER(SEARCH("Payroll Transfer",N15,1)),"XFR",IF(ISNUMBER(SEARCH("XFR",N15,1)),"XFR",IF(H15>0,"RCT","WDL"))))) -> RCT | L15: =VLOOKUP(D15,'Entity Code'!A:B,2,0) -> LCF | N15: Loan Deposit - Gainesville Portfolio (6 separate loans) | O15: 2701-LMS0-000 | P15: N/A | Q15: SS&C to post
B16: 12 | C16: PNC | D16: LCI | E16: 8026496012 | F16: 45973 | G16: CR | H16: 700000 | I16: '25BCH0530P2Z15XT | J16: BOOK TRANSFER CREDIT 0015XT ORIGINATOR:LADDER CAPI | K16: =IF(ISNUMBER(SEARCH("Manual Payment - ",N16,1)),"AP",IF(ISNUMBER(SEARCH("Payment - Concur",N16,1)),"WDL",IF(ISNUMBER(SEARCH("Payroll Transfer",N16,1)),"XFR",IF(ISNUMBER(SEARCH("XFR",N16,1)),"XFR",IF(H16>0,"RCT","WDL"))))) -> XFR | L16: =VLOOKUP(D16,'Entity Code'!A:B,2,0) -> LCI | N16: XFR from LCFHR PNC to LCI PNC | O16: 2701-CAMR-000 | P16: N/A | Q16: SS&C to post
B17: 12 | C17: PNC | D17: LCFH REIT | E17: 8026459924 | F17: 45973 | G17: DR | H17: -700000 | I17: '25BCH0530P2Z15XT | J17: BOOK TRANSFER DEBIT 0015XT ORIGINATOR:LADDER CAPIT | K17: =IF(ISNUMBER(SEARCH("Manual Payment - ",N17,1)),"AP",IF(ISNUMBER(SEARCH("Payment - Concur",N17,1)),"WDL",IF(ISNUMBER(SEARCH("Payroll Transfer",N17,1)),"XFR",IF(ISNUMBER(SEARCH("XFR",N17,1)),"XFR",IF(H17>0,"RCT","WDL"))))) -> XFR | L17: =VLOOKUP(D17,'Entity Code'!A:B,2,0) -> LCFHR | N17: XFR from LCFHR PNC to LCI PNC | O17: 2701-CAMR-000 | P17: N/A | Q17: SS&C to post
B18: 13 | C18: PNC | D18: LCI | E18: 8026496012 | F18: 45973 | G18: DR | H18: -700000 | I18: 'PABCC053049I4G09 | J18: WIRE TRANSFER ISO AMT:USD 700000.00 STTLMT DATE:11 | K18: =IF(ISNUMBER(SEARCH("Manual Payment - ",N18,1)),"AP",IF(ISNUMBER(SEARCH("Payment - Concur",N18,1)),"WDL",IF(ISNUMBER(SEARCH("Payroll Transfer",N18,1)),"XFR",IF(ISNUMBER(SEARCH("XFR",N18,1)),"XFR",IF(H18>0,"RCT","WDL"))))) -> XFR | L18: =VLOOKUP(D18,'Entity Code'!A:B,2,0) -> LCI | N18: XFR from LCI PNC to LCFP | O18: 2701-CAMR-000 | P18: N/A | Q18: SS&C to post
B19: 14 | C19: PNC | D19: LCC | E19: 8026482868 | F19: 45973 | G19: CR | H19: 81780 | I19: '25BCH05311VZ1GY0 | J19: BOOK TRANSFER CREDIT 001GY0 ORIGINATOR:LADDER CAPI | K19: =IF(ISNUMBER(SEARCH("Manual Payment - ",N19,1)),"AP",IF(ISNUMBER(SEARCH("Payment - Concur",N19,1)),"WDL",IF(ISNUMBER(SEARCH("Payroll Transfer",N19,1)),"XFR",IF(ISNUMBER(SEARCH("XFR",N19,1)),"XFR",IF(H19>0,"RCT","WDL"))))) -> XFR | L19: =VLOOKUP(D19,'Entity Code'!A:B,2,0) -> LCC | N19: XFR from LCFHR PNC to LCC | O19: 2701-CAMR-000 | P19: N/A | Q19: SS&C to post
B20: 14 | C20: PNC | D20: LCFH REIT | E20: 8026459924 | F20: 45973 | G20: DR | H20: -81780 | I20: '25BCH05311VZ1GY0 | J20: BOOK TRANSFER DEBIT 001GY0 ORIGINATOR:LADDER CAPIT | K20: =IF(ISNUMBER(SEARCH("Manual Payment - ",N20,1)),"AP",IF(ISNUMBER(SEARCH("Payment - Concur",N20,1)),"WDL",IF(ISNUMBER(SEARCH("Payroll Transfer",N20,1)),"XFR",IF(ISNUMBER(SEARCH("XFR",N20,1)),"XFR",IF(H20>0,"RCT","WDL"))))) -> XFR | L20: =VLOOKUP(D20,'Entity Code'!A:B,2,0) -> LCFHR | N20: XFR from LCFHR PNC to LCC | O20: 2701-CAMR-000 | P20: N/A | Q20: SS&C to post
B21: 15 | C21: PNC | D21: LCFH REIT | E21: 8026459924 | F21: 45973 | G21: DR | H21: -150000 | I21: 'PABCE3337J1H22EC | J21: WIRE TRANSFER ISO AMT:USD 150000.00 STTLMT DATE:11 | K21: =IF(ISNUMBER(SEARCH("Manual Payment - ",N21,1)),"AP",IF(ISNUMBER(SEARCH("Payment - Concur",N21,1)),"WDL",IF(ISNUMBER(SEARCH("Payroll Transfer",N21,1)),"XFR",IF(ISNUMBER(SEARCH("XFR",N21,1)),"XFR",IF(H21>0,"RCT","WDL"))))) -> XFR | L21: =VLOOKUP(D21,'Entity Code'!A:B,2,0) -> LCFHR | N21: XFR from LCFHR PNC to LCFP3 | O21: 2701-CAMR-000 | P21: N/A | Q21: SS&C to post
B22: 16 | C22: PNC | D22: LCR 3 | E22: 8026496047 | F22: 45973 | G22: CR | H22: 946255.03 | I22: '25BCJ32023JZ1MVU | J22: BOOK TRANSFER CREDIT 001MVU ORIGINATOR:LADDER CAPI | K22: =IF(ISNUMBER(SEARCH("Manual Payment - ",N22,1)),"AP",IF(ISNUMBER(SEARCH("Payment - Concur",N22,1)),"WDL",IF(ISNUMBER(SEARCH("Payroll Transfer",N22,1)),"XFR",IF(ISNUMBER(SEARCH("XFR",N22,1)),"XFR",IF(H22>0,"RCT","WDL"))))) -> RCT | L22: =VLOOKUP(D22,'Entity Code'!A:B,2,0) -> LCR3 | N22: Correction: Loan P&I Remit | O22: 2701-CAMR-000 | P22: N/A | Q22: SS&C to post
B23: 16 | C23: PNC | D23: Ladder Capital Finance | E23: 8026459916 | F23: 45973 | G23: DR | H23: -946255.03 | I23: '25BCJ32023JZ1MVU | J23: BOOK TRANSFER DEBIT 001MVU ORIGINATOR:LADDER CAPIT | K23: =IF(ISNUMBER(SEARCH("Manual Payment - ",N23,1)),"AP",IF(ISNUMBER(SEARCH("Payment - Concur",N23,1)),"WDL",IF(ISNUMBER(SEARCH("Payroll Transfer",N23,1)),"XFR",IF(ISNUMBER(SEARCH("XFR",N23,1)),"XFR",IF(H23>0,"RCT","WDL"))))) -> WDL | L23: =VLOOKUP(D23,'Entity Code'!A:B,2,0) -> LCF | N23: Correction: Loan P&I Remit | O23: 2701-CAMR-000 | P23: N/A | Q23: SS&C to post
... B25: 17 | C25: PNC | D25: LCR 3 | E25: 8026496047 | F25: 45973 | G25: DR | H25: -947000 | I25: '25BCJ32022XZ2OVR | J25: BOOK TRANSFER DEBIT 002OVR ORIGINATOR:LADDER CAPIT | K25: =IF(ISNUMBER(SEARCH("Manual Payment - ",N25,1)),"AP",IF(ISNUMBER(SEARCH("Payment - Concur",N25,1)),"WDL",IF(ISNUMBER(SEARCH("Payroll Transfer",N25,1)),"XFR",IF(ISNUMBER(SEARCH("XFR",N25,1)),"XFR",IF(H25>0,"RCT","WDL"))))) -> XFR | L25: =VLOOKUP(D25,'Entity Code'!A:B,2,0) -> LCR3 | N25: XFR from LCR3 PNC to LCFHR PNC | O25: 2701-CAMR-000 | P25: N/A | Q25: SS&C to post
B26: 18 | C26: PNC | D26: LCFH REIT | E26: 8026459924 | F26: 45973 | G26: CR | H26: 818000 | I26: '25BCL2603FL17H4H | J26: BOOK TRANSFER CREDIT 007H4H ORIGINATOR:LADDER CAPI | K26: =IF(ISNUMBER(SEARCH("Manual Payment - ",N26,1)),"AP",IF(ISNUMBER(SEARCH("Payment - Concur",N26,1)),"WDL",IF(ISNUMBER(SEARCH("Payroll Transfer",N26,1)),"XFR",IF(ISNUMBER(SEARCH("XFR",N26,1)),"XFR",IF(H26>0,"RCT","WDL"))))) -> XFR | L26: =VLOOKUP(D26,'Entity Code'!A:B,2,0) -> LCFHR | N26: XFR from LCREE PNC to LCFHR PNC | O26: =IFERROR(VLOOKUP(E27,'Bank Account'!A:B,2,FALSE),VLOOKUP(_xlfn.NUMBERVALUE(E27),'Bank Account'!A:B,2,FALSE)) -> LCREE-1065-0008-000- | P26: N/A | Q26: Ladder to post
B27: 18 | C27: PNC | D27: CRE EQUITY | E27: 8026496039 | F27: 45973 | G27: DR | H27: -818000 | I27: '25BCL2603FL17H4H | J27: BOOK TRANSFER DEBIT 007H4H ORIGINATOR:LADDER CAPIT | K27: =IF(ISNUMBER(SEARCH("Manual Payment - ",N27,1)),"AP",IF(ISNUMBER(SEARCH("Payment - Concur",N27,1)),"WDL",IF(ISNUMBER(SEARCH("Payroll Transfer",N27,1)),"XFR",IF(ISNUMBER(SEARCH("XFR",N27,1)),"XFR",IF(H27>0,"RCT","WDL"))))) -> XFR | L27: =VLOOKUP(D27,'Entity Code'!A:B,2,0) -> LCREE | N27: XFR from LCREE PNC to LCFHR PNC | O27: =IFERROR(VLOOKUP(E26,'Bank Account'!A:B,2,FALSE),VLOOKUP(_xlfn.NUMBERVALUE(E26),'Bank Account'!A:B,2,FALSE)) -> LCFHR-1065-0002-000- | P27: N/A | Q27: Ladder to post
